Workbook

Sheet README
A1: TFM - Master Revision Matrix v17
A2: Single source of truth for the jury-revision process. Updated 2-Oct-2026: the Econometric Panel Data Freeze Gate remains active. The pre-freeze audits for VIX, nominal Fed 3M Forward and nominal USD/BRL are complete. USD/BRL passed the same six-stage audit: source/ticker recorded as USDBRL Curncy; clean monthly history over the thesis window; end-of-month/last-weekday convention; exact month-by-month mapping into all 4,229 panel rows across 164 panel months; no baseline transformation or rescaling; and an economic label clarified as nominal USD/BRL in BRL per USD, where an increase denotes BRL depreciation. The original Bloomberg formula is not retained in the values-only macro workbook, so that provenance limitation remains documented. Current pre-freeze work moves to GDP YoY and then the remaining baseline explanatory variables. No final baseline, diagnostic or robustness regression should be rerun before the gate passes.
A4: Purpose and governance
A5: Purpose | B5: Use the Master Matrix as the authoritative record of every jury issue, Martin's disposition, the required evidence/change, dependencies and completion status.
A6: Workflow status | B6: WP-03 remains closed. WP-04 remains deferred only at its regression stage. The VIX, nominal Fed 3M Forward and nominal USD/BRL pre-freeze audits are complete. USD/BRL passed source/ticker -> raw series -> monthly convention -> full-sample panel match -> transformation/scaling -> economic-label review. Current Data Freeze Gate work moves to GDP YoY and then the remaining baseline regressors. If RER is ultimately substituted for NER in the final core table, RER must be audited separately before panel freeze. After every baseline explanatory variable is audited or explicitly accepted unchanged, freeze panel_main_and_robustness.xlsx once, rerun the FE-Driscoll-Kraay core table, and only then run diagnostics/robustness including WP-04 Models 5-6.
A7: Scope rule | B7: Every jury point must map to a change, diagnostic, defense answer or reasoned non-change. Not every suggested extension must be estimated.
A8: v16 update | B8: 2-Oct-2026: nominal Fed 3M Forward audit completed end-to-end. Bloomberg USSOC Curncy / PX_LAST (3M USD OIS) matched all 164 distinct panel months exactly (0 mismatches; max absolute difference 0.0). Baseline Stata uses the series directly in percentage points with no log, standardization or /100 scaling; only the separate macro-difference robustness creates D.fed_3m_forward. Thesis wording now keeps “Fed 3M Forward” as the intuitive label but defines the underlying 3M USD OIS precisely and states that it is forward-looking in economic content, not a forward-starting 3Mx3M rate. MR-09 is closed; any post-freeze raw/partial correlations and final VIX sign/H1 interpretation are tracked under MR-18/MR-19. Next pre-freeze audit: USD/BRL.
A9: v17 update | B9: 2-Oct-2026: nominal USD/BRL audit completed end-to-end. The macro workbook records USDBRL Curncy and BRL-per-USD semantics; the original Bloomberg formula/raw source layer is not retained and no second repo provenance trace was found. The thesis-window raw series contains 187 uninterrupted monthly observations from Jan-2010 to Jul-2025, with no zeros/blanks/duplicate months and every observation dated on the last weekday of the month. The econometric panel uses usd_brl with 0 blanks, one value per month, 0 missing source months and 0 mismatches across 4,229 rows / 164 panel months (Dec-2010 to Jun-2025). Baseline Stata uses the nominal spot level directly, with no log/rescaling/standardization; D.usd_brl is separate robustness only. Economic label frozen as nominal USD/BRL (BRL per USD); higher values mean BRL depreciation. Next pre-freeze audit: GDP YoY. RER remains a separate construction that must be audited before freeze if it enters the final core table.
A10: Authoritative inputs
A11: Source file / message | B11: Role | C11: Date/pages | D11: How used | E11: Current status
A12: TFM_Maestria_Economia_Siqueira_Thiago_Abril_10_2026.pdf | B12: Submitted thesis baseline | C12: 69 pages | D12: Locations, equations, tables, figures and annexes | E12: Frozen baseline
A13: Ailin - Informe Preliminar TFM_Siqueira_Thiago (2).pdf | B13: Jury report + Martin annotations | C13: 11 pages | D13: Criticisms A-01 to A-18 and annotated dispositions | E13: Integrated
A14: Maximo Sangiacomo - Evaluacion_TFM_Siqueira_Thiago (2).pdf | B14: Jury report + Martin annotations | C14: 5 pages | D14: Criticisms M-01 to M-18 and priority technical exercises | E14: Integrated - primary substantive priority
A15: Devolucion DM - Daniel Milia.pdf | B15: Third jury report | C15: 18-Sep-2026; 3 pages | D15: Criticisms D-01 to D-18 and defense guidance | E15: Integrated; director reviewed 24-Sep-2026
A16: Martin Grandes - WhatsApp audio/text | B16: Director follow-up guidance | C16: Sep-2026; latest 27-Sep-2026 | D16: SELIC, dynamics, sovereign ceiling, DK/PCSE, nominal FED3M, table design, robustness sequence, definitive Sovereign Risk (BRL) construction, common-reference two-spread specification and deadlines | E16: Integrated as MG-01 to MG-21
A17: Proceso de presentacion y evaluacion del Trabajo Final - Res.CD 1313/2023 | B17: Institutional process | C17: Sep-2023; 1 page | D17: Formal stages and generic time windows | E17: Exact project deadline still to enter
A18: Tabla para nuevas estimaciones panel-Siqueira & Grandes 25-9-2026.docx | B18: Director-provided estimation template | C18: 25-Sep-2026; 1 page | D18: Exact four-column FE-Driscoll-Kraay variable-inclusion grid and requested output statistics | E18: Integrated; two layout ambiguities flagged for confirmation
A19: Revision categories
A20: Category | B20: Definition | C20: Default implication
A21: A - Methodological issue / additional estimation | B21: Measurement, identification, data or inference concern. | C21: Change data/model and regenerate affected outputs.
A22: B - Clarification / reframing | B22: Valid criticism mainly solved through precise definitions, interpretation or wording. | C22: Rewrite after final estimates; may include a small diagnostic.
A23: C - Presentation / structure / literature / documentation | B23: Presentation, literature, reporting, provenance or reproducibility. | C23: Revise text/tables/appendix/package; not necessarily new estimation.
A24: D - Not endorsed / optional / response only | B24: Request rejected, narrowed or treated as optional/future research. | C24: No mandatory thesis change; answer in memo/defense or add only if low cost.
A26: Workbook map
A27: Dashboard | B27: Formula-driven overview of priorities, counts, current package and process status.
A28: Process & Deadlines | B28: Institutional stages, generic windows and project-specific control fields.
A29: Revision Tracker | B29: Sixteen dependency-based work packages. Update Status and Working notes.
A30: Master Matrix | B30: Thirty-four consolidated revision issues across all jurors and director guidance.
A31: Juror Log | B31: Every distinct juror criticism mapped to one or more master issues.
A32: Director Guidance | B32: Traceability for Martin's audio/text decisions, including the 25-Sep-2026 estimation plan and definitive sovereign-risk definition.
A33: Overlap Map | B33: Unified resolution of recurring issues to prevent duplicate work.
A34: Action Sequence | B34: Dependency order that minimizes rework.
A35: Estimation Plan | B35: Exact 25-Sep-2026 paper/seminar model grid, optional SELIC checks, ambiguities and delivery controls.
A36: v4 Change Log | B36: Historical changes introduced on 24-Sep-2026.
A37: v5 Change Log | B37: Exact changes introduced from Martin Grandes' 25-Sep-2026 instructions.
A38: v6 Change Log | B38: Changes introduced from Martin Grandes' 25-Sep-2026 sovereign-risk clarification and workflow handoff from WP-01 to WP-02.
... A49: v17 Change Log | B49: Changes introduced on 2-Oct-2026 after completing the six-step nominal USD/BRL audit and moving the Data Freeze Gate to GDP YoY while preserving the separate RER pre-freeze dependency.

Sheet Dashboard
A1: Revision Dashboard
A2: Formula-driven from the Master Matrix, Revision Tracker and Process & Deadlines. Updated through 2-Oct-2026: the VIX, nominal Fed 3M Forward and nominal USD/BRL pre-freeze audits are complete. USD/BRL passed all six stages: USDBRL Curncy recorded in the macro workbook; 187 uninterrupted thesis-window monthly observations; last-weekday month-end convention; exact panel mapping across 4,229 rows / 164 panel months with zero mismatches; no baseline rescaling or transformation; and BRL-per-USD economic labeling. The original Bloomberg formula is not retained in the values-only workbook and that provenance limitation is documented. Current Data Freeze Gate task is GDP YoY, followed by the remaining baseline regressors. If RER enters the final core specification, it requires its own pre-freeze audit. WP-04 regression-dependent steps and all final baseline/robustness estimation remain deferred until the final panel is frozen.
A4: Issue portfolio
A5: Metric | B5: Count | C5: Meaning | E5: Martin position | F5: Count | G5: Meaning
A6: Total master issues | B6: =COUNTA('Master Matrix'!A4:A200) | C6: Distinct consolidated issues. | E6: Agrees / strongly agrees | F6: =COUNTIF('Master Matrix'!H4:H200,E6) | G6: Explicitly endorsed.
A7: Critical priority | B7: =COUNTIF('Master Matrix'!D4:D200,"Critical") | C7: Can affect acceptance or downstream results. | E7: Partially agrees | F7: =COUNTIF('Master Matrix'!H4:H200,E7) | G7: Accepted with scope limits.
A8: Category A | B8: =COUNTIF('Master Matrix'!K4:K200,"A*") | C8: Measurement/diagnostics/estimation. | E8: Disagrees / not endorsed | F8: =COUNTIF('Master Matrix'!H4:H200,E8) | G8: Response only or future research.
A9: Category B | B9: =COUNTIF('Master Matrix'!K4:K200,"B*") | C9: Clarification/reframing. | E9: No explicit position | F9: =COUNTIF('Master Matrix'!H4:H200,E9) | G9: No direct disposition.
A10: Category C | B10: =COUNTIF('Master Matrix'!K4:K200,"C*") | C10: Presentation/literature/documentation.
A11: Category D | B11: =COUNTIF('Master Matrix'!K4:K200,"D*") | C11: Optional or non-endorsed.
A12: Changes required | B12: =COUNTIF('Master Matrix'!Q4:Q200,"Yes*") | C12: Mandatory/minimum-scope changes.
A13: Done | B13: =COUNTIF('Master Matrix'!R4:R200,"Done") | C13: Completed master issues.
A15: Critical workstreams - recommended order
A16: Order | B16: Workstream | C16: Master issues | D16: Why
A17: 1 | B17: Correct spread construction - measurement audit closed | C17: MR-03 | D17: Dependent-variable measurement audit completed; downstream regressions remain to be regenerated.
A18: 2 | B18: Sovereign Risk (BRL) construction and terminology - closed | C18: MR-01 / MR-02 | D18: Closed 29-Sep: 582/582 LTN+NTN-F sovereign observations validated against same-date exact-tenor DI; geometric spreads and exact-node handling verified; pytest 5/5; commit b551414 pushed. Thesis now uses sovereign_spread_brl, removes CDS language, and distinguishes the nominal sovereign DI benchmark from the IPCA-real corporate benchmark.
A19: 3 | B19: Issue-size identification - closed (WP-03) | C19: MR-14 | D19: Closed 30-Sep: amount_issued_to_bs_tot_asset reconstructed for 4,229/4,229 observations; 98/103 bonds (95.15%) vary within bond; variable retained in bond FE; ‰ units and relative-size interpretation documented; one-quarter-lagged denominator reserved as robustness.
A20: 4 | B20: Baseline explanatory-variable audits / Data Freeze Gate - CURRENT | C20: MR-09 closed pre-freeze; remaining baseline regressors | D20: VIX, Fed 3M Forward and nominal USD/BRL pre-freeze audits passed. USD/BRL: source label/ticker = USDBRL Curncy; 187 uninterrupted monthly source observations from Jan-2010 to Jul-2025; all dates follow last-weekday month-end convention; 4,229 panel rows / 164 distinct panel months map exactly with 0 blanks, 0 conflicting within-month values, 0 missing source months and 0 mismatches; baseline usd_brl enters directly in BRL per USD levels with no log/rescaling/standardization; D.usd_brl is robustness only; higher USD/BRL denotes BRL depreciation. CURRENT: audit GDP YoY using the same six-step sequence, then continue through the remaining baseline regressors. RER is not validated by the NER audit and must be audited separately before freeze if selected for the final core table. Do not rerun final baseline/robustness regressions before the freeze gate passes.
A21: 5 | B21: Single DK results table and inference reset - AFTER DATA FREEZE | C21: MR-16 / MR-17 / MR-18 / MR-24 | D21: Only after the final panel is frozen: rerun the four-model FE-Driscoll-Kraay baseline table using the finalized regressor definitions, then diagnostics and targeted robustness checks including the referee-only Brazil 3M DI exercise.
A22: 6 | B22: Ratings/sector heterogeneity | C22: MR-06 / MR-07 | D22: Convert ex-post explanations into bounded tests.
A23: 7 | B23: Hypothesis-result/sign rewrite | C23: MR-19 / MR-30 / MR-31 / MR-32 | D23: Daniel's valid contribution is primarily expositional and follows empirical freeze.
A24: 8 | B24: Replication and resubmission | C24: MR-27 | D24: Required alongside the revised thesis.
A25: Live revision status
A26: Current package | B26: =IFERROR(INDEX('Revision Tracker'!B12:B100,MATCH("In progress",'Revision Tracker'!J12:J100,0)),"")
A27: Current task | B27: =IFERROR(INDEX('Revision Tracker'!E12:E100,MATCH("In progress",'Revision Tracker'!J12:J100,0)),"")
A28: Completed packages | B28: =COUNTIF('Revision Tracker'!J12:J100,"Done") | C28: of 16
A29: Overall progress | B29: =B28/16
A30: Current gate | B30: =IFERROR(INDEX('Revision Tracker'!K12:K100,MATCH("In progress",'Revision Tracker'!J12:J100,0)),"")
A32: Institutional process status
A33: Third report | B33: ='Process & Deadlines'!B5
A34: Daniel resolution | B34: ='Process & Deadlines'!B6
A35: Director review | B35: ='Process & Deadlines'!B7
A36: Current branch | B36: ='Process & Deadlines'!B8
A37: Official due date | B37: ='Process & Deadlines'!B9
A38: Days remaining | B38: ='Process & Deadlines'!B10
A39: Next formal step | B39: ='Process & Deadlines'!B11
A40: Seminar table target | B40: ='Process & Deadlines'!B13

Sheet Process & Deadlines
A1: Institutional Process & Deadlines
A2: Official generic time windows plus project-specific controls. Enter the exact official resubmission deadline when confirmed.
A4: Current project control
A5: Third jury report received | B5: Yes - Daniel Milia report dated 18-Sep-2026
A6: Daniel formal resolution | B6: Pasa a Defensa (favorable)
A7: Director review of Daniel | B7: Completed 24-Sep-2026 - less substantive; selective exposition/diagnostics/bibliography changes
A8: Current formal branch | B8: Awaiting official confirmation
A9: Official resubmission deadline
A10: Days remaining | B10: =IF(B9="","",B9-TODAY())
A11: Next formal step | B11: Confirm Ailin and Maximo formal resolutions, exact due date and whether a revised filing is formally required.
A12: Control note | B12: The user reports that a deadline exists, but the exact date is not in the process sheet.
A13: Paper/seminar table target | B13: 30-Sep-2026 - one consolidated FE-Driscoll-Kraay table for Martin (core four models; SELIC 3M Forward only as optional referee diagnostic)
A14: Official process and generic time windows
A15: Step | B15: Process stage | C15: Trigger | D15: Official time limit | E15: Current relevance | F15: Owner | G15: Status | H15: Evidence / next action
A16: 1 | B16: PTFM evaluation | C16: Formal receipt of project proposal | D16: 30 days | E16: Historical - not current | F16: Academic authority | G16: Not current | H16: Included for completeness.
A17: 2 | B17: PTFM correction, if required | C17: Authority requests project corrections | D17: 1 to 3 months | E17: Historical - not current | F17: Student + director | G17: Not current | H17: Not the current thesis-evaluation branch.
A18: 3 | B18: TFM review / jury convocation | C18: Formal receipt of TFM | D18: 45 days | E18: Completed | F18: Academic authority | G18: Completed | H18: The thesis was sent to three jurors.
A19: 4 | B19: Preliminary individual reports | C19: Jurors receive the TFM | D19: 45 days | E19: Completed - all three reports received | F19: Each juror | G19: Completed | H19: Daniel is the third report; dated 18-Sep-2026 and favorable.
A20: 5 | B20: Revision and resubmission, if formally required | C20: One or more resolutions require revision | D20: 1 to 4 months, set by authority | E20: Current only if official branch is revision | F20: Student + director | G20: Pending confirmation | H20: Enter the exact date in C9.
A21: 6 | B21: Second preliminary reports | C21: Revised TFM is formally resubmitted | D21: 45 days | E21: Contingent on revision branch | F21: Each juror | G21: Not started | H21: Jurors decide whether the revised version can pass to defense.
A22: 7 | B22: Oral and public defense | C22: Three favorable reports received | D22: Within 45 days | E22: Current if all three resolutions are favorable | F22: Program direction + student + jurors | G22: Pending confirmation | H22: Confirm Ailin/Maximo resolutions and coordinate defense date.
A24: Source: Proceso de presentacion y evaluacion del Trabajo Final de Maestria o Especializacion, Res.CD No. 1313/23 (Sep-2023). Daniel status: Devolucion DM - Daniel Milia, 18-Sep-2026. Director reviews: WhatsApp, 24-27 Sep-2026, including definitive Sovereign Risk (BRL), preferred common-reference two-spread specification and referee-only SELIC clarifications. Estimation template: Tabla para nuevas estimaciones panel, 25-Sep-2026.

Sheet Revision Tracker
A1: TFM Jury Revision Tracker
A2: Sixteen dependency-based work packages consolidate 34 master issues. Updated 2-Oct-2026: the Econometric Panel Data Freeze Gate remains active. WP-06 has completed the VIX, Fed 3M Forward and nominal USD/BRL pre-freeze audits. USD/BRL passed all six stages with exact 4,229-row / 164-month panel mapping, level scaling in BRL per USD and clarified depreciation semantics. The original Bloomberg formula is not retained in the values-only workbook, which is documented as a provenance limitation. Current Data Freeze Gate task: audit GDP YoY, then the remaining baseline regressors. If RER is used in the final core table, it must be audited separately before freeze. No final baseline/robustness estimation should run before the gate passes.
A4: Current package | B4: =IFERROR(INDEX(B12:B100,MATCH("In progress",J12:J100,0)),"")
A5: Current task | B5: =IFERROR(INDEX(E12:E100,MATCH("In progress",J12:J100,0)),"")
A6: Completed packages | B6: =COUNTIF(J12:J100,"Done")
A7: Overall progress | B7: =B6/16
A8: Current status | B8: =IFERROR(INDEX(J12:J100,MATCH("In progress",J12:J100,0)),"")
A9: Gate before moving on | B9: =IFERROR(INDEX(K12:K100,MATCH("In progress",J12:J100,0)),"")
A11: Seq. | B11: WP ID | C11: Phase | D11: Master issue IDs | E11: Work package | F11: Why this is sequenced here | G11: Thesis location(s) | H11: Concrete deliverable | I11: Dependencies | J11: Status | K11: Gate / acceptance criterion | L11: Working notes
A12: 1 | B12: WP-01 | C12: Measurement | D12: MR-03 | E12: Recalculate the corporate spread using consistent compounding | F12: The dependent variable feeds every regression and conclusion. | G12: Sec. 2.2; Sec. 4.3; Sec. 4.5.2; Annex 8.7; all results | H12: Audited conventions; corrected spread series; old-vs-new comparison; unit tests. | I12: Submitted code/data and curve audit | J12: Done | K12: Approve formula, units, day-count, compounding and field types; benchmark/corporate inputs pass hand checks. | L12: Completed 25-Sep-2026: corrected the 2012-2013 NTN-B field contamination, revalidated the relevant government-curve inputs, checked corporate bond price/yield fields, and closed the corporate-spread measurement audit. Downstream estimates will be regenerated after WP-02.
A13: 2 | B13: WP-02 | C13: Measurement | D13: MR-01, MR-02 | E13: Verify Sovereign Risk (BRL) construction, common-reference logic and terminology | F13: Martin confirmed the intended sovereign regressor and preferred two-spread transmission specification. The nominal sovereign implementation was validated end-to-end: LTN and NTN-F government yields are compared with the same-date DI reference curve at exact BUS/252 residual tenor. Thesis terminology and documentation were subsequently aligned, including the distinction between the nominal sovereign DI benchmark and the IPCA-real corporate benchmark. | G13: Secs. 2.2, 4.3, 4.5.1-4.5.3, 5.2.3; Annex 8.3 and 8.8-8.9 | H13: COMPLETED: code/formula audit; 252 LTN + 330 NTN-F maturity-matched sovereign spreads; same-date exact-tenor DI benchmark; geometric annual-effective spread; exact-node interpolation guard; regression tests; variable rename to sovereign_spread_brl; removal of synthetic-CDS wording; explicit methodology/appendix formula; literature/two-spread rationale; corporate-IPCA versus nominal-DI indexation clarification; affected figures/tables relabeled. | I13: WP-01 | J13: Done | K13: Corporate Spread is documented against the matched IPCA-real reference curve and sovereign_spread_brl against the matched nominal DI reference curve, each at the appropriate date/tenor/indexation. The thesis explains why the two spreads are modeled separately rather than collapsed into a direct corporate-minus-sovereign spread; CDS terminology is removed. Any final search for unintended USD CDS usage is a pre-estimation integrity check and does not reopen WP-02. | L13: Closed 29-Sep-2026. Nominal Sovereign Risk (BRL) implementation validated on 582/582 observations with 0 missing benchmarks and max absolute benchmark difference 5.33e-13 bp; spread arithmetic independently verified; BZDIOVRA cash + liquid DI futures + Pre x DI swaps; exact BUS/252 tenor; pytest 5/5; commit b551414 pushed. Thesis edits confirmed complete: sovereign_spread_brl adopted, synthetic-CDS wording removed, explicit construction added in methodology/annex, corporate IPCA-real versus nominal sovereign DI benchmark distinction documented, and relevant diagrams/table labels updated. Final coefficients remain provisional until all explanatory-variable audits are complete.
A14: 3 | B14: WP-03 | C14: Data audit | D14: MR-14 | E14: Audit amount_issued_to_bs_tot_asset and within-bond variation | F14: A time-invariant issue-size variable cannot be estimated in bond FE. | G14: Table 1 H6; Secs. 4.5.3 and 4.7; Table 3; Sec. 5.2.4; Annex 8.6.2 and Table 7; Figure 3 | H14: COMPLETED: raw-field trace from AMT_ISSUED and issuer BS_TOT_ASSET; full-panel reconstruction; within-bond variation diagnostics; timing/scaling audit; retain/rename decision; one-quarter-lagged denominator robustness construction; thesis wording/table/figure alignment. | I14: Raw panel and construction code | J14: Done | K14: PASSED: 4,229/4,229 panel observations reconstructed from raw sources; 98/103 bonds (95.15%) have within-bond variation; the regressor is identified in bond FE; ‰ units, quarterly timing and interpretation are documented; lagged-quarter timing robustness is available. | L14: Closed 30-Sep-2026. The jury concern applies to AMT_ISSUED in levels, but the estimated variable is AMT_ISSUED / BS_TOT_ASSET. AMT_ISSUED is fixed by bond; quarterly issuer assets generate within-bond variation. Raw-source reconstruction matched all 4,229 panel observations essentially exactly. 98/103 bonds vary within bond; five very-short-history bonds do not. The stored scale is per-mille (‰). A one-quarter-lagged BS_TOT_ASSET version retains 4,223/4,229 observations, correlates 0.9918 with the original, and preserves 98/103 varying bonds; its six missing observations are limited to two Serena bonds in 2022Q1 due to unavailable 2021Q4 assets. Decision: retain the existing contemporaneous relative-size variable in the main specification, reserve the lagged denominator as robustness, and interpret the coefficient as relative issue size versus issuer scale—not as a change in original amount issued. Thesis edits were completed across H6, methodology/FE identification, results, conclusions, Tables 3/7, Figure 3 and Annex 8.6.2.
A15: 4 | B15: WP-04 | C15: Variables | D15: MR-04 | E15: Clarify SELIC baseline non-inclusion and run referee-only SELIC 3M Forward check(s) | F15: SELIC anchors the short end of the local reference curve and its influence propagates through the curve; Martin's 3M Forward SELIC exercise is only a low-cost referee diagnostic, not a competing baseline specification. | G15: Secs. 3.1-3.3, 4.3, 4.5.3, 5.2-5.4, 6.1 | H15: Dual-rationale note; correlations/VIF; optional SELIC 3M Forward check(s) under the specified exclusions; label the exercise referee-only and decide whether it is worth reporting only after seeing its informational value. | I15: WP-01; final curve definitions | J15: Deferred | K15: Baseline omission is explicit; the local-curve embedding of SELIC is explained; any SELIC 3M Forward check follows the required exclusions, is labeled referee-only and does not replace the preferred model. | L15: 1-Oct-2026 sequencing update: thesis Section 4.5.3 already justifies baseline SELIC non-inclusion, and the referee-only Brazil 3M DI proxy (YCSW0089 Index 3M) has been validated/downloaded for Dec-2010 to Dec-2025 with a reproducible BQNT notebook and README. Data preparation is complete. Regression-dependent closure is intentionally deferred under the Econometric Panel Data Freeze Gate: do not merge this robustness-only series into the authoritative panel or run Models 5-6 until the remaining baseline explanatory variables are audited/accepted unchanged and the final panel is frozen. After the core baseline rerun, review correlations/VIF/incremental information and run Model 5 (retain nominal FED3M) and Model 6 (omit FED3M), both omitting FX and Sovereign Risk (BRL).
A16: 5 | B16: WP-05 | C16: Heterogeneity | D16: MR-06, MR-07 | E16: Test sovereign transmission by ratings and sector groups | F16: Post-hoc explanations must be converted into bounded tests. | G16: Secs. 3.1, 3.3.2, 4.1, 4.3, 5.2.3, 6.1, 6.3 | H16: Rating tiers; sector groups; interactions; equality tests; group counts; optional issuer/bond slopes where powered. | I16: WP-02; rating rules | J16: Not started | K16: Homogeneity is tested with adequate-cell groups; small-T issuer/bond estimates are labeled imprecise.
A17: 6 | B17: WP-06 | C17: Data Freeze Gate | D17: MR-09 closed; remaining baseline regressors | E17: Complete explanatory-variable Data Freeze Gate (VIX + Fed + USD/BRL passed; GDP YoY current) | F17: Daniel asks for a direct H1-result link and better explanation of the negative sign. | G17: Secs. 3.1, 3.3.1, 4.1, 4.5.3, 5.2.1, 6.1 | H17: VIX PRE-FREEZE COMPLETE. FED 3M FORWARD SIX-STEP AUDIT COMPLETE. NOMINAL USD/BRL SIX-STEP AUDIT COMPLETE: macro workbook records USDBRL Curncy and BRL-per-USD semantics; original Bloomberg formula/raw-source layer is not retained and no duplicate repo provenance trace was found; 187 uninterrupted monthly observations Jan-2010 to Jul-2025 with no zeros/blanks/duplicate months; all observations use the last weekday of the month; panel variable usd_brl has 0 blanks, one value per month and exact source matching across 4,229 rows / 164 panel months; baseline enters in nominal BRL-per-USD levels with no log/rescaling/standardization; D.usd_brl is robustness only; higher values mean BRL depreciation. CURRENT: audit GDP YoY through source/ticker -> raw series -> monthly convention -> panel match -> transformation/scaling -> economic label, then continue through the remaining baseline regressors. If RER replaces NER in the final core table, RER requires a separate pre-freeze audit. POST-FREEZE: correlations/sequential DK and final counterintuitive-sign interpretation are handled under MR-18/MR-19. | I17: VIX, Fed and nominal USD/BRL fully validated; GDP YoY is the next baseline audit; final diagnostics/estimation blocked by Data Freeze Gate | J17: In progress | K17: Global-factor block and nominal USD/BRL pre-freeze audit PASSED. Continue until every remaining baseline explanatory variable is audited or explicitly accepted unchanged; if RER is selected for the final core table, audit RER separately before freeze. Then rebuild/freeze panel_main_and_robustness.xlsx as the authoritative input. Post-freeze correlations and final VIX sign/H1 interpretation remain under MR-18/MR-19. | L17: 2-Oct-2026 USD/BRL audit closure: macro workbook column D identifies “USDBRL Spot Exchange Rate - Price of 1 USD in BRL” / USDBRL Curncy. Upstream Bloomberg formula/raw source is not retained in the values-only workbook and repo-wide search found no second ticker trace, so this provenance limitation is explicit. Thesis-window source series contains 187 monthly observations from Jan-2010 through Jul-2025, no zeros/blanks/duplicate months, range 1.5493-6.1736, and every date is the last weekday of the month. Panel ts.usd_brl contains 0 blanks across 4,229 rows; 164 unique panel months from Dec-2010 through Jun-2025; no within-month conflicts; no source-month gaps; and 0 month-by-month mismatches. Stata uses usd_brl directly in levels; no log, /100, *100, z-score or standardization is applied. D_usd_brl = D.usd_brl exists only in the macro-differences robustness. Economic label: nominal USD/BRL (BRL per USD), month-end spot; an increase denotes BRL depreciation. Next Data Freeze Gate audit: GDP YoY. Separate caution: if RER replaces NER in the final core specification, the RER construction must be audited before panel freeze.
A18: 7 | B18: WP-07 | C18: Estimator | D18: MR-16, MR-17, MR-23 | E18: Reset inference to one bond-FE Driscoll-Kraay table; remove plain FE and PCSE | F18: Martin confirmed the PCSE rationale and requested no separate conventional-FE or PCSE columns. | G18: Secs. 4.2, 4.6, 4.8, 5.1-5.3; Tables 2-3; Annex 8.10-8.11 | H18: Audited logs; diagnostics; final DK setup/lag; precise PCSE exclusion note; one-table layout. | I18: WP-01 to WP-06 final variable definitions | J18: Not started | K18: All main significance uses one DK setup; diagnostics are shown; the core table has no separate plain-FE or PCSE columns. | L18: PCSE rationale confirmed 25-Sep-2026: imbalance and limited common time overlap weaken covariance estimation.
A19: 8 | B19: WP-08 | C19: Estimator | D19: MR-18 | E19: Produce the single four-model DK table and targeted robustness checks | F19: Immediate paper/seminar deliverable requested by Martin for 30-Sep-2026. | G19: Secs. 4.6-4.8, 5.1-5.4; Annex 8.11 | H19: Four core FE-DK columns using nominal FED3M; sovereign/local-macro and NER/RER variants; within R2/rho; referee-only optional SELIC Models 5-6; correlation matrix. | I19: WP-01, WP-02, WP-04, WP-07; confirm template ambiguities | J19: Not started | K19: Core grid matches the director template; old FED3M Real is excluded; NER/RER and stacking ambiguities are confirmed; any SELIC columns are separate, referee-only diagnostics. | L19: Target 30-Sep-2026. Attached table marks both NER and RER in Model 1 and keeps firm/bond controls in all columns; confirm before final code. 27-Sep: SELIC 3M Forward is only a referee check, not a baseline extension.
A20: 9 | B20: WP-09 | C20: Robustness | D20: MR-25 | E20: Address stale OTC pricing as a competing explanation | F20: Lagged quotes may mechanically create anomalous signs. | G20: Secs. 2.1.1, 4.5.2, 4.6, 5.2.1, 5.2.3, 6.1-6.3; Annex 8.2 and 8.5 | H20: Literature/limitation plus one feasible diagnostic or documented data limit. | I20: WP-01; source fields; WP-07 | J20: Not started | K20: Flight-to-quality is not stated as fact before stale pricing is considered.
A21: 10 | B21: WP-10 | C21: Identification | D21: MR-13, MR-15 | E21: Clarify identifying variation and panel imbalance | F21: Common regressors vary monthly; bond histories are unequal. | G21: Secs. 4.2-4.4, 4.7-4.8, 5.1, 5.3-5.4, 6.1; Annex 8.10 | H21: Variation-level table and T_i/coverage profile. | I21: WP-03 and WP-07 | J21: Not started | K21: Months, bonds, issuers, T_i distribution and FE limits are reported.
A22: 11 | B22: WP-11 | C22: Text/literature | D22: MR-11, MR-12, MR-21, MR-32, MR-34 | E22: Correct language and make bounded literature/theory updates | F22: Daniel's literature comments are secondary and should support, not expand, the empirical design. | G22: Introduction; Secs. 3-4; references; defense literature map | H22: Non-causal wording; citation corrections; construct-proxy table; closest-study comparison. | I22: Final empirical framing from WP-04, WP-08, WP-09 | J22: Not started | K22: Every citation supports the statement; the gap/proxies are demonstrated without theoretical overhaul.
A23: 12 | B23: WP-12 | C23: Reporting | D23: MR-22, MR-24 | E23: Build the single consolidated regression table and run table-to-text checks | F23: Final DK evidence must be readable and auditable. | G23: Table 3; Sec. 5.2.2; Annex Table 7 | H23: One FE-DK table with SE, N, panel dimensions, within R2, rho, DK lag/FE metadata and diagnostics panel. | I23: WP-08 final estimates | J23: Not started | K23: The requested four core columns and any optional SELIC columns are readable, auditable and matched exactly by the prose. | L23: Table design source: Martin's 25-Sep-2026 template.
A24: 13 | B24: WP-13 | C24: Interpretation | D24: MR-19, MR-26 | E24: Rewrite results and explain counterintuitive signs | F24: Daniel's central contribution is better H-result linkage; Brazil-specific mechanisms must be separated from evidence. | G24: Secs. 5.2-5.4 and 6.1-6.3 | H24: Robust/partial/null/unresolved hierarchy; H-result map; Brazil-specific mechanisms. | I24: WP-02, WP-04, WP-05, WP-08, WP-09, WP-12 | J24: Not started | K24: Every hypothesis and sign is tied to a final table or labeled as a mechanism/limitation.
A25: 14 | B25: WP-14 | C25: Narrative | D25: MR-30, MR-31, MR-32, MR-33 | E25: Rewrite gap, contribution, abstract/conclusions and final copy-edit | F25: Do this only after the empirical freeze; Daniel is treated selectively as exposition. | G25: Resumen/Abstract; Introduction; Secs. 5.4 and 6; entire-thesis QA | H25: Closest-study contribution; one central question; hypothesis scorecard; final language consistency. | I25: WP-13 | J25: Not started | K25: Question, contribution, tables and conclusions are consistent and appropriately bounded.
A26: 15 | B26: WP-15 | C26: Reproducibility | D26: MR-27, MR-28 | E26: Complete replication package and data provenance | F26: Ailin requests a runnable pipeline and Martin agrees. | G26: Secs. 4.4-4.5; Annex 8.1-8.14; source notes | H26: README, environment, scripts, queries, dates, hashes, consolidation rules, curve settings and clean-run evidence. | I26: All final code/outputs | J26: Not started | K26: A clean run regenerates every permitted output and provenance is complete.
A27: 16 | B27: WP-16 | C27: Resubmission | D27: MR-05, MR-08, MR-10, MR-20, MR-29; synthesis MR-30/31/32 | E27: Prepare response memo, defense and Bordeaux/Geneva materials | F27: All comments must receive a change, diagnostic, answer or reasoned non-change. | G27: Response memo; future research; defense/seminar deck; deadline checklist | H27: Issue-by-issue memo; final single DK seminar table; diagnostics; scoped non-changes; confirmed deadlines; concise Bordeaux/Geneva deck. | I27: WP-01 to WP-15 | J27: Not started | K27: Every observation maps to evidence or a reasoned non-change; seminar materials use the agreed table; deadlines and formal branch are tracked. | L27: Near-term table target recorded as 30-Sep-2026.

Sheet Master Matrix
A1: Master Revision Matrix
A2: One row per distinct issue across all three jurors. Overlaps are consolidated so the same problem is solved once. Updated through 2-Oct-2026: WP-03/MR-14 is closed; MR-04/WP-04 regression work remains deferred under the Data Freeze Gate; MR-09 is closed as a VIX/global-proxy data-definition issue; the companion Fed 3M Forward and nominal USD/BRL six-step audits are also complete. Current pre-freeze work moves to GDP YoY and the remaining baseline regressors. If RER is selected for the final core table, it must be audited separately before freeze. Post-freeze correlations and final counterintuitive-sign interpretation remain under MR-18/MR-19.
A3: ID | B3: Source IDs | C3: Overlap group | D3: Priority | E3: Juror(s) | F3: Consolidated juror criticism | G3: Report location | H3: Martin position | I3: Martin annotation / evidence | J3: My diagnosis | K3: Revision category | L3: Thesis location | M3: Required action | N3: Estimation / work type | O3: Dependencies | P3: Acceptance criterion | Q3: Change required? | R3: Status | S3: Working notes
A4: MR-01 | B4: A-03, A-10, A-13; M-04, M-17, M-18; D-10, D-17 | C4: OG-01 | D4: Critical | E4: Ailin + Maximo + Daniel | F4: The sovereign-risk regressor and the dependent corporate spread share the IPCA benchmark. The jury asks whether this creates mechanical covariance and how the negative coefficient should be interpreted. | G4: Ailin pp. 2, 6-7 and M1; Maximo p. 2 sec. 1.2 and pp. 4-5; Daniel pp. 2-3 | H4: Agrees / strongly agrees | I4: 24-Sep-2026: Martin identifies this as the main priority and frames corporate excess/shortfall relative to the sovereign through the sovereign-ceiling hypothesis. 25-Sep: the sovereign regressor is a local BRL sovereign spread, government YTM minus the matched local risk-free/reference yield, not a CDS. 27-Sep: USD CDS 5Y was never part of the economic model. Corporate Spread and Sovereign Risk (BRL) should remain separate spreads over the same local reference curve so the model estimates the response of corporate spread to sovereign risk; a direct corporate-minus-sovereign spread is a related alternative, not the preferred econometric specification. | J4: Resolved. The jurors' shared-benchmark/mechanical-covariance concern was separated from the actual final implementation. Corporate spreads are measured against an IPCA-real reference curve, while sovereign_spread_brl uses nominal LTN/NTN-F minus the DI reference curve. The thesis now states that each spread is matched to its own instrument/indexation benchmark and explains why they remain separate variables in the sovereign-transmission regression. | K4: A - Methodological issue / additional estimation | L4: Sec. 2.2; Sec. 4.3; Sec. 4.5.1-4.5.3; Sec. 5.2.3; Annex 8.3 and 8.8-8.9 | M4: Completed: audit/document both formulas and tenor matching; distinguish the IPCA-real corporate benchmark from the nominal DI sovereign benchmark; explain the preferred two-spread transmission specification and the direct corporate-minus-sovereign alternative; remove synthetic-CDS terminology and align thesis figures/tables/appendix. Final model-panel integrity checks are deferred to the pre-estimation gate. | N4: Code/formula audit + terminology correction + re-estimation if implementation changes | O4: MR-03 measurement audit; local curve inputs; government-bond matching | P4: The thesis and code use explicit Corporate Spread and sovereign_spread_brl constructions with date/tenor/indexation matching appropriate to each instrument. The shared-benchmark concern is addressed without falsely claiming an identical curve; the two-spread specification is justified; no CDS label or pure-default interpretation remains. Final estimates will be refreshed only after the remaining regressor audits. | Q4: Yes | R4: Done | S4: Closed 29-Sep-2026. Sovereign code audit: 252 LTN + 330 NTN-F = 582 observations; 582/582 DI benchmarks reproduced; 0 missing; max abs diff 5.33e-13 bp; geometric spread verified; exact-node guard; pytest 5/5; commit b551414 pushed. Thesis edits completed across Resumen/Abstract, sovereign-risk literature/methodology, results terminology, annex construction, and Figures 3/4. Corporate IPCA-real versus nominal sovereign DI benchmark distinction is now explicit.
A5: MR-02 | B5: A-03, A-13; M-04 | C5: OG-01 | D5: High | E5: Ailin + Maximo | F5: The labels synthetic CDS BRL and risk-free real curve overstate what is measured when the benchmark includes sovereign NTN-B yields and market-basis components. | G5: Ailin pp. 2, 6-7; Maximo p. 2 sec. 1.2 | H5: Agrees / strongly agrees | I5: 25-Sep-2026: Martin explicitly rejects the "synthetic CDS" label; there is no credit default swap in the construction. 27-Sep: he further clarifies that USD CDS 5Y was never part of the economic model and should not be introduced. The intended object remains a maturity-matched local-currency sovereign spread: government-bond yield minus the relevant futures/swap/interpolated local reference curve yield. | J5: Resolved. The final variable is sovereign_spread_brl / local-currency sovereign spread, not a CDS. The nominal DI reference curve and exact-tenor matching are documented, and language that could imply a pure default-protection measure was removed. The corporate IPCA-real benchmark is described separately so the indexation treatment is transparent. | K5: B - Clarification / reframing | L5: Resumen/Abstract; Sec. 2.2; Sec. 4.5.1-4.5.3; Sec. 5.2.3; Annex 8.3 and 8.8-8.9; Glossary | M5: Completed: rename the variable consistently as sovereign_spread_brl / sovereign risk in local currency; define it algebraically as government YTM versus the matched nominal DI reference yield; explain the DI curve construction and tenor matching; remove synthetic CDS BRL from thesis text, diagrams and table labels. Keep the director-confirmed USD CDS 5Y non-use as a final pre-estimation code-integrity check only. | N5: Terminology correction + code/formula verification | O5: MR-01 measurement decision | P5: One name and one formula are used throughout; the variable is never described as a CDS; the nominal DI reference curve and maturity matching are transparent; the implementation reproduces the documented construction; the IPCA-real corporate benchmark is separately identified. No USD CDS variable is to be introduced into the model. | Q5: Yes | R5: Done | S5: Closed 29-Sep-2026 after thesis terminology and documentation cleanup. sovereign_spread_brl replaces synthetic_cds_brl; p.26-27 and Annex 8.8 construction rewritten; Resumen/Abstract, results text, tables/diagrams and Mermaid source relabeled; DI curve description updated to dynamic cash + liquid futures + Pre x DI swaps and framed as a local nominal market reference rather than an absolute risk-free rate.
A6: MR-03 | B6: A-05 | C6: OG-02 | D6: Critical | E6: Ailin | F6: Spreads were computed by linear subtraction of yields despite compounding conventions. Ailin requests a geometric or log-consistent spread on matched curves. | G6: Ailin p. 2 sec. 2(c), p. 7, M2 | H6: Agrees / strongly agrees | I6: Martin explicitly instructed a recalculation. This remains WP-01 and precedes every re-estimation. | J6: Genuine dependent-variable measurement correction. Exact units, signs, field types and compounding must be audited before coding. | K6: A - Methodological issue / additional estimation | L6: Sec. 2.2 eq. (1); Sec. 4.3; Sec. 4.5.2 eq. (3); Annex 8.7; all empirical outputs | M6: Recompute each bond-month spread with consistent compounding, matched tenor and consistent YTM/zero conventions. Unit-test hand cases, compare old versus new series, and regenerate all estimates, tables and conclusions. | N6: Dependent-variable rebuild + full re-estimation | O6: Curve and yield convention audit | P6: Formula, units, day count and compounding are documented; old/new summary statistics and hand checks reproduce; all downstream outputs use the corrected series. | Q6: Yes | R6: In progress | S6: Corporate-spread measurement stage completed 25-Sep-2026: NTN-B 2012-2013 field contamination corrected and corporate yield inputs rechecked. MR-03 remains open only because downstream estimates/tables still need regeneration with the corrected series.
A7: MR-04 | B7: A-02, A-04, A-14 | C7: OG-02 | D7: High | E7: Ailin | F7: Subtracting the real curve implicitly imposes unit exposure to the curve factor; the level/slope of Brazilian real rates may be omitted. | G7: Ailin p. 2 sec. 2(b), pp. 5-7, M3 | H7: Partially agrees | I7: 25-Sep-2026: baseline SELIC non-inclusion has two reasons: UIP implies overlap with FED3M plus expected BRL depreciation, and SELIC anchors the short end of the local reference curve. 27-Sep: Martin reinforces that the local curve already embeds the SELIC effect and that the SELIC 3M Forward exercise is only for the referee; after seeing the result, decide whether it adds enough information to show or publish. | J7: Baseline omission is economically defensible and the referee-only domestic short-rate proxy is now fully sourced/documented. Because Models 5-6 depend on the final common regressor set, the regression stage is intentionally parked until all baseline explanatory variables are audited and the authoritative panel is frozen. | K7: A - Methodological issue / additional estimation | L7: Secs. 3.1-3.3; Sec. 4.3; Sec. 4.5.3; Sec. 5.2-5.4; Sec. 6.1 | M7: Explain the dual rationale for excluding SELIC from the baseline, including its role at the short end of the local reference curve. Report common-block correlations/VIF. If feasible, run the scoped SELIC 3M Forward referee checks: (i) omit FX and sovereign spread; (ii) also omit FED3M Forward. Label them referee-only and decide whether to retain them in the paper only if informative. | N7: Clarification + diagnostics + optional two-column robustness | O7: MR-03; final curve definitions | P7: The baseline SELIC omission is explicit and tied to both UIP overlap and the curve construction; any SELIC 3M Forward columns obey the required exclusions, are labeled referee-only, and are not treated as a baseline replacement. | Q7: Yes - clarification / minimum scope | R7: Deferred | S7: 1-Oct-2026: thesis rationale and Brazil 3M DI data package are complete. Regression-dependent closure is deferred, not dropped. After the Data Freeze Gate: merge/validate brazil_3m_di as a robustness-only series, review correlations/VIF, and run the two scoped referee diagnostics under Martin's exclusions.
A8: MR-05 | B8: A-02, A-04, A-14 | C8: OG-02 | D8: Low | E8: Ailin | F8: Ailin proposes a full two-step Fama-MacBeth factor model with bond-specific betas to the real curve. | G8: Ailin pp. 5-7, M3 | H8: Disagrees / not endorsed | I8: Martin does not endorse a full theoretical redesign; treat it as a future extension. Current work should use bounded grouped heterogeneity tests. | J8: Interesting but disproportionate as a mandatory revision. | K8: D - Not endorsed / optional / response only | L8: Potentially Sec. 4.3-4.8 and Annex A | M8: Do not redesign the TFM around Fama-MacBeth. Mention it as future research and address the core concern through MR-04 and MR-06. | N8: No mandatory estimation | O8: MR-04 and MR-06 | P8: Response memo explains the scoped remedy and future extension. | Q8: No - response only | R8: Not started
A9: MR-06 | B9: A-07; M-01, M-16, M-17; D-10, D-18 | C9: OG-03 | D9: Critical | E9: Ailin + Maximo + Daniel | F9: The theory allows heterogeneous sovereign transmission, but the submitted model estimates one average coefficient and then invokes heterogeneous issuers to explain the sign. | G9: Ailin pp. 2, 9-10; Maximo pp. 1, 4; Daniel pp. 2-3 | H9: Agrees / strongly agrees | I9: Test heterogeneity parsimoniously. Martin later clarified that issuer-level and, where powered, bond-level estimates may be informative, but small-T slopes can be imprecise. Sector/industry and rating groups are the current priority. | J9: Real model-result consistency issue; avoid 103 underpowered separate slopes. | K9: A - Methodological issue / additional estimation | L9: Secs. 3.1, 3.3.2, 4.1, 4.3, 5.2.3, 6.1, 6.3 | M9: Estimate staged heterogeneity: broad rating tiers; defensible sector groups; issuer/bond slopes only where T is adequate. Report counts, confidence intervals and equality tests. | N9: Additional estimation | O9: MR-01, MR-03, MR-16; group definitions | P9: At least one defensible rating and sector test is reported; small-cell limitations are explicit and explanations follow estimates. | Q9: Yes | R9: Not started
A10: MR-07 | B10: A-07; M-01, M-16, M-17 | C10: OG-03 | D10: High | E10: Ailin + Maximo | F10: Local-currency credit quality is used ex post to explain the sovereign coefficient but is absent from the model. | G10: Ailin pp. 2, 9-10; Maximo pp. 1, 4 | H10: Partially agrees | I10: Martin supports a compact rating-tier test but not an unlimited interaction battery. | J10: A compact rating interaction is the cleanest direct test if rating timing and cells are defensible. | K10: A - Methodological issue / additional estimation | L10: Sec. 5.2.3; Sec. 6.1 and 6.3; variable section 4.5.3 | M10: Add broad local-currency rating tiers, define timing/missing treatment, interact with the sovereign factor and test equality. | N10: New data field + additional estimation | O10: MR-06; rating source/timing rule | P10: Rating definitions, dates, counts and equality tests are documented. | Q10: Yes - minimum scope | R10: Not started
A11: MR-08 | B11: M-16, M-17, M-18 | C11: OG-03 | D11: Low | E11: Maximo | F11: Test flight-to-quality explanations with crisis/event dummies and interactions. | G11: Maximo p. 4 and defense questions | H11: Disagrees / not endorsed | I11: Useful but optional/future research; the thesis must have a bounded end. | J11: Potentially informative but secondary after ratings, sectors and stale-price checks. | K11: D - Not endorsed / optional / response only | L11: Sec. 5.2.1, 5.2.3, 6.1, 6.3 | M11: Keep as future research unless a pre-specified low-cost robustness can be added. Do not present flight-to-quality as a finding. | N11: Optional interaction estimation | O11: MR-06 and MR-07 | P11: Narrative labels this as a possible mechanism unless directly tested. | Q11: No - response only | R11: Not started
A12: MR-09 | B12: A-01, A-06; M-03, M-10, M-18; D-09, D-18 | C12: OG-04 | D12: High | E12: Ailin + Maximo + Daniel | F12: VIX differs from the proxy in the cited reference, is not pure risk aversion, and its negative sign relative to H1 requires an explicit conditional interpretation. | G12: Ailin pp. 1, 7-8; Maximo pp. 1, 3, 5; Daniel pp. 2-3 | H12: Agrees / strongly agrees | I12: 24-Sep-2026: Daniel mainly requires clearer hypothesis-result links and better explanations of counterintuitive signs. Keep VIX if justified; do not overstate robustness. | J12: Retain VIX as a global volatility/financial-stress proxy, not pure risk aversion, and interpret it conditionally after sequential models. | K12: B - Clarification / reframing | L12: Secs. 3.1, 3.3.1, H1/Table 1, Sec. 4.5.3, Sec. 5.2.1, Sec. 6.1 | M12: CLOSED PRE-FREEZE. VIX source/monthly history/panel mapping/scaling/economic label are validated and the thesis frames VIX as expected S&P 500 implied volatility used as a proxy for global financial stress, not pure risk aversion. The companion Fed 3M Forward audit also passed all six stages: Bloomberg USSOC Curncy / PX_LAST (3M USD OIS), daily history, month-end convention, 164/164 exact panel match, native percentage-point scaling and corrected technical definition. Final coefficient-movement/correlation diagnostics and final VIX sign/H1 prose are downstream tasks under MR-18/MR-19 after the frozen-panel DK rerun; they do not keep MR-09 open. | N12: Data/source audit + text revision + diagnostic; optional alternative proxy | O12: MR-18 correlation matrix | P12: PASSED: the VIX construct/proxy is justified and accurately labeled; its source, monthly mapping and scaling are validated. The companion nominal Fed control is independently sourced and reproduced end-to-end, including 164/164 exact panel-month matches and a technically correct OIS definition. Any post-freeze correlation table and final sign interpretation are assigned to MR-18/MR-19. | Q12: Yes | R12: Done | S12: Closed 2-Oct-2026. VIX pre-freeze audit passed (187/187 monthly history check; 4,229/4,229 panel mapping; raw index-point scaling; corrected financial-stress wording). Fed 3M Forward audit passed all six stages: USSOC Curncy / PX_LAST (3M USD OIS); daily/raw coverage confirmed; month-end/last-available-quote convention validated; 164/164 distinct panel months exact with 0 mismatches and max abs diff 0.0; baseline Stata uses native percentage-point values without rescaling; thesis definition now states the exact ticker/field, OIS instrument, month-end convention and that the series is not forward-starting. Reproducible BQNT notebook and README are version-controlled in fb7748d. Remaining post-freeze correlation/sign work is consolidated under MR-18/MR-19.
A13: MR-10 | B13: A-06 | C13: OG-04 | D13: Low | E13: Ailin | F13: Replace or complement VIX with a large composite PCA index. | G13: Ailin pp. 7-8, M4 | H13: Disagrees / not endorsed | I13: No mandatory replacement. Acknowledge alternatives; at most use one transparent proxy. | J13: Large extension with substantial discretion; not necessary to resolve the core criticism. | K13: D - Not endorsed / optional / response only | L13: Would affect Sec. 4.5.3, all regressions and Annex A | M13: Do not build the PCA as a mandatory revision. Mention as future research; optionally show one simple alternative proxy. | N13: No mandatory estimation | O13: MR-09 | P13: Response memo explains the narrower remedy. | Q13: No - response only | R13: Not started
A14: MR-11 | B14: A-02, A-04, A-12; D-03, D-15 | C14: OG-05 | D14: High | E14: Ailin + Daniel | F14: The literature bridge to factor exposure, stale OTC pricing and the closest empirical studies is too descriptive or incomplete. | G14: Ailin pp. 1, 3, 5-7; Daniel pp. 1-3 | H14: Partially agrees | I14: 24-Sep-2026: Daniel is less substantial than the other reports; bibliography is a minor, targeted correction. Add only literature that supports the actual specification, tests and limits. | J14: A concise, critical comparison is warranted; no theoretical overhaul. | K14: C - Presentation / structure / literature / documentation | L14: Secs. 3.1-3.3, 4.6-4.7, 5.2-5.4; References | M14: Add a concise factor/stale-price bridge and directly compare the closest local-currency corporate-debt and panel-method papers. Correct minor bibliography issues. | N14: Literature and interpretation rewrite | O14: MR-04, MR-25, MR-34 | P14: Each added reference is tied to a specific construct, test or limitation. | Q14: Yes | R14: Not started
A15: MR-12 | B15: M-02; D-07, D-17 | C15: OG-06 | D15: High | E15: Maximo + Daniel | F15: The thesis sometimes uses causal language although the design is observational and correlational. | G15: Maximo p. 1; Daniel pp. 2-3 | H15: No explicit position | I15: No direct Martin comment; consistent with the general instruction to avoid overstatement. | J15: Valid, low-cost wording correction. | K15: B - Clarification / reframing | L15: Sec. 4.3, 4.7; Resumen/Abstract; Conclusions | M15: Audit causal verbs and replace them with conditional-association language unless a specific identification argument supports causality. | N15: Text-only global edit | O15: Final model wording after MR-19 | P15: Abstract, methods, results and conclusions use consistent non-causal language. | Q15: Yes | R15: Not started
A16: MR-13 | B16: M-05; D-05, D-17 | C16: OG-07 | D16: High | E16: Maximo + Daniel | F16: The 4,229 rows do not equal 4,229 independent macro observations; the panel is strongly unbalanced with unequal bond histories. | G16: Maximo p. 2; Daniel pp. 2-3 | H16: Agrees / strongly agrees | I16: Clarify the effective monthly dimension and the panel-balance profile; do not overstate precision or generalizability. | J16: Does not invalidate panel estimation, but affects inference and exposition. | K16: B - Clarification / reframing | L16: Secs. 4.2-4.4, 5.1; Annex 8.10 | M16: Report observations, months, bonds and issuers separately; add T_i distribution, entry/exit years and annual coverage. | N16: Method clarification + table metadata | O16: MR-16 and MR-24 | P16: Methods and tables distinguish all dimensions and state unequal coverage clearly. | Q16: Yes | R16: Not started
A17: MR-14 | B17: M-06, M-17; D-11, D-18 | C17: OG-07 | D17: Critical | E17: Maximo + Daniel | F17: A time-invariant issue-size variable should be absorbed by bond fixed effects, yet a coefficient is reported; the sign also changes under PCSE. | G17: Maximo pp. 2, 4; Daniel pp. 2-3 | H17: Agrees / strongly agrees | I17: Audit the construction. Issue size itself is invariant; any variation must come from the denominator or timing. | J17: Resolved. The time-invariance concern applies to AMT_ISSUED in levels, not to the estimated ratio. The actual regressor is AMT_ISSUED / BS_TOT_ASSET; quarterly issuer assets create time variation. In the estimation sample 98/103 bonds (95.15%) exhibit within-bond variation, so the ratio is identified under bond fixed effects. The coefficient measures changes in relative issue size versus issuer scale, not changes in the original issue amount. | K17: A - Methodological issue / additional estimation | L17: Table 1 H6; Secs. 4.5.3 and 4.7; Table 3; Sec. 5.2.4; Sec. 6.1-6.2.2; Annex 8.6.2 and Table 7; Figure 3 | M17: Completed: trace AMT_ISSUED and issuer BS_TOT_ASSET from raw inputs; reconstruct the full panel; quantify within/between variation and quarterly timing; document the ‰ scale; retain and rename/define the variable consistently; revise FE identification and interpretation; keep a one-quarter-lagged denominator as timing robustness. | N17: Data audit + possible model revision | O17: Raw panel and code | P17: Passed: 4,229/4,229 observations reproduce from raw sources; 98/103 bonds vary within bond; the final variable name and ‰ units match construction; the thesis states that identification comes from the time-varying denominator and does not interpret the coefficient as the effect of changing AMT_ISSUED. | Q17: Yes | R17: Done | S17: Closed 30-Sep-2026. Full raw-source reconciliation matched the thesis panel essentially exactly. Within-bond audit: 98/103 bonds vary (95.15%); five bonds with <=1 distinct value have very short histories. Timing check showed the contemporaneous quarterly denominator; a Q-1 denominator robustness was built (4,223/4,229 available; corr=0.9918; same 98/103 varying bonds). Main specification retains the audited contemporaneous ratio. Thesis updated in H6, Sec. 4.5.3, Sec. 4.7, results/conclusions, Tables 3/7, Figure 3 and Annex 8.6.2.
A18: MR-15 | B18: M-06; D-05 | C18: OG-07 | D18: Medium | E18: Maximo + Daniel | F18: Most regressors vary at month or firm-month level while same-firm bonds can have different spreads; substantial bond-time variation remains unexplained. | G18: Maximo p. 2; Daniel p. 2 | H18: Partially agrees | I18: Clarify what fixed effects do and do not absorb; no model can cover every bond-time factor. | J18: Primarily a scope and interpretation issue. | K18: B - Clarification / reframing | L18: Secs. 4.7-4.8, 5.3-5.4, 6.1 and limitations | M18: Explain identification at month, firm-month and bond-month levels; interpret low within R2 without claiming model failure. | N18: Clarification; optional controls | O18: MR-13 and MR-14 | P18: The thesis states FE limits and unexplained variation transparently. | Q18: Yes | R18: Not started
A19: MR-16 | B19: M-07, M-08, M-10, M-17, M-18; D-06, D-17 | C19: OG-08 | D19: Critical | E19: Maximo + Daniel | F19: Issuer-clustered errors ignore common shocks. Heteroskedasticity, cross-sectional dependence, serial autocorrelation and imbalance make inference estimator-sensitive. | G19: Maximo pp. 3-5; Daniel pp. 2-3 | H19: Agrees / strongly agrees | I19: 24-Sep-2026: Driscoll-Kraay is the least-worst reference estimator. 25-Sep-2026: Martin confirms the PCSE rationale and asks for one results table containing FE with Driscoll-Kraay SE only, excluding the separate conventional FE and PCSE columns. | J19: Genuine inference correction. DK should anchor all significance claims, while its limitations are stated. | K19: A - Methodological issue / additional estimation | L19: Secs. 4.2, 4.6, 4.8, 5.1-5.3; Tables 2-3; Annex 8.10-8.11 | M19: Use bond FE with Driscoll-Kraay as the sole reference inference. Report diagnostics and DK lag/finite-sample setup below the single results table. Remove separate conventional-FE and PCSE columns from the paper/seminar output. | N19: Full re-estimation / inference reset | O19: MR-03 and final variable set | P19: The core output is one FE-Driscoll-Kraay table, diagnostics are visible, and no main result is shown in a separate plain-FE or PCSE column. | Q19: Yes | R19: Not started | S19: PCSE exclusion rationale explicitly accepted by Martin on 25-Sep-2026.
A20: MR-17 | B20: M-09, M-17, M-18; D-06, D-11 | C20: OG-08 | D20: Critical | E20: Maximo + Daniel | F20: PCSE coefficients differ from FE even though the thesis presents PCSE as merely another error correction; sign/significance changes need explanation. | G20: Maximo pp. 3, 5; Daniel p. 2 | H20: Agrees / strongly agrees | I20: 25-Sep-2026: Martin accepts the explanation that the highly unbalanced panel and limited common temporal overlap make the contemporaneous cross-sectional covariance estimate required by PCSE less reliable. PCSE should not appear in the main table. | J20: The old comparison is internally inconsistent. The code should be audited only to document what was run; the preferred output must not invite a FE-versus-PCSE horse race. | K20: A - Methodological issue / additional estimation | L20: Secs. 4.2, 4.6, 4.8, 5.1-5.3; Tables 3 and 7 | M20: Recover the exact PCSE command for the internal audit, document why imbalance/common-overlap weakens its use here, and remove PCSE from the main thesis and seminar table. Retain it, if at all, only in a clearly qualified appendix note. | N20: Code audit + table redesign | O20: Original do-file/logs; MR-16 | P20: The response memo states the panel-structure rationale precisely; the main results contain no PCSE column and make no unsupported claim that PCSE is merely an error correction. | Q20: Yes | R20: Not started | S20: Director confirmed the stated reason for discarding PCSE on 25-Sep-2026.
A21: MR-18 | B21: M-16, M-17; A-18 via Martin | C21: OG-08 | D21: Critical | E21: Maximo; reinforced by Martin | F21: The full model does not show how correlated aggregate regressors alter one another. Sequential specifications and correlation diagnostics are required. | G21: Maximo p. 4; Martin annotations/messages 24-25 Sep-2026; attached four-model table dated 25-Sep-2026 | H21: Agrees / strongly agrees | I21: 25-Sep-2026: prepare one consolidated four-column FE-Driscoll-Kraay table using nominal FED3M Forward, varying the BRL sovereign spread and domestic macro controls, with RER as the requested alternative to NER. 27-Sep: any SELIC 3M Forward columns are referee-only diagnostics and should not be presented as part of the preferred baseline. | J21: This is now an exact paper/seminar output design rather than a generic robustness request. Two source ambiguities must be confirmed instead of silently resolved: Model 1 marks both NER and RER, and the text asks for sequential stacking while the template includes firm/bond controls in all four columns. | K21: A - Methodological issue / additional estimation | L21: Secs. 4.6-4.8, 5.1-5.4; Annex 8.11 | M21: Implement the four core FE-DK columns exactly as documented in the Estimation Plan; use nominal FED3M Forward and exclude the old real construction. Compare sovereign/local-macro combinations and NER/RER; report correlations and coefficient movements. After the core table, run the two SELIC checks only as referee diagnostics if feasible. Confirm the two template ambiguities before final coding. | N21: Additional estimation + single consolidated table + optional robustness | O21: MR-01, MR-03, MR-04, MR-16; confirmed model grid | P21: One pre-specified FE-DK table uses nominal FED3M Forward, documents every included block, reports diagnostics/statistics, and does not silently resolve the NER/RER or stacking ambiguities. Any SELIC columns are clearly separated and labeled referee-only. | Q21: Yes | R21: Not started | S21: Requested target: 30-Sep-2026. See Estimation Plan sheet for the exact grid and unresolved source ambiguities.
A22: MR-19 | B22: M-10, M-18; A-10, A-16; D-06, D-09, D-11, D-12, D-18 | C22: OG-08 | D22: Critical | E22: Ailin + Maximo + Daniel | F22: The submitted narrative relies on estimator-sensitive significance. Daniel asks that hypotheses be tied explicitly to final results and counterintuitive signs be explained better. | G22: Ailin pp. 3-4; Maximo pp. 3-5; Daniel pp. 2-3 | H22: Agrees / strongly agrees | I22: 24-Sep-2026: treat Daniel mainly as an exposition task after the core spread and DK work. Rebuild interpretations only after final estimates. | J22: Required downstream rewrite, not a separate empirical choice. | K22: B - Clarification / reframing | L22: Resumen/Abstract; Secs. 5.2-5.4; Secs. 6.1-6.4; Tables 3 and 7 | M22: After the estimation freeze, classify every hypothesis/result as robust, partial/sensitive, null or unresolved. Explain counterintuitive signs against the final DK sequence and avoid carrying old PCSE/FE claims forward. | N22: Results/abstract/conclusions rewrite | O22: MR-01 through MR-18 finalized | P22: A hypothesis-to-result and table-to-text audit confirms every sign, magnitude and significance statement. | Q22: Yes | R22: Not started
A23: MR-20 | B23: M-11; D-08, D-17 | C23: OG-09 | D23: Low | E23: Maximo + Daniel | F23: Persistence, serial correlation and inability to apply standard unit-root tests raise questions about dynamics and stationarity. | G23: Maximo pp. 3-4; Daniel pp. 2-3 | H23: Disagrees / not endorsed | I23: Do not convert the thesis to a dynamic panel or add a monthly lagged spread; markets are forward-looking. Acknowledge the limitation and answer it. | J23: The concern is real, but DK does not solve non-stationarity. A bounded explanation is required; first-difference work remains optional. | K23: D - Not endorsed / optional / response only | L23: Sec. 4.6; Sec. 5.1; Annex 8.11 | M23: Explain the static monthly specification, acknowledge persistence/unit-root limits and avoid claiming they are tested away. Keep first-difference robustness optional. | N23: No mandatory estimation; optional robustness | O23: MR-16 and MR-25 | P23: The response memo justifies the non-change and the thesis states the limitation accurately. | Q23: No - response only | R23: Not started
A24: MR-21 | B24: M-12 | C24: OG-09 | D24: Medium | E24: Maximo | F24: Collin-Dufresne, Goldstein and Martin (2001) is cited to justify levels although it studies spread changes. | G24: Maximo p. 3 | H24: Agrees / strongly agrees | I24: 24-Sep-2026: bibliography corrections are minor but should be made. | J24: Valid citation-accuracy correction independent of the model debate. | K24: C - Presentation / structure / literature / documentation | L24: Secs. 3.3 and 4.6; References | M24: Correct the citation and retain only sources that actually support the chosen specification. | N24: Literature correction | P24: The paper is described accurately and no unsupported citation claim remains. | Q24: Yes | R24: Not started
A25: MR-22 | B25: M-13 | C25: OG-10 | D25: Medium | E25: Maximo | F25: Debt/GDP is described as significant at 1 percent in text while the DK table reports 5 percent. | G25: Maximo pp. 3-4 | H25: No explicit position | I25: Covered by the instruction to rewrite results after final DK estimates. | J25: Straightforward reporting error. | K25: C - Presentation / structure / literature / documentation | L25: Sec. 5.2.2; Table 3; Annex Table 7 | M25: Correct after the final estimation freeze and run a complete table-to-text audit. | N25: Text correction | O25: MR-19 | P25: Text and table match exactly. | Q25: Yes | R25: Not started
A26: MR-23 | B26: M-14 | C26: OG-10 | D26: Medium | E26: Maximo | F26: The thesis says PCSE corrects serial correlation, which is not necessarily true without an explicit autoregressive transformation. | G26: Maximo p. 4 | H26: Agrees / strongly agrees | I26: Remove PCSE from the main thesis and seminar; delete the unsupported claim. | J26: Valid technical correction. | K26: C - Presentation / structure / literature / documentation | L26: Secs. 4.8, 5.1; Annex 8.10.4 | M26: Delete the claim; if PCSE remains in an appendix, state the exact correlation structure and limitations. | N26: Technical text correction | O26: MR-17 | P26: No unsupported PCSE statement remains. | Q26: Yes | R26: Not started
A27: MR-24 | B27: M-15 | C27: OG-10 | D27: High | E27: Maximo | F27: The main regression table omits standard errors and N. | G27: Maximo p. 4 | H27: Agrees / strongly agrees | I27: 25-Sep-2026: the director-provided table explicitly requests Within R-squared and rho under each of the four FE-DK models. Existing matrix requirements for SE, N, panel dimensions and DK metadata remain. | J27: Essential reporting standard. | K27: C - Presentation / structure / literature / documentation | L27: Table 3; Annex Table 7; table notes | M27: Build one consolidated FE-DK table reporting coefficient, standard error, N, bonds, issuers, months, within R2, rho, FE type, DK lag, units and significance legend; place diagnostic-test information immediately below or in a linked panel. | N27: Table redesign | O27: MR-16 and MR-18 | P27: A reader can evaluate every coefficient and model statistic in the single consolidated table and compare specifications directly. | Q27: Yes | R27: Not started | S27: The attached 25-Sep template names Within R-squared and rho explicitly.
A28: MR-25 | B28: A-10, A-12; M-11, M-16 | C28: OG-11 | D28: High | E28: Ailin + Maximo | F28: Stale or lagged OTC quotes may mechanically compress measured spreads when the liquid reference curve moves quickly. | G28: Ailin pp. 3, 5-6; Maximo pp. 3-4 | H28: Partially agrees | I28: Add the literature and a bounded diagnostic if feasible; do not present flight-to-quality as the only explanation. | J28: Serious measurement limitation in an OTC setting. | K28: B - Clarification / reframing | L28: Secs. 2.1.1, 4.5.2, 4.6, 5.2.1, 5.2.3, 6.1-6.3; Annex 8.2 and 8.5 | M28: Add the limitation and one feasible lead-lag/liquidity/source-stability diagnostic where possible. | N28: Text + optional diagnostic estimation | O28: MR-03, source fields, MR-16 | P28: Stale pricing is treated as a competing mechanism and any available diagnostic is reported. | Q28: Yes - minimum scope | R28: Not started
A29: MR-26 | B29: A-10, A-11, A-16; M-16, M-18 | C29: OG-11 | D29: High | E29: Ailin + Maximo | F29: Unexpected signs are discussed with generic emerging-market narratives rather than Brazil-specific institutions. | G29: Ailin pp. 3-4; Maximo pp. 4-5 | H29: Agrees / strongly agrees | I29: Use Selic/DI/IPCA structure, institutional investors, indexed liabilities and Law 12.431 in interpretation. 25-Sep-2026: Martin reports nominal and real exchange rates give almost the same result/significance; RER remains meaningful as a relative price. 27-Sep: the local reference curve already embeds SELIC at the short end; any direct SELIC 3M Forward regression is only a referee diagnostic. | J29: Valid reframing; mechanisms must be distinguished from tested evidence. | K29: B - Clarification / reframing | L29: Secs. 2.1.1, 3.1, 5.2.1, 5.2.3, 5.4, 6.1-6.3; Glossary | M29: Rewrite mechanisms around Brazilian real-rate institutions, distinguish evidence from plausible channels, and explain the RER robustness as a relative-price channel. Do not add SELIC mechanically to the baseline or reintroduce inflation without a clear identification role. | N29: Interpretation rewrite | O29: MR-01, MR-04, MR-06/07, MR-19, MR-25 | P29: Every counterintuitive sign has a Brazil-specific but appropriately qualified interpretation. | Q29: Yes | R29: Not started | S29: NER/RER similarity is a reported director observation to verify in the regenerated estimates.
A30: MR-27 | B30: A-08, A-09 | C30: OG-12 | D30: Critical | E30: Ailin | F30: The thesis lacks a complete computational replication package, including source consolidation, queries, dates, code and Nelson-Siegel settings. | G30: Ailin p. 2, p. 10, M7 | H30: Agrees / strongly agrees | I30: Deliver the complete package, subject to data licensing. | J30: Mandatory submission deliverable. | K30: C - Presentation / structure / literature / documentation | L30: Secs. 4.4-4.5; Annex 8.1-8.14 | M30: Create README, environment, ordered scripts, queries, extraction dates, hashes, OTC source rules, missing/outlier treatment, accounting timing and curve-estimation settings. Clean-run all outputs. | N30: Replication package / documentation | O30: Final code and outputs | P30: A clean run regenerates every permitted table and figure. | Q30: Yes | R30: Not started
A31: MR-28 | B31: A-08 | C31: OG-12 | D31: Medium | E31: Ailin | F31: Bloomberg is sometimes described as the original source where it is an access vendor or aggregator. | G31: Ailin p. 2 | H31: No explicit position | I31: Covered within the broader replication package. | J31: Valid provenance issue. | K31: C - Presentation / structure / literature / documentation | L31: Secs. 2.1.1, 4.5.2-4.5.3; figure notes; References; Annex A | M31: Create a data dictionary separating original producer, access channel, ticker/query, field, frequency, transformation and extraction date. | N31: Source and documentation revision | O31: MR-27 | P31: Every variable and figure has a traceable provenance chain. | Q31: Yes | R31: Not started
A32: MR-29 | B32: A-15 | C32: OG-13 | D32: Low | E32: Ailin | F32: Build a new sovereign-versus-corporate breakeven analysis including synthetic fixed-rate equivalents for CDI-linked debentures. | G32: Ailin pp. 8-10, M6 | H32: Disagrees / not endorsed | I32: This is a separate research project; the thesis must have a bounded end. | J32: Not proportionate to the current TFM revision. | K32: D - Not endorsed / optional / response only | L32: Would require major new material beyond Secs. 4-6 and Annex A | M32: Do not add the full exercise. Mention it as a future research extension and explain scope in the response memo. | N32: No thesis modification beyond future research | P32: Future-research paragraph captures the idea without implying it was estimated. | Q32: No - response only | R32: Not started
A33: MR-30 | B33: A-10, A-11, A-16, A-18; M-10, M-16, M-18; D-01, D-04, D-09, D-10, D-12, D-13, D-16, D-18 | C33: OG-11 | D33: Critical | E33: Ailin + Maximo + Daniel | F33: The abstract, results and conclusions over-center anomalous signs and imply broader hypothesis confirmation than the estimator sensitivity supports. | G33: Ailin pp. 3-4; Maximo pp. 3-5; Daniel pp. 1-3 | H33: Agrees / strongly agrees | I33: 24-Sep-2026: Daniel is less substantial, but his main expositional requests are valid: link hypotheses to results and explain counterintuitive signs. For seminars emphasize external versus internal factors and show only the final DK evidence. | J33: Final synthesis task after empirical freeze. | K33: B - Clarification / reframing | L33: Resumen/Abstract; Introduction; Secs. 5.2-5.4 and 6.1-6.4; defense/seminar deck | M33: Rewrite around a robust/partial/null/unresolved hierarchy; add a hypothesis scorecard; emphasize external versus internal determinants; explain scoped non-changes and future extensions. | N33: Full narrative rewrite + response memo | O33: All empirical and literature revisions complete | P33: Thesis, response memo and seminar deck classify each hypothesis consistently and do not overstate results. | Q33: Yes | R33: Not started
A34: MR-31 | B34: D-01, D-02, D-13, D-16 | C34: OG-14 | D34: High | E34: Daniel | F34: The research gap and originality are asserted more than demonstrated, and three broad questions obscure the central contribution. | G34: Daniel pp. 1-3 | H34: Partially agrees | I34: 24-Sep-2026: Martin reads Daniel as less substantial than Ailin and Maximo. Address this as a selective exposition improvement after the spread and estimator issues, not as a redesign. | J34: Valid framing correction; final wording should match the revised evidence. | K34: B - Clarification / reframing | L34: Resumen/Abstract; Introduction; literature/framework; Sec. 6; defense/PPT | M34: State one primary question, subordinate secondary questions, and demonstrate the contribution against the closest empirical studies. Link data, curve and empirical design to concrete contributions. | N34: Introduction/contribution rewrite | O34: Final results; MR-30 and MR-34 | P34: One central question and two or three evidence-backed contributions are stated clearly. | Q34: Yes | R34: Not started | S34: Secondary to Maximo-driven measurement and estimator work.
A35: MR-32 | B35: D-03, D-04, D-18 | C35: OG-14 | D35: High | E35: Daniel | F35: The theoretical framework is descriptive; nine hypotheses may exceed the identifying capacity of one panel and some proxies are contestable. | G35: Daniel pp. 1, 3 | H35: Partially agrees | I35: Keep the paper empirical. Rationalize the theory-to-variable chain and link hypotheses to final results without a structural-theory redesign. | J35: The issue is sharper architecture, not more theory. | K35: C - Presentation / structure / literature / documentation | L35: Sec. 3; Sec. 4.1; variable definitions; results and defense | M35: Create a construct-to-proxy table; designate core versus secondary hypotheses; produce a final supported/partial/not-confirmed scorecard. | N35: Theory-to-specification mapping | O35: Final variable definitions; MR-11, MR-19, MR-30 | P35: Every retained hypothesis has a defensible proxy and maps to a final result. | Q35: Yes | R35: Not started
A36: MR-33 | B36: D-14 | C36: OG-15 | D36: Medium | E36: Daniel | F36: A final academic-language and consistency review is needed for causal wording, econometric phrasing, repetition and multilingual terminology. | G36: Daniel p. 2 | H36: Partially agrees | I36: Treat as a minor final-stage correction after all estimates and tables are frozen. | J36: Low methodological risk but worthwhile for submission quality. | K36: C - Presentation / structure / literature / documentation | L36: Entire thesis | M36: Run a controlled final terminology, language, acronym, table-text and cross-reference QA pass. | N36: Final copy-edit / QA | O36: All empirical outputs and narrative revisions complete | P36: No inconsistent variable names, undefined acronyms, causal overclaims or table-text mismatch remain. | Q36: Yes | R36: Not started
A37: MR-34 | B37: D-15 | C37: OG-16 | D37: Medium | E37: Daniel | F37: The literature review should be more critical and current; bibliometrics do not replace direct comparison with comparable empirical work. | G37: Daniel pp. 2-3 | H37: Partially agrees | I37: 24-Sep-2026: bibliography issues are minor. Make bounded, purpose-driven updates; do not turn the thesis into a new survey. | J37: Efficient remedy is a direct comparison tied to data, benchmark, estimator, identification and findings. | K37: C - Presentation / structure / literature / documentation | L37: Literature review; methods justification; introduction contribution; bibliography; defense | M37: Add a compact closest-study comparison and recent method references directly supporting DK, local-currency debt and macrofinance identification. | N37: Targeted literature review | O37: MR-11, MR-31, MR-32; final method choice | P37: Closest studies are compared critically and new citations support actual model choices. | Q37: Yes | R37: Not started

Sheet Juror Log
A1: Juror-by-Juror Source Log
A2: Traceability sheet: every distinct criticism from all three reports maps to one or more consolidated master issues. Daniel dispositions reflect Martin's review on 24-Sep-2026.
A3: Source ID | B3: Juror | C3: Report location | D3: Original criticism - concise | E3: Master issue ID(s) | F3: Overlap group | G3: Martin position / disposition
A4: A-01 | B4: Ailin | C4: p. 1; pp. 7-8 | D4: VIX operationalization differs from Gonzalez-Rozada and Levy-Yeyati (2008) and is not justified. | E4: MR-09, MR-10 | F4: OG-04 | G4: Partial agreement: justify VIX; no mandatory replacement.
A5: A-02 | B5: Ailin | C5: p. 1; p. 3; pp. 5-7 | D5: Missing SDF/Euler, Fama (1984), Lustig et al. (2011) and related asset-pricing bridge. | E5: MR-04, MR-05, MR-11 | F5: OG-02 / OG-05 | G5: Partial agreement: concise bridge, no theoretical redesign.
A6: A-03 | B6: Ailin | C6: p. 2; p. 6; M1 | D6: Sovereign indicator reuses the IPCA curve; long end may be near zero by construction and short end a market basis. | E6: MR-01, MR-02 | F6: OG-01 | G6: Now high priority: answer through sovereign-ceiling framing, matching and robustness.
A7: A-04 | B7: Ailin | C7: p. 2; pp. 5-7; M3 | D7: Implicit beta=1 to the real-curve factor; domestic real rate omitted. | E7: MR-04, MR-05 | F7: OG-02 | G7: SELIC not added separately; bounded real-curve diagnostic only.
A8: A-05 | B8: Ailin | C8: p. 2; p. 7; M2 | D8: Arithmetic spread calculation is inconsistent with compounding conventions. | E8: MR-03 | F8: OG-02 | G8: Agrees: recalculate geometrically/log-consistently.
A9: A-06 | B9: Ailin | C9: p. 2; pp. 7-8; M4 | D9: VIX is not pure risk aversion; use a composite PCA index. | E9: MR-09, MR-10 | F9: OG-04 | G9: No mandatory PCA; justify VIX and acknowledge alternatives.
A10: A-07 | B10: Ailin | C10: p. 2; pp. 9-10; M5 | D10: Rating heterogeneity must be modeled, not used ex post. | E10: MR-06, MR-07 | F10: OG-03 | G10: Agrees on bounded rating/sector tests.
A11: A-08 | B11: Ailin | C11: p. 2 | D11: Bloomberg is an access channel, not always the primary source. | E11: MR-28 | F11: OG-12 | G11: Handle within data provenance.
A12: A-09 | B12: Ailin | C12: p. 2; p. 10; M7 | D12: No complete replication package. | E12: MR-27 | F12: OG-12 | G12: Agrees: deliver complete package.
A13: A-10 | B13: Ailin | C13: p. 3 | D13: Central signs have plausible mechanical explanations that are not ruled out. | E13: MR-01, MR-25, MR-30 | F13: OG-01 / OG-11 | G13: Rewrite after spread/DK work; test or qualify mechanisms.
A14: A-11 | B14: Ailin | C14: p. 3; p. 4; M8 | D14: Interpretation omits Selic, real curve, investors and Law 12.431. | E14: MR-26, MR-30 | F14: OG-11 | G14: Deepen Brazil-specific interpretation; no mechanical SELIC inclusion.
... A57: D-18 | B57: Daniel | C57: p. 3 | D57: Defense must discuss counterintuitive signs, issue-size sensitivity and non-robust firm variables. | E57: MR-09, MR-14, MR-19, MR-30, MR-32 | F57: OG-04 / OG-07 / OG-11 / OG-14 | G57: Use final H-result scorecard and robust/partial/null hierarchy.

Sheet Director Guidance
A1: Director Follow-up Guidance
A2: Traceability for Martin Grandes' September 2026 audio/text guidance. Entries through 27-Sep-2026 update disposition, scope and the exact estimation output; they are not additional juror criticisms.
A3: Guidance ID | B3: Source / date | C3: Topic | D3: Director guidance - condensed | E3: Master issue / WP | F3: Disposition | G3: Required incorporation
A4: MG-01 | B4: WhatsApp audio, Sep-2026 | C4: Dynamic panel / lagged spread | D4: A one-month lag of price/spread has no clear economic role in a forward-looking market at monthly frequency; answer the juror but do not make the model dynamic. | E4: MR-20 / WP-16 | F4: Not endorsed for main model | G4: Add a concise static-model rationale, acknowledge persistence and include the non-change in the response memo/PPT.
A5: MG-02 | B5: WhatsApp audio, Sep-2026 | C5: SELIC - first rationale | D5: Do not add SELIC mechanically; it may duplicate the U.S. forward rate plus expected BRL depreciation. | E5: MR-04, MR-26 / WP-04 | F5: Diagnostic first | G5: Document overlap and incremental information before any robustness use.
A6: MG-03 | B6: WhatsApp audio, Sep-2026 | C6: Sovereign risk measure | D6: The relevant object is Brazil sovereign risk in local currency, not international USD CDS; this is why local curves were built. 27-Sep-2026 clarification: USD CDS 5Y was never part of the economic model and should not be introduced. | E6: MR-01, MR-02 / WP-02 | F6: Core clarification | G6: Keep the primary benchmark local and matched; verify USD CDS 5Y is absent from the model and remove any secondary-control language suggesting otherwise.
A7: MG-04 | B7: WhatsApp audio, Sep-2026 | C7: Heterogeneity | D7: Differences across bonds or groups by sector/industry may be important, but the revision should remain bounded. | E7: MR-06, MR-07 / WP-05 | F7: Endorsed parsimoniously | G7: Use pre-specified rating/sector groups and equality tests; avoid an unlimited battery.
A8: MG-05 | B8: WhatsApp audio, Sep-2026 | C8: Theoretical scope | D8: Acknowledge what theory can derive, but the thesis/paper is empirical and should not be redesigned as a theoretical model. | E8: MR-05, MR-11, MR-32, MR-34 / WP-11 | F8: Bounded clarification | G8: Strengthen the theory-to-specification bridge only where it supports the empirical design.
A9: MG-06 | B9: WhatsApp audio/text, Sep-2026 | C9: Geneva presentation | D9: Shorten the deck; remove excessive methodology/literature; emphasize external versus internal factors and state what was not estimated and why. | E9: MR-30, MR-31 / WP-14, WP-16 | F9: Presentation requirement | G9: Build the concise narrative after final results.
A10: MG-07 | B10: Follow-up text, Sep-2026 | C10: Issuer/bond point estimates | D10: Issuer-level and, where sufficiently powered, bond-level heterogeneous estimates may be informative; small-T slopes can be imprecise. | E10: MR-05, MR-06 / WP-05, WP-16 | F10: Extension / bounded test | G10: Prioritize grouped tests; disclose precision limits and do not delay the TFM for 103 separate slopes.
A11: MG-08 | B11: WhatsApp audio, Sep-2026 | C11: Revision scope | D11: Respond to every comment, but not every suggested extension must be implemented; the thesis must have a bounded end. | E11: All / Action Sequence | F11: Scope-control principle | G11: Map each point to a change, diagnostic, defense answer or reasoned non-change.
A12: MG-09 | B12: WhatsApp text, 24-Sep-2026 | C12: Daniel report triage | D12: Daniel is less substantive than Ailin and Maximo. His main points are better hypothesis-result links, clearer explanations of counterintuitive signs, visible treatment of estimation problems already addressed, and minor bibliography corrections. | E12: MR-09, MR-11, MR-16, MR-19, MR-30-MR-34 / WP-07, WP-11, WP-13, WP-14 | F12: Selective / secondary priority | G12: Do not redesign the model for Daniel. Implement targeted exposition, diagnostics visibility and bibliography clean-up after the core empirical work.
A13: MG-10 | B13: WhatsApp text, 24-Sep-2026 | C13: SELIC - final disposition | D13: Do not include SELIC as a separate baseline regressor: beyond the redundancy argument, it anchors the short end of the local reference curve. A 3M Forward SELIC may be run only as a referee diagnostic under the later specified exclusions. | E13: MR-04, MR-26 / WP-04 | F13: Baseline excluded; referee diagnostic only | G13: Explain the non-inclusion in the thesis/response; do not add SELIC mechanically. If run, keep SELIC 3M Forward outside the preferred baseline.
A14: MG-11 | B14: WhatsApp text, 24-Sep-2026 | C14: Sovereign ceiling and matched-yield formulation | D14: Corporate excess or shortfall relative to the sovereign is closely related to the sovereign-ceiling hypothesis. 27-Sep-2026 clarification: the preferred econometric model keeps Corporate Spread = corporate YTM - local reference yield and Sovereign Risk = government YTM - the same local reference yield as separate variables, because the objective is to estimate how the first responds to the second. A direct corporate-minus-sovereign spread is a related alternative, not an identical econometric specification. | E14: MR-01, MR-02 / WP-02 | F14: Top substantive priority | G14: Add sovereign-ceiling framing, matching audit and literature justification for the preferred two-spread transmission specification; do not replace the dependent corporate spread with a direct corporate-sovereign differential.
... A24: MG-21 | B24: WhatsApp audio, 27-Sep-2026 | C24: Common-reference two-spread specification and referee-only SELIC check | D24: Corporate Spread = corporate YTM minus the matched local reference yield and Sovereign Risk (BRL) = government YTM minus that same reference curve. Although closely related to a direct corporate-minus-sovereign spread, Martin prefers keeping the two spreads separate so the model estimates the response of corporate spread to sovereign risk. Explain this choice with literature. USD CDS 5Y was never in the economic model. SELIC is already embedded at the curve short end; SELIC 3M Forward may be run only for the referee and shown/published only if informative. | E24: MR-01, MR-02, MR-04, MR-18 / WP-02, WP-04, WP-08 | F24: Preferred specification confirmed | G24: Document both spread equations and the common-reference logic; justify the separate-regressor specification with literature; verify USD CDS 5Y is absent; keep SELIC 3M Forward secondary/referee-only.

Sheet Overlap Map
A1: Overlap Map
A2: Shows where jurors raise the same underlying problem and defines one unified resolution to prevent duplicate work.
A3: Overlap group | B3: Cross-juror overlap? | C3: Theme | D3: What the reports/director say | E3: Master issue IDs | F3: Unified resolution | G3: Duplication-control note
A4: OG-01 | B4: Yes | C4: Sovereign measure construction, sovereign ceiling and interpretation | D4: Ailin questions the shared benchmark; Maximo shows the algebra; Daniel asks for a better negative-sign explanation. Martin clarified that Sovereign Risk (BRL) is a government-minus-local-reference spread, not a CDS, and that the preferred model keeps Corporate Spread and Sovereign Risk separate to estimate transmission. The final implementation/documentation now distinguishes the IPCA-real corporate benchmark from the nominal DI sovereign benchmark rather than asserting an identical curve. | E4: MR-01, MR-02 | F4: Closed 29-Sep-2026: nominal sovereign formula, same-date exact-tenor matching, DI source hierarchy and spread arithmetic validated; sovereign_spread_brl terminology adopted; CDS language removed; corporate IPCA-real versus nominal sovereign DI indexation/reference-curve distinction documented; two-spread sovereign-ceiling logic explained. Final coefficient refresh is downstream of the remaining regressor audits. | G4: Do not create a new CDS-like proxy. Do not reopen WP-02 when final regressions are rerun; only refresh coefficients/interpretation using the frozen explanatory-variable set.
A5: OG-02 | B5: No - Ailin | C5: Spread construction and real-curve exposure | D5: Arithmetic spread, implicit beta=1, missing real-rate factors and full Fama-MacBeth ideal. | E5: MR-03, MR-04, MR-05 | F5: Recalculate spreads; justify baseline SELIC non-inclusion; if useful, run only the two scoped SELIC 3M Forward referee checks; use bounded real-curve diagnostics; leave Fama-MacBeth as future research. | G5: MR-03 precedes every re-estimation; SELIC 3M Forward is diagnostic only, not a baseline redesign.
A6: OG-03 | B6: Yes | C6: Heterogeneous sovereign transmission and ratings | D6: Ailin/Maximo/Daniel criticize one average coefficient followed by heterogeneous explanations. | E6: MR-06, MR-07, MR-08 | F6: Use parsimonious rating and sector groups; issuer/bond slopes only where powered; events optional. | G6: One grouped table can answer multiple comments.
A7: OG-04 | B7: Yes | C7: VIX and global-risk proxy | D7: Both main jurors question the proxy; Daniel asks for direct hypothesis/sign interpretation. | E7: MR-09, MR-10 | F7: Closed proxy/data-definition portion: retain VIX as an S&P 500 implied-volatility / global-financial-stress proxy, not pure risk aversion; large PCA rebuild rejected. VIX data mapping/scaling and the companion Fed 3M Forward control are fully audited. Post-freeze correlations/sequential DK and final VIX sign interpretation are handled under MR-18/MR-19. | G7: Do not reopen MR-09 during the final rerun; use MR-18 for correlations/coefficient movement and MR-19 for the final hypothesis/sign narrative.
A8: OG-05 | B8: Ailin + Daniel | C8: Asset-pricing and literature bridge | D8: Ailin asks for factor/stale-price literature; Daniel asks for a more critical review. | E8: MR-11 | F8: Add concise, purpose-driven literature tied to actual tests and closest studies. | G8: Do not turn the revision into a theory survey.
A9: OG-06 | B9: Maximo + Daniel | C9: Causality versus association | D9: Both reports flag causal overstatement. | E9: MR-12 | F9: Global wording audit after final results. | G9: Low effort, high credibility.
A10: OG-07 | B10: Maximo + Daniel | C10: Identifying variation and issue-size identification | D10: Monthly common factors, unbalanced bond histories and possible time-invariant issue size. | E10: MR-13, MR-14, MR-15 | F10: WP-03/MR-14 closed 30-Sep-2026: relative issue size reconstructed and shown to vary within 98/103 bonds; units/timing/FE interpretation documented. Remaining MR-13/MR-15 work is to report panel dimensions/coverage and state FE limits in WP-10. | G10: Do not reopen the issue-size construction audit in WP-10; use the completed WP-03 evidence and focus WP-10 on broader identifying variation and panel imbalance.
A11: OG-08 | B11: Cross-juror synthesis | C11: Estimator, diagnostics, sequential specifications and final significance | D11: Maximo provides the detailed DK/PCSE critique; Daniel asks for estimator-problem visibility; Martin specifies the exact 25-Sep one-table output. | E11: MR-16, MR-17, MR-18, MR-19 | F11: Use one FE-DK table only, show diagnostics, discard PCSE/plain FE columns, use nominal FED3M, run the specified sovereign/macro and FX variants, then rewrite results. | G11: Do this once after the spread is frozen; confirm the two source-template ambiguities before coding.
A12: OG-09 | B12: Maximo + Daniel | C12: Persistence, levels and citation support | D12: Questions on stationarity/dynamics plus inaccurate citation use. | E12: MR-20, MR-21 | F12: Correct the citation; provide a bounded static-model response; no dynamic redesign. | G12: Separate the valid citation fix from the non-endorsed extension.
A13: OG-10 | B13: Maximo; reinforced by Daniel sensitivity | C13: Regression-table accuracy and completeness | D13: Significance mismatch, PCSE claim and missing SE/N. | E13: MR-22, MR-23, MR-24 | F13: One final consolidated FE-DK table with SE/N/panel dimensions, within R2, rho, DK metadata and a table-to-text QA pass. | G13: Do not repair old tables before final estimates.
A14: OG-11 | B14: Yes | C14: Untested narratives, Brazil mechanisms and final contribution | D14: Ailin emphasizes stale pricing/Brazil institutions; Maximo demands tests; Daniel asks for sign and hypothesis-result clarity. | E14: MR-25, MR-26, MR-30 | F14: Test what is feasible, label mechanisms, and rewrite contribution around final evidence. | G14: One integrated final narrative addresses all three.
... A19: OG-16 | B19: Daniel; complements Ailin | C19: Critical and recent comparable literature | D19: Bibliometrics do not replace direct comparison with relevant empirical work. | E19: MR-34; linked MR-11 and MR-31 | F19: Make minor, targeted bibliography corrections and a compact closest-study comparison. | G19: Keep additions purpose-driven and bounded.

Sheet Action Sequence
A1: Action Sequence
A2: Dependency-based workflow updated 2-Oct-2026 after completion of the VIX audit and all six Fed 3M Forward audit stages. This is the order that minimizes rework, not an effort estimate.
A3: Order | B3: Phase | C3: Master issue IDs | D3: Core tasks | E3: Deliverable | F3: Dependency | G3: Gate / decision rule
A4: 0 | B4: Governance and baseline | C4: MR-27, MR-30 | D4: Freeze the submitted thesis, code, data and outputs; maintain a response memo keyed to master IDs. | E4: Baseline archive + response memo shell | G4: Do not edit the only submitted copy.
A5: 1 | B5: Data and measurement audit | C5: MR-01, MR-02, MR-03, MR-14, MR-28 | D5: WP-01 corporate-spread measurement, WP-02 Sovereign Risk (BRL), and WP-03 relative issue-size identification are closed. Proceed through the remaining baseline explanatory-variable audits before rebuilding/finalizing the econometric panel. No final baseline or robustness specification should be rerun while the common regressor set can still change. | E5: Verified corporate spread + closed sovereign_spread_brl package + closed relative issue-size audit | F5: Phase 0 | G5: Econometric Panel Data Freeze Gate applies after the measurement work: finish or explicitly accept unchanged every baseline explanatory-variable audit, then freeze one authoritative panel and perform the final code/specification integrity search.
A6: 2 | B6: Explanatory-variable audit and Econometric Panel Data Freeze Gate | C6: MR-09 pre-freeze block closed; VIX/Fed/USD-BRL complete; GDP YoY current; MR-04 robustness parked; remaining baseline regressors | D6: VIX, nominal Fed 3M Forward and nominal USD/BRL have passed the full six-step pre-freeze audit. USD/BRL is USDBRL Curncy in the macro source, with uninterrupted monthly history over the thesis window, last-weekday month-end convention, exact 4,229-row / 164-month panel matching, direct BRL-per-USD level scaling and clarified depreciation semantics; the missing upstream Bloomberg formula is documented as a provenance limitation. CURRENT: audit GDP YoY using the same sequence, then continue through the remaining baseline explanatory variables. If the final core table substitutes RER for NER, audit the RER construction before freeze. WP-04 Brazil 3M DI data preparation is complete, but its merge/Models 5-6 remain deferred until after the final panel is frozen. | E6: Audited/frozen baseline regressor set + documented robustness-only Brazil 3M DI series/design | F6: Phase 1 | G6: Freeze variables before looking at new final results. Gate passes only when every baseline explanatory variable is audited or explicitly accepted unchanged and panel_main_and_robustness.xlsx is rebuilt/frozen as the authoritative econometric input.
A7: 3 | B7: Econometric reset | C7: MR-16, MR-17, MR-18, optional MR-20 | D7: AFTER DATA FREEZE: use one FE-DK table only; remove plain FE/PCSE columns; use finalized nominal FED3M and other audited regressors; run the exact four-model sovereign/macro/FX grid; then diagnostics and referee-only SELIC/Brazil 3M DI checks. | E7: Single four-model DK table + optional referee-only SELIC columns + logs/diagnostics | F7: Phase 2 | G7: Do not begin Phase 2 until the Data Freeze Gate passes. Confirm NER/RER and stacking ambiguities, rerun the baseline once on the frozen panel, then execute targeted robustness specifications.
A8: 4 | B8: Literature, methods and framing | C8: MR-11, MR-12, MR-13, MR-15, MR-21, MR-26, MR-31, MR-32, MR-34 | D8: Correct causal language/citations; explain panel balance; sharpen gap/question; create construct-proxy map; add bounded literature and Brazil mechanisms. | E8: Revised Introduction and Chapters 3-4 | F8: Can proceed partly in parallel; final wording after Phase 3 | G8: Keep evidence separate from mechanisms; no theoretical redesign.
A9: 5 | B9: Results and conclusion rewrite | C9: MR-19, MR-22, MR-24, MR-30, MR-33 | D9: Rebuild tables; link every hypothesis to final results; explain counterintuitive signs; add scorecard and final QA. | E9: Revised Chapters 5-6, abstract/resumen and copy-edit | F9: Phases 3 and 4 | G9: Run table-to-text, hypothesis-to-result and terminology checks.
A10: 6 | B10: Replication, response and seminars | C10: MR-27, MR-30, MR-31, MR-32; response-only MR-05, MR-08, MR-10, MR-20, MR-29 | D10: Clean-run the package; finalize a three-juror response memo; prepare the agreed single DK table and concise Bordeaux/Geneva materials; confirm exact resubmission deadline/branch. | E10: Submission-ready thesis + package + response memo + agreed seminar table/deck + deadline checklist | F10: All prior phases | G10: Every comment has a change or reasoned non-change; deadlines and formal resolutions are confirmed.

Sheet Estimation Plan
A1: Paper/Seminar Estimation Plan - updated 2-Oct-2026 (Data Freeze Gate active)
A2: Source: Martin Grandes WhatsApp messages through 27-Sep-2026 plus completed WP-02/WP-03 work, the WP-04 data package, and completed pre-freeze audits for VIX, nominal Fed 3M Forward and nominal USD/BRL. Core output remains one FE-Driscoll-Kraay table, but estimation is intentionally deferred until the Econometric Panel Data Freeze Gate passes. Current audit: GDP YoY, followed by the remaining baseline regressors. If RER is used in the final core specification, its construction must be audited separately before panel freeze. WP-04 Brazil 3M DI data remain ready for later referee-only robustness after the panel freeze.
A4: Core four-model template (attachment transcribed exactly; implementation notes flag unresolved points)
A5: Variable / statistic | B5: Model 1 | C5: Model 2 | D5: Model 3 | E5: Model 4 | F5: Decision | G5: Implementation note
A6: Estimator | B6: FE-DK | C6: FE-DK | D6: FE-DK | E6: FE-DK | F6: Required | G6: Bond fixed effects with Driscoll-Kraay standard errors only.
A7: VIX | B7: x | C7: x | D7: x | E7: x | F7: Core | G7: Pre-freeze MR-09/WP-06 audit passed: VIX Index source/ticker, 187/187 monthly history, month-end convention, 4,229/4,229 panel mapping, raw index-point scaling and economic label/H1 wording are validated. Keep VIX in all four core columns. Raw/partial correlations and final sign/H1 interpretation wait for post-freeze DK results.
A8: FED3M Forward (nominal) | B8: x | C8: x | D8: x | E8: x | F8: Core | G8: PRE-FREEZE AUDIT PASSED. Baseline fed_3m_forward is Bloomberg USSOC Curncy / PX_LAST, the 3M USD OIS fixed rate. Native daily history and last-available month-end convention validated; 164/164 distinct panel months match exactly (0 mismatches; max abs diff 0.0). Baseline uses Bloomberg percentage-point values directly with no rescaling/log/standardization; D.fed_3m_forward exists only in the separate macro-differences robustness. Keep the thesis-facing label “Fed 3M Forward” for readability, but define it technically as the 3M USD OIS and state explicitly that it is forward-looking in economic content, not a forward-starting 3Mx3M rate. Keep the nominal market rate; do not reintroduce the old real construction.
A9: FED3M Forward Real (old construction) | B9: - | C9: - | D9: - | E9: - | F9: Exclude | G9: Do not use: inflation adjustment was not horizon-consistent with the 3-month forward rate.
A10: USD/BRL NER | B10: x | F10: Attachment | G10: PRE-FREEZE AUDIT PASSED FOR CURRENT NOMINAL NER. Source workbook identifies USDBRL Curncy (BRL per USD); 187 uninterrupted monthly source observations from Jan-2010 to Jul-2025; all timestamps follow the last-weekday month-end convention; panel usd_brl maps exactly across 4,229 rows / 164 months with 0 blanks, 0 within-month conflicts, 0 missing source months and 0 mismatches. Baseline uses the level directly with no log/rescaling/standardization; D.usd_brl is macro-differences robustness only. Label as nominal USD/BRL (BRL per USD); an increase denotes BRL depreciation. Original Bloomberg formula/raw layer is not retained in the values-only workbook.
A11: USD/BRL RER | B11: x | C11: x | E11: x | F11: Confirm | G11: RER remains a separate construction from the audited nominal NER. If Martin's final specification replaces NER with RER, complete a separate six-step RER audit before the panel is frozen; do not infer RER validity from the nominal USD/BRL audit.
A12: GDP growth (YoY) | B12: x | C12: x | E12: x | F12: Attachment | G12: CURRENT DATA FREEZE AUDIT. Apply source/ticker -> raw series -> monthly convention -> panel match -> transformation/scaling -> economic label before any regression rerun.
A13: Public debt / GDP | B13: x | C13: x | E13: x | F13: Attachment | G13: Domestic macro robustness block.
A14: Sovereign Risk (BRL) | B14: x | C14: x | D14: x | F14: Core - validated | G14: Closed 29-Sep-2026: sovereign_spread_brl = nominal government YTM minus same-date DI reference yield at exact BUS/252 tenor; 252 LTN + 330 NTN-F = 582/582 reproduced. Thesis documentation and terminology are aligned; no CDS label; corporate IPCA-real benchmark remains distinct.
A15: Cash flow / assets | B15: x | C15: x | D15: x | E15: x | F15: Attachment | G15: Firm control included in every attached column.
A16: Relative issue size (AMT_ISSUED / BS_TOT_ASSET, ‰) | B16: x | C16: x | D16: x | E16: x | F16: Retain - audited | G16: Closed WP-03 on 30-Sep-2026. Reconstructed 4,229/4,229 observations from raw AMT_ISSUED and quarterly BS_TOT_ASSET; 98/103 bonds (95.15%) vary within bond, so the ratio is identified in bond FE. Interpret as relative issue size versus issuer scale, not a change in AMT_ISSUED. Q-1 BS_TOT_ASSET robustness: 4,223/4,229 available, corr=0.9918, same 98/103 within-varying bonds.
A17: Debt / EBITDA | B17: x | C17: x | D17: x | E17: x | F17: Attachment | G17: Firm control included in every attached column.
A18: Residual bond maturity | B18: x | C18: x | D18: x | E18: x | F18: Attachment | G18: Bond control included in every attached column.
A19: Within R-squared | B19: report | C19: report | D19: report | E19: report | F19: Required | G19: Explicitly requested in the attachment.
A20: rho | B20: report | C20: report | D20: report | E20: report | F20: Required | G20: Explicitly requested in the attachment.
A21: Diagnostics / DK metadata | B21: below | C21: below | D21: below | E21: below | F21: Required | G21: Show diagnostic tests, DK lag and panel dimensions with the table.
A24: Optional SELIC 3M Forward robustness checks (secondary to the core four models)
A25: Element | B25: Model 5 | C25: Model 6 | D25: Status | E25: Required exclusion | F25: Open point | G25: Implementation note
A26: SELIC 3M Forward | B26: include | C26: include | D26: Prepared; regression deferred | E26: - | F26: Proxy sourced/documented: YCSW0089 Index 3M (Brazil 3M DI). Do not merge/run Models 5-6 until all baseline regressors are audited and the authoritative panel is frozen. | G26: Referee-only low-cost diagnostic proposed by Martin, not the preferred baseline. Use the 3M point of Bloomberg BM&F Pre x DI curve as the forward-looking domestic short-rate proxy; do not label it a literal 3Mx6M forward-starting SELIC rate. After data freeze and the core baseline rerun, validate panel alignment/correlations/VIF and decide whether it is informative enough to report.
A27: FED3M Forward (nominal) | B27: retain | C27: omit | D27: Specified | E27: Model 6 omits it | F27: - | G27: Second SELIC variant removes FED3M as well.
A28: FX (NER/RER) | B28: omit | C28: omit | D28: Specified | E28: Both models omit FX | F28: - | G28: Required by Martin.
A29: Sovereign Risk (BRL) | B29: omit | C29: omit | D29: Specified | E29: Both models omit sovereign spread | F29: - | G29: Required by Martin.
A30: Other macro and firm/bond controls | B30: base set | C30: base set | D30: Confirm | E30: - | F30: Exact retained block not fully stated | G30: Use the selected base column only after confirmation.
A32: Implementation controls and unresolved source points
A33: # | B33: Control / ambiguity | C33: Status | D33: Required decision or evidence | E33: Owner | F33: Target | G33: Source
A34: 1 | B34: Use nominal FED3M Forward; exclude old real series | C34: Resolved | D34: Implement nominal series in all four core models | E34: Thiago | F34: Before estimation | G34: Martin 25-Sep
A35: 2 | B35: One table only; no separate plain-FE or PCSE columns | C35: Resolved | D35: Use FE-DK columns and place diagnostics below | E35: Thiago | F35: 30-Sep-2026 | G35: Martin 25-Sep
A36: 3 | B36: PCSE rationale | C36: Resolved | D36: Document imbalance and limited common overlap; retain audit only internally | E36: Thiago | F36: Response memo | G36: Martin 25-Sep
A37: 4 | B37: Model 1 contains both NER and RER in attachment | C37: Confirm | D37: Ask whether Model 1 should contain NER, RER or both | E37: Thiago + Martin | F37: Before final code | G37: Attached table
A38: 5 | B38: Stacking text versus controls in all attached columns | C38: Confirm | D38: Map external -> domestic/sovereign -> firm/bond sequence to final columns | E38: Thiago + Martin | F38: Before final code | G38: Martin + table
A39: 6 | B39: No separate inflation term in paper exercise | C39: Clarify wording | D39: Verify consistency with IPCA-linked yield units and thesis notation | E39: Thiago + Martin | F39: Before writing | G39: Martin 25-Sep
A40: 7 | B40: NER and RER reportedly similar | C40: Verify | D40: Confirm on regenerated corrected-spread estimates | E40: Thiago | F40: With core table | G40: Martin 25-Sep
A41: 8 | B41: Core table delivery | C41: Target | D41: Send one consolidated table with diagnostics and statistics | E41: Thiago | F41: 30-Sep-2026 | G41: Martin 25-Sep
A42: 9 | B42: Sovereign Risk (BRL) definition / old synthetic-CDS label | C42: Implementation validated; text pending | D42: Code audit complete: 582/582 LTN+NTN-F observations reproduce government YTM minus same-date exact-tenor DI reference yield; exact-node guard added and tests pass. Remaining: document currency/indexation treatment, rename/remove synthetic-CDS terminology in thesis/outputs, and verify USD CDS 5Y absence in code/specifications. | E42: Thiago | F42: Before estimation | G42: Martin audio 25-Sep
A43: 10 | B43: USD CDS 5Y in the economic model | C43: Deferred final-panel integrity check | D43: Martin confirms USD CDS 5Y was never part of the economic model. Keep a final code/specification search immediately before estimation to confirm it is absent everywhere; do not add it as a main or secondary control. This is a final-panel integrity check and no longer an open WP-02 closure condition. | E43: Thiago | F43: Before final estimation | G43: Martin audio 25 & 27-Sep
A44: 11 | B44: Common-reference two-spread specification | C44: Specification intent resolved; reconciliation pending | D44: Document the preferred two-spread transmission specification, but first reconcile the phrase 'same local reference curve' with the implemented data: the corporate dependent variable is IPCA-linked and benchmarked to the real IPCA reference curve, while the validated nominal sovereign series uses LTN/NTN-F versus the DI curve. Do not claim an identical benchmark unless the indexation-consistent mapping is explicitly demonstrated. Then support the chosen formulation with literature. | E44: Thiago | F44: Before final estimation/write-up | G44: Martin audio 27-Sep
A45: 12 | B45: SELIC 3M Forward role | C45: Resolved - referee only | D45: Run only as an optional referee diagnostic under the specified exclusions; do not treat it as baseline; decide whether to show/publish only if informative. | E45: Thiago | F45: After data freeze and core table / if time permits | G45: Martin audio 27-Sep
A46: 13 | B46: Econometric Panel Data Freeze Gate | C46: Active | D46: Before any final baseline or robustness regression, close or explicitly accept unchanged all baseline explanatory-variable audits; rebuild/finalize panel_main_and_robustness.xlsx once; verify source/units/date mapping and run the final code/specification integrity checks. Only then rerun the core FE-DK table and targeted robustness checks. | E46: Thiago | F46: Before any final estimation | G46: Workflow sequencing decision 1-Oct-2026

Sheet v4 Change Log
A1: v4 Change Log
A2: Exact changes merged from Martin Grandes' 24-Sep-2026 messages after he read Daniel Milia's report.
A3: Change ID | B3: Date | C3: Topic | D3: Sheets / rows affected | E3: What changed
A4: v4-01 | B4: 24-Sep-2026 | C4: Daniel overall priority | D4: Director Guidance; README; Dashboard | E4: Recorded Martin's assessment that Daniel is less substantive than Ailin and Maximo and should be handled selectively after the core empirical work.
A5: v4-02 | B5: 24-Sep-2026 | C5: Hypothesis-result linkage | D5: MR-09, MR-19, MR-30, MR-31, MR-32; WP-06, WP-13, WP-14 | E5: Added an explicit requirement to link each hypothesis to final results and classify evidence as robust, partial/sensitive, null or unresolved.
A6: v4-03 | B6: 24-Sep-2026 | C6: Counterintuitive signs | D6: MR-01, MR-09, MR-19, MR-26, MR-30 | E6: Made clearer sign explanations a required downstream narrative task.
A7: v4-04 | B7: 24-Sep-2026 | C7: Heteroskedasticity and diagnostics | D7: MR-16; WP-07 | E7: Recorded that the problem was already treated in substance; the revision must make diagnostics and the correction visible.
A8: v4-05 | B8: 24-Sep-2026 | C8: Minor bibliography | D8: MR-11, MR-21, MR-34; WP-11 | E8: Reclassified Daniel bibliography requests as bounded, targeted corrections rather than a literature overhaul.
A9: v4-06 | B9: 24-Sep-2026 | C9: SELIC disposition | D9: MR-04, MR-26; MG-10; WP-04 | E9: Changed SELIC from a possible robustness variable to an explicit separate-regressor non-inclusion: it is part of the short end and potentially redundant.
A10: v4-07 | B10: 24-Sep-2026 | C10: Sovereign ceiling | D10: MR-01, MR-02; MG-11; WP-02 | E10: Added Martin's sovereign-ceiling framing and its link to the corporate excess/shortfall over the sovereign.
A11: v4-08 | B11: 24-Sep-2026 | C11: Matched YTM alternative | D11: MR-01; WP-02; Action Sequence | E11: Added the alternative corporate-YTM-on-sovereign-YTM interpretation with same tenor, currency and approximately the same coupon, plus literature justification.
A12: v4-09 | B12: 24-Sep-2026 | C12: DK-only main estimator | D12: MR-16, MR-17, MR-23; MG-12; WP-07 | E12: Specified Driscoll-Kraay as the only main estimator and added a short explanation for discarding PCSE.
A13: v4-10 | B13: 24-Sep-2026 | C13: Seminar specifications | D13: MR-18; MG-12; WP-08, WP-16 | E13: Added real exchange rate and with/without macro controls correlated with local sovereign risk for Bordeaux/Geneva.
A14: v4-11 | B14: 24-Sep-2026 | C14: Priority sequence | D14: Dashboard; Action Sequence | E14: Kept WP-01 current, then elevated Maximo-driven spread/sovereign construction before Daniel-only exposition.
A15: v4-12 | B15: 24-Sep-2026 | C15: Source-of-truth update | D15: All tabs | E15: Merged the latest WhatsApp guidance without adding duplicate master issues or work packages.

Sheet v5 Change Log
A1: v5 Change Log
A2: Exact changes merged from Martin Grandes' 25-Sep-2026 messages and attached estimation table.
A3: Change ID | B3: Date | C3: Topic | D3: Sheets / rows affected | E3: What changed
A4: v5-01 | B4: 25-Sep-2026 | C4: PCSE rationale confirmed | D4: MR-16, MR-17; MG-13; WP-07 | E4: Recorded Martin's acceptance of the imbalance/common-overlap rationale and retained PCSE only for internal audit, not the main output.
A5: v5-02 | B5: 25-Sep-2026 | C5: Single FE-DK table | D5: MR-16, MR-18, MR-24; MG-14; WP-07/08/12 | E5: Specified one consolidated FE-Driscoll-Kraay table and removed separate plain-FE and PCSE columns.
A6: v5-03 | B6: 25-Sep-2026 | C6: FED3M variable correction | D6: MR-18; MG-15; WP-08; Estimation Plan | E6: Replaced the old FED3M Forward Real construction with nominal FED3M Forward for the requested exercise.
A7: v5-04 | B7: 25-Sep-2026 | C7: SELIC baseline and optional checks | D7: MR-04, MR-26; MG-16; WP-04/08 | E7: Preserved SELIC exclusion from the baseline but added two explicitly scoped optional SELIC 3M Forward robustness columns.
A8: v5-05 | B8: 25-Sep-2026 | C8: Exact four-model grid | D8: MR-18, MR-24; MG-17/19; Estimation Plan | E8: Transcribed the attached four-column variable grid and required Within R-squared/rho outputs.
A9: v5-06 | B9: 25-Sep-2026 | C9: FX and inflation treatment | D9: MR-01, MR-18, MR-26; MG-18 | E9: Recorded the requested RER robustness, NER/RER similarity to verify, and the instruction not to add a separate inflation term.
A10: v5-07 | B10: 25-Sep-2026 | C10: Source ambiguities preserved | D10: MR-18; WP-08; Estimation Plan | E10: Flagged Model 1 NER+RER and stacking-versus-all-controls inconsistencies for confirmation rather than silently changing the source.
A11: v5-08 | B11: 25-Sep-2026 | C11: Near-term target | D11: Process & Deadlines; Dashboard; WP-08/16 | E11: Added the requested Wednesday target of 30-Sep-2026 for the consolidated result table.
A12: v5-09 | B12: 25-Sep-2026 | C12: New Estimation Plan sheet | D12: README; Estimation Plan | E12: Added an implementation-ready grid with core models, optional SELIC checks, controls, ambiguities and source traceability.
A13: v5-10 | B13: 25-Sep-2026 | C13: Source-of-truth update | D13: All relevant tabs | E13: Merged the latest director instructions without creating duplicate jury issues or work packages.

Sheet v6 Change Log
A1: v6 Change Log
A2: Changes merged from Martin Grandes' 25-Sep-2026 audio clarifying the sovereign-risk construction and the transition from WP-01 to WP-02.
A3: Change ID | B3: Date | C3: Topic | D3: Sheets / rows affected | E3: What changed
A4: v6-01 | B4: 25-Sep-2026 | C4: Definitive Sovereign Risk (BRL) definition | D4: MR-01, MR-02; MG-03, MG-11, MG-20; WP-02; Estimation Plan | E4: Resolved the conceptual ambiguity: the sovereign regressor is government-bond YTM minus the matched local risk-free/reference curve yield, not a CDS.
A5: v6-02 | B5: 25-Sep-2026 | C5: Synthetic CDS terminology removed from design | D5: MR-02; WP-02; Overlap Map; Estimation Plan | E5: Reclassified "synthetic CDS BRL" as a misnomer and required consistent renaming to Sovereign Risk (BRL) / local-currency sovereign spread.
A6: v6-03 | B6: 25-Sep-2026 | C6: Dependent-variable interpretation corrected | D6: MR-01; MG-11; WP-02 | E6: Superseded the v5 ambiguity: Corporate YTM versus matched Sovereign YTM is an equivalent sovereign-ceiling framing/check, not a replacement for the corporate-spread dependent variable.
A7: v6-04 | B7: 25-Sep-2026 | C7: USD CDS 5Y main-model treatment | D7: MR-01, MR-02; MG-03, MG-20; Estimation Plan | E7: Recorded Martin's stronger instruction that the external USD sovereign CDS should not enter the main model.
A8: v6-05 | B8: 25-Sep-2026 | C8: WP-01 to WP-02 workflow handoff | D8: README; Dashboard; Revision Tracker; Action Sequence | E8: Marked the corporate-spread measurement audit as closed and activated the sovereign-risk code/formula audit as the current work package.
A9: v6-06 | B9: 25-Sep-2026 | C9: Implementation gate before re-estimation | D9: WP-02; Estimation Plan; Action Sequence | E9: Added an explicit pre-estimation gate: verify government-minus-reference formula, maturity/tenor matching and currency/indexation consistency in code before running the DK table.
A10: v6-07 | B10: 25-Sep-2026 | C10: Director traceability | D10: Director Guidance | E10: Added MG-20 with the definitive construction and strengthened earlier sovereign-risk guidance without erasing the historical record.
A11: v6-08 | B11: 25-Sep-2026 | C11: Source-of-truth reconciliation | D11: README; Master Matrix; Overlap Map; v6 Change Log | E11: Merged the latest audio into existing issues rather than creating duplicate jury items; v5 remains preserved as the prior snapshot.

Sheet v7 Change Log
A1: v7 Change Log
A2: Changes merged from Martin Grandes' 27-Sep-2026 audio clarifying the preferred two-spread specification, USD CDS status and SELIC referee check.
A3: Change ID | B3: Date | C3: Topic | D3: Sheets / rows affected | E3: What changed
A4: v7-01 | B4: 27-Sep-2026 | C4: USD CDS 5Y status | D4: MR-01, MR-02; MG-03, MG-20, MG-21; WP-02; Estimation Plan | E4: Corrected the record: USD CDS 5Y was never part of the economic model. The workbook now requires verification of absence rather than treating it as a possible secondary/main control.
A5: v7-02 | B5: 27-Sep-2026 | C5: Preferred common-reference two-spread model | D5: MR-01; MG-11, MG-20, MG-21; WP-02; Overlap Map; Action Sequence | E5: Specified Corporate Spread = corporate YTM - local reference yield and Sovereign Risk = government YTM - the same matched reference yield, kept as separate variables so the model estimates the response of corporate spread to sovereign risk.
A6: v7-03 | B6: 27-Sep-2026 | C6: Direct corporate-sovereign differential reclassified | D6: MR-01; MG-11; WP-02; Estimation Plan | E6: Replaced the earlier shorthand that the matched corporate-sovereign formulation was econometrically equivalent. It is a related alternative, but not the preferred specification.
A7: v7-04 | B7: 27-Sep-2026 | C7: Literature justification added | D7: MR-01, MR-02; WP-02; Action Sequence; Estimation Plan | E7: Added an explicit requirement to justify the common-reference two-spread transmission specification with literature before final re-estimation/write-up.
A8: v7-05 | B8: 27-Sep-2026 | C8: SELIC embedded in local curve | D8: MR-02, MR-04, MR-26; MG-10, MG-16, MG-21; WP-04 | E8: Strengthened the explanation that SELIC anchors the short end of the local reference curve and its influence is already embedded in the curve used by the model.
A9: v7-06 | B9: 27-Sep-2026 | C9: SELIC 3M Forward is referee-only | D9: MR-04, MR-18; MG-16, MG-21; WP-04, WP-08; Estimation Plan | E9: Narrowed the SELIC 3M Forward exercise to an optional referee diagnostic. It is not a baseline extension and should be shown/published only if informative.
A10: v7-07 | B10: 27-Sep-2026 | C10: Director traceability | D10: Director Guidance | E10: Added MG-21 and updated earlier guidance rows to preserve the latest director interpretation without creating new juror issues or work packages.
A11: v7-08 | B11: 27-Sep-2026 | C11: Source-of-truth reconciliation | D11: README; Dashboard; Revision Tracker; Master Matrix; Overlap Map; Action Sequence; Process & Deadlines | E11: Updated version/date/source notes and kept WP-02 as the active package; v6 remains preserved as the prior snapshot.

Sheet v8 Change Log
A1: v8 Change Log
A2: Changes from the 29-Sep-2026 nominal sovereign-risk implementation audit, exact-node interpolation fix, and WP-02 status reconciliation.
A3: Change ID | B3: Date | C3: Topic | D3: Sheets / rows affected | E3: What changed
A4: v8-01 | B4: 29-Sep-2026 | C4: Nominal sovereign implementation validated | D4: WP-02; MR-01, MR-02; Estimation Plan; Action Sequence | E4: Validated 252 LTN + 330 NTN-F observations (582 total): same-date DI benchmark at exact BUS/252 residual tenor, 0 missing benchmarks, 582/582 reproduced to numerical precision, and geometric spread arithmetic independently confirmed.
A5: v8-02 | B5: 29-Sep-2026 | C5: DI exact-node interpolation hardened | D5: Interpolation helper; WP-02 evidence | E5: Added an exact/near-node guard after identifying floating-point behavior when a requested tenor coincides with a raw DI market node. Regenerated outputs and re-audited the full sample.
A6: v8-03 | B6: 29-Sep-2026 | C6: WP-02 status split | D6: README; Dashboard; Revision Tracker; Master Matrix | E6: Kept WP-02 In progress while explicitly closing the implementation/code component. Remaining closure items are thesis terminology, equations/literature, USD CDS code-absence verification, and reference-curve/indexation reconciliation.
A7: v8-04 | B7: 29-Sep-2026 | C7: Common-reference wording flagged | D7: MR-01; WP-02; Overlap Map; Estimation Plan | E7: Flagged that the implemented corporate dependent variable is IPCA-linked and uses the real IPCA benchmark, while the validated nominal sovereign series uses LTN/NTN-F versus the DI curve. The thesis must reconcile this before claiming both spreads use an identical local reference curve.
A8: v8-05 | B8: 29-Sep-2026 | C8: Validation and Git milestone | D8: WP-02 evidence | E8: Full pytest suite passed 5/5 after the interpolation fix. Commit b551414 (Refactor nominal DI interpolation and sovereign spreads) was pushed to branch jury-revision-recalculate-corporate-spread.

Sheet v9 Change Log
A1: v9 Change Log
A2: Changes from the 29-Sep-2026 WP-02 closure, thesis terminology/indexation cleanup, and workflow handoff to WP-03.
A3: Change ID | B3: Date | C3: Topic | D3: Sheets / rows affected | E3: What changed
A4: v9-01 | B4: 29-Sep-2026 | C4: WP-02 closed | D4: README; Dashboard; Revision Tracker; Master Matrix | E4: Closed WP-02 after validated 582/582 nominal sovereign observations, formula/unit tests, exact-node hardening, thesis terminology cleanup, and documentation of the nominal DI sovereign versus IPCA-real corporate benchmark distinction.
A5: v9-02 | B5: 29-Sep-2026 | C5: Sovereign variable terminology finalized | D5: WP-02; MR-01, MR-02; thesis edits | E5: Adopted sovereign_spread_brl / sovereign risk in local currency. Removed synthetic-CDS language from methodology, appendix, results labels, diagrams and Mermaid source; clarified that the measure is a local BRL sovereign spread, not a CDS.
A6: v9-03 | B6: 29-Sep-2026 | C6: Reference-curve/indexation wording reconciled | D6: MR-01; Overlap Map; Action Sequence | E6: Replaced the inaccurate claim that corporate and sovereign spreads use an identical reference curve. Corporate spread uses an IPCA-real matched benchmark; sovereign_spread_brl uses nominal LTN/NTN-F versus the DI reference curve. Each is matched to its own indexation/tenor.
A7: v9-04 | B7: 29-Sep-2026 | C7: WP-03 activated | D7: Revision Tracker; Dashboard; Action Sequence | E7: Set WP-03 to In progress. Next gate is to audit amount_issued_to_asset construction and within-bond variation before deciding whether it is identified in bond fixed effects.
A8: v9-05 | B8: 29-Sep-2026 | C8: Regression rerun deferred | D8: Estimation Plan; Action Sequence | E8: Confirmed sequencing: finish all explanatory-variable audits first, freeze the final panel, then rerun FE/Driscoll-Kraay once. USD CDS 5Y absence is retained only as a final pre-estimation integrity check and does not keep WP-02 open.

Sheet v10 Change Log
A1: v10 Change Log
A2: Changes from the 30-Sep-2026 WP-03 issue-size audit closure, thesis consistency update, and workflow handoff to WP-04.
A3: Change ID | B3: Date | C3: Topic | D3: Sheets / rows affected | E3: What changed
A4: v10-01 | B4: 30-Sep-2026 | C4: WP-03 closed | D4: README; Dashboard; Revision Tracker; Master Matrix; Action Sequence | E4: Closed the issue-size identification package after tracing AMT_ISSUED and BS_TOT_ASSET through the final panel, reconstructing 4,229/4,229 observations, and confirming within-bond variation for 98/103 bonds (95.15%).
A5: v10-02 | B5: 30-Sep-2026 | C5: Relative issue-size interpretation and units finalized | D5: MR-14; WP-03; Estimation Plan; thesis edits | E5: Retained amount_issued_to_bs_tot_asset as relative issue size rather than time-invariant amount issued; documented that within variation comes from quarterly issuer assets; standardized the scale as per-mille (‰) and the coefficient interpretation as relative size versus issuer scale.
A6: v10-03 | B6: 30-Sep-2026 | C6: Timing robustness documented | D6: WP-03; MR-14; Estimation Plan | E6: Constructed a one-quarter-lagged BS_TOT_ASSET denominator check: 4,223/4,229 observations available, correlation 0.9918 with the original ratio, and the same 98/103 bonds with within variation. Kept it as robustness rather than replacing the main regressor.
A7: v10-04 | B7: 30-Sep-2026 | C7: Thesis-side WP-03 consistency confirmed | D7: MR-14 thesis locations; Tables 3/7; Figure 3; Annex 8.6.2 | E7: Confirmed the latest thesis aligns H6, methodology, FE identification, results, conclusions, tables, Figure 3 and the annex with the audited construction and cautious liquidity-proxy interpretation.
A8: v10-05 | B8: 30-Sep-2026 | C8: WP-04 activated | D8: README; Dashboard; Revision Tracker; Master Matrix; Action Sequence; Estimation Plan | E8: Set WP-04/MR-04 to In progress. Current task is the baseline SELIC non-inclusion rationale plus the bounded referee-only SELIC 3M Forward diagnostic(s). Final regression rerun remains deferred until the remaining explanatory-variable audits are complete.

Sheet v11 Change Log
A1: TFM Master Revision Matrix - v11 Change Log
A2: Changes introduced on 1-Oct-2026 after inserting the WP-04 SELIC baseline non-inclusion rationale into thesis Section 4.5.3. WP-04 is not yet closed because the referee-only SELIC 3M Forward diagnostics remain pending.
A4: ID | B4: Date | C4: Change | D4: Affected items | E4: Detail
A5: v11-01 | B5: 1-Oct-2026 | C5: SELIC baseline rationale inserted | D5: WP-04; MR-04; thesis Sec. 4.5.3 | E5: Added an explicit rationale immediately after Fed 3M Forward: SELIC is excluded from the baseline because domestic monetary conditions are partly embedded in the short end of the local reference curve and may overlap with the external-rate/FX block.
A6: v11-02 | B6: 1-Oct-2026 | C6: WP-04 remains open | D6: Dashboard; Revision Tracker; Action Sequence | E6: Did not close WP-04. Remaining gate is to identify/audit the SELIC 3M Forward series and run the two scoped referee-only diagnostics before moving to WP-05.
A7: v11-03 | B7: 1-Oct-2026 | C7: SELIC diagnostic scope preserved | D7: Estimation Plan | E7: Model 5: include SELIC 3M Forward and retain nominal FED3M; Model 6: include SELIC 3M Forward and omit FED3M. Both omit FX and Sovereign Risk (BRL). Review correlations/VIF and incremental information before deciding whether to report.

Sheet v12 Change Log
A1: TFM Master Revision Matrix - v12 Change Log
A2: Changes introduced on 1-Oct-2026 after identifying, validating, downloading and documenting the Brazil 3M DI referee-only robustness proxy for WP-04. WP-04 remains open pending panel merge, diagnostics and Models 5-6.
A4: ID | B4: Date | C4: Change | D4: Affected items | E4: Detail
A5: v12-01 | B5: 1-Oct-2026 | C5: Brazil 3M DI proxy identified | D5: WP-04; MR-04; Estimation Plan | E5: Operationalized the referee-only domestic short-rate proxy as the 3M point of Bloomberg BM&F Pre x DI curve YCSW0089 Index. Explicitly distinguished it from a literal 3Mx6M forward-starting SELIC rate.
A6: v12-02 | B6: 1-Oct-2026 | C6: Historical series downloaded | D6: WP-04; data acquisition | E6: Validated YCSW0089 Index 3M in BQNT and downloaded the complete monthly Dec-2010 to Dec-2025 series. Historical DI curve-member tickers were retained for auditability.
A7: v12-03 | B7: 1-Oct-2026 | C7: Reproducibility package added | D7: WP-04; data documentation | E7: Created TFM_WP04_Brazil_3M_DI_YCSW0089.ipynb and README.md documenting Bloomberg/BQL source, units, construction, terminology, and intended referee-only use.
A8: v12-04 | B8: 1-Oct-2026 | C8: WP-04 remains open | D8: Dashboard; Revision Tracker; Action Sequence; Estimation Plan | E8: Data acquisition is complete, but WP-04 is not closed. Remaining gate: merge brazil_3m_di into the panel, validate date/scaling consistency, review correlations/VIF, run Model 5 and Model 6, and assess incremental information before reporting.

Sheet v13 Change Log
A1: TFM Master Revision Matrix - v13 Change Log
A2: Changes introduced on 1-Oct-2026 after adopting the Econometric Panel Data Freeze Gate. WP-04 data/rationale preparation is complete but its regression stage is parked until post-freeze robustness; WP-06 / MR-09 (VIX) is now the active audit.
A4: ID | B4: Date | C4: Change | D4: Affected items | E4: Detail
A5: v13-01 | B5: 1-Oct-2026 | C5: Econometric Panel Data Freeze Gate adopted | D5: README; Dashboard; Action Sequence; Estimation Plan | E5: Final baseline, diagnostics and robustness regressions are blocked until all baseline explanatory-variable audits are closed or explicitly accepted unchanged and panel_main_and_robustness.xlsx is rebuilt/frozen as the authoritative input.
A6: v13-02 | B6: 1-Oct-2026 | C6: WP-04 regression stage parked | D6: WP-04; MR-04; Estimation Plan | E6: Kept the completed SELIC rationale and Brazil 3M DI data/reproducibility package, but changed the regression-dependent stage to Deferred. Models 5-6 will run only after the data freeze and core baseline rerun.
A7: v13-03 | B7: 1-Oct-2026 | C7: VIX audit activated | D7: WP-06; MR-09; Dashboard; Estimation Plan | E7: Activated VIX as the current explanatory-variable audit. Required sequence is source/ticker -> raw series -> monthly convention -> panel match -> transformation/scaling -> economic label; final sign interpretation waits for post-freeze DK results.
A8: v13-04 | B8: 1-Oct-2026 | C8: Estimation sequence revised to avoid rework | D8: Revision Tracker; Action Sequence; Estimation Plan | E8: New sequence: audit/finalize explanatory variables -> freeze authoritative panel -> rerun baseline FE-DK once -> diagnostics -> targeted robustness, including the referee-only Brazil 3M DI exercise.

Sheet v14 Change Log
A1: TFM Master Revision Matrix - v14 Change Log
A2: Changes introduced on 2-Oct-2026 after completing the pre-freeze VIX data/proxy audit, correcting the thesis VIX/H1 wording, and continuing the Econometric Panel Data Freeze Gate with the remaining baseline-regressor audits.
A4: ID | B4: Date | C4: Change | D4: Affected items | E4: Detail
A5: v14-01 | B5: 2-Oct-2026 | C5: VIX source and monthly-history audit completed | D5: WP-06; MR-09; README; Dashboard | E5: Confirmed macro_explanatory_variables.xlsx / VIX Index. Bloomberg field metadata is not preserved in the values-only workbook. Independent validation found 187/187 monthly values from Jan-2010 to Jul-2025 equal to FRED VIXCLS at the last available daily close; workbook dates use the last weekday of each month as the monthly label.
A6: v14-02 | B6: 2-Oct-2026 | C6: VIX panel mapping and scaling validated | D6: WP-06; MR-09; Estimation Plan | E6: Matched 4,229/4,229 panel rows exactly across 164 distinct panel months, with no missing or conflicting within-month VIX values. Stata uses VIX in raw index points; no log, standardization, divide-by-100 or differencing is applied.
A7: v14-03 | B7: 2-Oct-2026 | C7: VIX terminology and H1 framing corrected | D7: WP-06; MR-09; thesis Sections 3-5 | E7: Reframed VIX as expected 30-day S&P 500 implied volatility used as a parsimonious proxy for global financial stress, not pure risk aversion. H1/Table 1 and VIX result labels were updated accordingly while preserving the positive ex-ante sign prediction.
A8: v14-04 | B8: 2-Oct-2026 | C8: Data Freeze Gate handed to remaining regressors | D8: Dashboard; Action Sequence; Estimation Plan | E8: MR-09 remains In progress only for post-freeze raw/partial correlations and final DK sign/H1 interpretation. No final sign narrative is accepted yet. Continue the pre-freeze audit with nominal Fed 3M Forward, then the remaining baseline regressors; do not rerun final baseline or robustness models before the gate passes.

Sheet v15 Change Log
A1: v15 Change Log
A2: Changes introduced on 2-Oct-2026 after identifying and independently validating the Bloomberg source for nominal Fed 3M Forward and completing the raw-series and monthly-convention stages of the Data Freeze Gate.
A4: ID | B4: Date | C4: Change | D4: Affected items | E4: Detail
A5: v15-01 | B5: 2-Oct-2026 | C5: Fed 3M Forward Bloomberg source identified | D5: WP-06; MR-09; Estimation Plan | E5: Identified the baseline panel series as Bloomberg USSOC Curncy, field PX_LAST, the 3M USD OIS fixed rate. BQNT reproduces panel spot-check values exactly to four decimals. FEDL01 Index is explicitly rejected as the source because it is the effective Fed Funds rate and does not match the panel series.
A6: v15-02 | B6: 2-Oct-2026 | C6: Fed raw-series audit completed | D6: WP-06; MR-09 | E6: Validated the native daily USSOC Curncy history over 2010-2025. The series is quoted in percentage points, has normal non-quotation-day gaps, and provides continuous coverage across the thesis sample.
A7: v15-03 | B7: 2-Oct-2026 | C7: Fed monthly convention validated | D7: WP-06; MR-09 | E7: Validated calendar-month-end extraction with the previous available quote used when month-end is not a quotation day. The resulting 2011 monthly values reproduce the panel exactly, including months whose panel date is the last business day.
A8: v15-04 | B8: 2-Oct-2026 | C8: Fed reproducibility package archived; audit remains open | D8: WP-06; MR-09; Dashboard; Action Sequence | E8: Committed the BQNT replication notebook and README in fb7748d under datos_y_modelos/db/brazil_macroeconomic_data/fed_3m_forward/. MR-09 remains In progress: Step 4 full-sample panel match, Step 5 transformation/scaling and Step 6 economic-label review still precede panel freeze and any regression rerun.

Sheet v16 Change Log
A1: TFM Master Revision Matrix - v16 Change Log
A2: Changes introduced on 2-Oct-2026 after completing the full six-step Fed 3M Forward Data Freeze audit, closing MR-09 as a proxy/data-definition issue, and handing the pre-freeze sequence to USD/BRL and the remaining baseline regressors.
A4: ID | B4: Date | C4: Change | D4: Affected items | E4: Detail
A5: v16-01 | B5: 2-Oct-2026 | C5: Fed full-sample panel match passed | D5: WP-06; MR-09; Data Freeze Gate | E5: Compared every distinct panel month to Bloomberg USSOC Curncy / PX_LAST by calendar month: 164/164 matched, 0 missing Bloomberg rows, 164 exact matches, 0 mismatches, maximum absolute difference 0.0.
A6: v16-02 | B6: 2-Oct-2026 | C6: Fed transformation/scaling validated | D6: WP-06; MR-09; Estimation Plan | E6: Confirmed the baseline uses fed_3m_forward directly in Bloomberg native percentage-point units. No divide-by-100, multiply-by-100, log, standardization or z-score is applied; D.fed_3m_forward is created only for the separate macro-differences robustness specification.
A7: v16-03 | B7: 2-Oct-2026 | C7: Fed economic label corrected without renaming shorthand | D7: WP-06; MR-09; thesis Sec. 4.5.3 | E7: Retained “Fed 3M Forward” as the intuitive thesis-facing shorthand, but replaced the inaccurate forward-curve construction text with the exact definition: Bloomberg USSOC Curncy / PX_LAST, 3M USD OIS fixed rate referencing EFFR, last available monthly close, forward-looking in economic content but not a forward-starting rate.
A8: v16-04 | B8: 2-Oct-2026 | C8: MR-09 closed; Data Freeze Gate moves to USD/BRL | D8: MR-09; WP-06; Dashboard; Action Sequence | E8: Closed MR-09 as a VIX/global-proxy data-definition issue after the VIX audit and companion Fed six-step audit. Post-freeze raw/partial correlations and final VIX sign/H1 interpretation are consolidated under MR-18/MR-19. WP-06 remains the active Data Freeze Gate container, with USD/BRL next; no final regression rerun yet.

Sheet v17 Change Log
A1: v17 Change Log
A2: Changes introduced on 2-Oct-2026 after completing the six-step nominal USD/BRL Data Freeze audit, documenting its provenance limitation, and handing the pre-freeze sequence to GDP YoY while preserving the separate RER audit dependency.
A4: ID | B4: Date | C4: Change | D4: Affected items | E4: Detail
A5: v17-01 | B5: 2-Oct-2026 | C5: USD/BRL source, raw series and month-end convention validated | D5: WP-06; Data Freeze Gate; Estimation Plan | E5: Macro workbook identifies “USDBRL Spot Exchange Rate - Price of 1 USD in BRL” / USDBRL Curncy. Original Bloomberg formula/raw source layer is not retained and repo search found no second ticker trace. Thesis-window source series has 187 uninterrupted monthly observations Jan-2010 to Jul-2025, no zeros/blanks/duplicate months, and all dates are the last weekday of the month.
A6: v17-02 | B6: 2-Oct-2026 | C6: USD/BRL full panel match passed | D6: WP-06; Data Freeze Gate | E6: Panel ts.usd_brl contains 0 blanks across 4,229 rows and 164 unique months (Dec-2010 to Jun-2025). Each month has one common FX value; no panel months are absent from the macro source; month-by-month comparison produced 0 mismatches.
A7: v17-03 | B7: 2-Oct-2026 | C7: USD/BRL scaling and economic label validated | D7: WP-06; Estimation Plan; thesis FX wording | E7: Baseline Stata uses usd_brl directly in nominal BRL-per-USD levels, with no log, /100, *100, z-score or standardization. D_usd_brl = D.usd_brl exists only for the macro-differences robustness. Economic label frozen as nominal USD/BRL (BRL per USD), month-end spot; an increase denotes BRL depreciation.
A8: v17-04 | B8: 2-Oct-2026 | C8: Data Freeze Gate moves to GDP YoY; RER dependency preserved | D8: Dashboard; Revision Tracker; Action Sequence; Estimation Plan | E8: Next audit is GDP YoY under the same six-step sequence. No final regressions may be rerun yet. The completed nominal NER audit does not validate RER; if RER replaces NER in the final core table, RER must be audited separately before panel freeze.
