Workbook

Sheet README
A1: TFM - Master Revision Matrix v30
A2: Single source of truth for the jury-revision process. Updated 9-Oct-2026 after closing the Econometric Panel Data Freeze Gate. The reproducible builder now writes and validates panel_main_and_robustness_rebuilt.xlsx with 4,648 bond-month rows, 19 columns, 103 bonds and 48 issuers while preserving the legacy 4,229-row workbook unchanged. BCB SGS 13762 Gross General Government Debt (% GDP) now uses the frozen uniform L2 reference-month timing. Sovereign Risk (BRL) keeps the validated WP-02 LTN/NTN-F-vs-DI arithmetic and is mapped contemporaneously inside WP-06: 3,918 rows are populated from Jan-2016 onward and 730 pre-2016 rows remain intentionally missing; there is no backward time extrapolation and the legacy synthetic-CDS/latest-curve mapper remains rejected. Full overlap reconciliation passed: metadata plus VIX/Fed 3M OIS/USD-BRL/GDP reconcile exactly on 4,226 common bond-months; relative issue size is exact; accounting differences follow the frozen PIT timing; residual maturity differs by at most 1/252 year from the legacy convention; the revised spread and fiscal/sovereign constructs change by design. Reproducibility commit 23435a4 contains the builder, candidate panel and required canonical inputs. CURRENT: WP-07 is active — reset inference to the single bond-FE / Driscoll-Kraay core table, then run the agreed targeted robustness checks.
A3: v30 update | B3: 9-Oct-2026: Data Freeze Gate PASSED. Sovereign panel mapping was frozen and implemented without reopening WP-02: same-date nominal government nodes are used only from 2016 onward; flat-forward interpolation is used between contemporaneous tenor nodes, endpoint-flat mapping outside the available tenor range, and a single observed node is carried across corporate maturities on that same date. No sovereign value is time-extrapolated back into 2010-2015, leaving 730 intentionally missing rows and 3,918 populated rows. BCB SGS 13762 public-debt/GDP now applies the frozen uniform L2 reference-month timing across all 175 panel months. The candidate panel was assembled and validated at 4,648 rows x 19 columns, 103 bonds, 48 issuers, 0 duplicate bond-month keys and complete coverage for every baseline field other than the documented pre-2016 sovereign gap. Sample reconciliation: 4,226 legacy bond-months retained, 422 newly recovered observations added, and three AN275276 Corp legacy rows (May-Jul 2017) intentionally removed because the revised ANDE replacement history begins 29-Aug-2017; net change +419. Unchanged metadata and VIX/Fed3M/USD-BRL/GDP match exactly on all 4,226 common rows; relative issue size also matches exactly. Expected differences in spreads, public debt/GDP, PIT liquidity/leverage, BUS/252 maturity and sovereign risk are documented. The rebuilt panel and reproducible builder were committed as 23435a4 (Build reproducible frozen econometrics panel). WP-06 is Done; WP-07 is now In progress.
A4: Purpose and governance
A5: Purpose | B5: Use the Master Matrix as the authoritative record of every jury issue, Martin's disposition, the required evidence/change, dependencies and completion status.
A6: Workflow status | B6: The Econometric Panel Data Freeze Gate is CLOSED/PASSED. The authoritative reproducible candidate is datos_y_modelos/db/econometrics_db/panel_main_and_robustness_rebuilt.xlsx (4,648 x 19; 103 bonds; 48 issuers). The legacy panel_main_and_robustness.xlsx remains an untouched archival comparison file. Fiscal control is BCB SGS 13762 Gross General Government Debt (% GDP) with uniform L2 timing; accounting controls use the frozen PIT quarter-selection rules; relative issue size and BUS/252 residual maturity are reproducible; Sovereign Risk (BRL) is populated contemporaneously from 2016 onward with 730 documented pre-2016 missing rows and no backward time extrapolation. Ratings remain descriptive and the revised corporate-pricing/BVAL source hierarchy remains frozen. CURRENT: WP-07 — audit/execute the final bond-FE Driscoll-Kraay setup and produce the single core table, followed by targeted robustness under WP-08.
A7: Scope rule | B7: Every jury point must map to a change, diagnostic, defense answer or reasoned non-change. Not every suggested extension must be estimated.
A8: v16 update | B8: 2-Oct-2026: nominal Fed 3M Forward audit completed end-to-end. Bloomberg USSOC Curncy / PX_LAST (3M USD OIS) matched all 164 distinct panel months exactly (0 mismatches; max absolute difference 0.0). Baseline Stata uses the series directly in percentage points with no log, standardization or /100 scaling; only the separate macro-difference robustness creates D.fed_3m_forward. Thesis wording now keeps “Fed 3M Forward” as the intuitive label but defines the underlying 3M USD OIS precisely and states that it is forward-looking in economic content, not a forward-starting 3Mx3M rate. MR-09 is closed; any post-freeze raw/partial correlations and final VIX sign/H1 interpretation are tracked under MR-18/MR-19. Next pre-freeze audit: USD/BRL.
A9: v23 update | B9: 4-Oct-2026: days_to_maturity completed the six-step audit. Source field is contractual MATURITY from universo_brazil_deb_des.xlsx / db_values_only; all 103 panel bonds map uniquely with 0 missing maturities. The monthly calendar is the common corporate-YTM / real-curve obs_date set: 175 unique dates from Dec-2010 to Jun-2025, exactly one per month and identical across both inputs; 62 dates are before literal calendar month-end. The stored panel variable is not days: days_to_maturity x 252 is an integer for every row, and 4,229/4,229 observations reproduce exactly as ANBIMA business days from obs_date through maturity, inclusive of a valid maturity date, divided by 252, with 20 November included as a holiday from 2024 onward. Stata uses this BUS/252-year level directly. Preferred label: residual bond maturity (BUS/252 years) / plazo residual al vencimiento (años, BUS/252). The current DayCounts helper omits 20 November and excludes the terminal date, so align/document that helper during the final controlled rebuild; do not change the historical panel values ad hoc. NEXT: reconcile synthetic_cds_brl with the validated Sovereign Risk (BRL) / sovereign_spread_brl construction.
A10: Authoritative inputs
A11: Source file / message | B11: Role | C11: Date/pages | D11: How used | E11: Current status
A12: TFM_Maestria_Economia_Siqueira_Thiago_Abril_10_2026.pdf | B12: Submitted thesis baseline | C12: 69 pages | D12: Locations, equations, tables, figures and annexes | E12: Frozen baseline
A13: Ailin - Informe Preliminar TFM_Siqueira_Thiago (2).pdf | B13: Jury report + Martin annotations | C13: 11 pages | D13: Criticisms A-01 to A-18 and annotated dispositions | E13: Integrated
A14: Maximo Sangiacomo - Evaluacion_TFM_Siqueira_Thiago (2).pdf | B14: Jury report + Martin annotations | C14: 5 pages | D14: Criticisms M-01 to M-18 and priority technical exercises | E14: Integrated - primary substantive priority
A15: Devolucion DM - Daniel Milia.pdf | B15: Third jury report | C15: 18-Sep-2026; 3 pages | D15: Criticisms D-01 to D-18 and defense guidance | E15: Integrated; director reviewed 24-Sep-2026
A16: Martin Grandes - WhatsApp audio/text + Zoom meeting | B16: Director follow-up guidance | C16: Sep-2026 through 2-Oct-2026 | D16: SELIC, dynamics, sovereign ceiling, DK/PCSE, nominal FED3M, table design, robustness sequence, Sovereign Risk (BRL), two-spread specification, liquidity proxy, VIX defense, ratings scope, stale-price/BVAL treatment, presentation design and deadlines | E16: Integrated as MG-01 to MG-29
A17: Proceso de presentacion y evaluacion del Trabajo Final - Res.CD 1313/2023 | B17: Institutional process | C17: Sep-2023; 1 page | D17: Formal stages and generic time windows | E17: Exact project deadline still to enter
A18: Tabla para nuevas estimaciones panel-Siqueira & Grandes 25-9-2026.docx | B18: Director-provided estimation template | C18: 25-Sep-2026; 1 page | D18: Exact four-column FE-Driscoll-Kraay variable-inclusion grid and requested output statistics | E18: Integrated; two layout ambiguities flagged for confirmation
A19: Revision categories
A20: Category | B20: Definition | C20: Default implication
A21: A - Methodological issue / additional estimation | B21: Measurement, identification, data or inference concern. | C21: Change data/model and regenerate affected outputs.
A22: B - Clarification / reframing | B22: Valid criticism mainly solved through precise definitions, interpretation or wording. | C22: Rewrite after final estimates; may include a small diagnostic.
A23: C - Presentation / structure / literature / documentation | B23: Presentation, literature, reporting, provenance or reproducibility. | C23: Revise text/tables/appendix/package; not necessarily new estimation.
A24: D - Not endorsed / optional / response only | B24: Request rejected, narrowed or treated as optional/future research. | C24: No mandatory thesis change; answer in memo/defense or add only if low cost.
A26: Workbook map
A27: Dashboard | B27: Formula-driven overview of priorities, counts, current package and process status.
A28: Process & Deadlines | B28: Institutional stages, generic windows and project-specific control fields.
A29: Revision Tracker | B29: Sixteen dependency-based work packages. Update Status and Working notes.
A30: Master Matrix | B30: Thirty-four consolidated revision issues across all jurors and director guidance.
A31: Juror Log | B31: Every distinct juror criticism mapped to one or more master issues.
A32: Director Guidance | B32: Traceability for Martin's audio/text decisions through the 2-Oct-2026 Zoom meeting, including updated econometric, data-quality, ratings and delivery guidance.
A33: Overlap Map | B33: Unified resolution of recurring issues to prevent duplicate work.
A34: Action Sequence | B34: Dependency order that minimizes rework.
A35: Estimation Plan | B35: Current FE-Driscoll-Kraay model grid, post-freeze robustness checks, pricing-data QA controls, ratings response and 10-Oct delivery target; Data Freeze passed 9-Oct-2026.
A36: v4 Change Log | B36: Historical changes introduced on 24-Sep-2026.
A37: v5 Change Log | B37: Exact changes introduced from Martin Grandes' 25-Sep-2026 instructions.
A38: v6 Change Log | B38: Changes introduced from Martin Grandes' 25-Sep-2026 sovereign-risk clarification and workflow handoff from WP-01 to WP-02.
... A62: v30 Change Log | B62: Changes introduced on 9-Oct-2026 after implementing the frozen sovereign mapping and public-debt L2 timing, writing/reconciling the 4,648-row candidate panel, passing the Data Freeze Gate, and committing the reproducible econometrics panel under 23435a4.

Sheet Dashboard
A1: Revision Dashboard
A2: Formula-driven from the Master Matrix, Revision Tracker and Process & Deadlines. Updated 9-Oct-2026 after the Econometric Panel Data Freeze Gate PASSED. The reproducible builder now writes panel_main_and_robustness_rebuilt.xlsx with 4,648 rows, 19 columns, 103 bonds and 48 issuers while leaving the legacy 4,229-row panel untouched. BCB SGS 13762 uses the frozen uniform L2 timing. Sovereign Risk (BRL) retains the closed WP-02 LTN/NTN-F-vs-DI definition and now has a documented same-date panel mapping: 3,918 rows populated from 2016 onward and 730 pre-2016 rows intentionally missing, with no backward time extrapolation. Full overlap reconciliation passed and the reproducible package was committed as 23435a4. CURRENT: WP-07 — reset inference to the single bond-FE / Driscoll-Kraay table, then execute WP-08 targeted robustness.
A4: Issue portfolio
A5: Metric | B5: Count | C5: Meaning | E5: Martin position | F5: Count | G5: Meaning
A6: Total master issues | B6: =COUNTA('Master Matrix'!A4:A200) | C6: Distinct consolidated issues. | E6: Agrees / strongly agrees | F6: =COUNTIF('Master Matrix'!H4:H200,E6) | G6: Explicitly endorsed.
A7: Critical priority | B7: =COUNTIF('Master Matrix'!D4:D200,"Critical") | C7: Can affect acceptance or downstream results. | E7: Partially agrees | F7: =COUNTIF('Master Matrix'!H4:H200,E7) | G7: Accepted with scope limits.
A8: Category A | B8: =COUNTIF('Master Matrix'!K4:K200,"A*") | C8: Measurement/diagnostics/estimation. | E8: Disagrees / not endorsed | F8: =COUNTIF('Master Matrix'!H4:H200,E8) | G8: Response only or future research.
A9: Category B | B9: =COUNTIF('Master Matrix'!K4:K200,"B*") | C9: Clarification/reframing. | E9: No explicit position | F9: =COUNTIF('Master Matrix'!H4:H200,E9) | G9: No direct disposition.
A10: Category C | B10: =COUNTIF('Master Matrix'!K4:K200,"C*") | C10: Presentation/literature/documentation.
A11: Category D | B11: =COUNTIF('Master Matrix'!K4:K200,"D*") | C11: Optional or non-endorsed.
A12: Changes required | B12: =COUNTIF('Master Matrix'!Q4:Q200,"Yes*") | C12: Mandatory/minimum-scope changes.
A13: Done | B13: =COUNTIF('Master Matrix'!R4:R200,"Done") | C13: Completed master issues.
A15: Critical workstreams - recommended order
A16: Order | B16: Workstream | C16: Master issues | D16: Why
A17: 1 | B17: Correct spread construction - measurement audit closed | C17: MR-03 | D17: Dependent-variable measurement audit completed; downstream regressions remain to be regenerated.
A18: 2 | B18: Sovereign Risk (BRL) construction - WP-02 closed; WP-06 panel mapping resolved/frozen | C18: MR-01 / MR-02 | D18: WP-02 remains closed upstream: 252 LTN + 330 NTN-F = 582 sovereign observations validated against same-date exact-tenor DI, geometric bps, exact-node guard, pytest 5/5 and commit b551414. WP-06 now supplies the panel mapping without reviving the legacy synthetic-CDS/latest-curve mapper: same-date mapping only; flat-forward interpolation between tenor nodes; endpoint-flat mapping outside the contemporaneous tenor range; single-node flat mapping when only one nominal bond is available. No backward time extrapolation into 2010-2015. Result: 3,918 populated bond-dates and 730 documented missing pre-2016 rows.
A19: 3 | B19: Issue-size identification - closed (WP-03) | C19: MR-14 | D19: Closed 30-Sep: amount_issued_to_bs_tot_asset reconstructed for 4,229/4,229 observations; 98/103 bonds (95.15%) vary within bond; variable retained in bond FE; ‰ units and relative-size interpretation documented; one-quarter-lagged denominator reserved as robustness.
A20: 4 | B20: Baseline explanatory-variable audits / Data Freeze Gate - PASSED | C20: Reproducible 4,648 x 19 panel generated, reconciled and committed; legacy panel preserved | D20: Data Freeze PASS: rebuilt panel has 4,648 rows, 19 columns, 103 bonds, 48 issuers, 0 duplicate bond-month keys and complete baseline coverage except the documented 730 pre-2016 sovereign rows. SGS 13762 uniform L2 timing is implemented. Sample bridge versus legacy: 4,226 common bond-months, 422 new rows, three intentional AN275276 Corp removals (May-Jul 2017; revised ANDE history starts 29-Aug-2017), net +419. Metadata and VIX/Fed3M/USD-BRL/GDP match exactly on common rows; relative issue size matches exactly; accounting and maturity differences follow frozen timing/day-count rules; spread, fiscal and sovereign changes are intentional methodology revisions. Builder + candidate + required inputs committed as 23435a4.
A21: 5 | B21: Single DK results table and inference reset - CURRENT (WP-07) | C21: MR-16 / MR-17 / MR-18 / MR-24 | D21: Data Freeze has passed. CURRENT: audit the exact bond-FE / Driscoll-Kraay implementation, lock lag and finite-sample choices, document FE coefficient estimation versus DK covariance/inference, and rerun the four-model core table on the frozen rebuilt panel. Keep plain FE/PCSE out of the main table; retain them only as qualified diagnostics/appendix if useful. Then execute WP-08 targeted robustness, including Brazil 3M DI variants. Target package for Martin remains 10-Oct-2026.
A22: 6 | B22: Ratings evidence / bounded heterogeneity response - EVIDENCE AUDIT CLOSED | C22: MR-06 / MR-07 | D22: Bloomberg point-in-time rating audit completed on the exact 4,229 bond-month sample using bond_id + obs_date overrides. Global LT local-currency issuer fields are too sparse for a baseline control (>=1 usable agency 41.6%; 41/103 bonds, 17/48 legal issuers). Brazilian national-scale LT issuer fields provide broader complementary descriptive coverage (>=1 agency 75.8%; 84/103 bonds, 37/48 issuers) but are a distinct scale and must not be mixed with global ratings. Agencies remain separate; no silent parent/issue fallback or synthetic composite. Primary use is the issuer/company table, appendix and jury response. Extra interaction regressions remain optional only if later powered and useful. Audit files stored under datos_y_modelos/db/ratings/; commit b087203.
A23: 7 | B23: Hypothesis-result/sign rewrite | C23: MR-19 / MR-30 / MR-31 / MR-32 | D23: Daniel's valid contribution is primarily expositional and follows empirical freeze.
A24: 8 | B24: Replication and resubmission | C24: MR-27 | D24: Required alongside the revised thesis.
A25: Live revision status
A26: Current package | B26: =IFERROR(INDEX('Revision Tracker'!B12:B100,MATCH("In progress",'Revision Tracker'!J12:J100,0)),"")
A27: Current task | B27: =IFERROR(INDEX('Revision Tracker'!E12:E100,MATCH("In progress",'Revision Tracker'!J12:J100,0)),"")
A28: Completed packages | B28: =COUNTIF('Revision Tracker'!J12:J100,"Done") | C28: of 16
A29: Overall progress | B29: =B28/16
A30: Current gate | B30: =IFERROR(INDEX('Revision Tracker'!K12:K100,MATCH("In progress",'Revision Tracker'!J12:J100,0)),"")
A32: Institutional process status
A33: Third report | B33: ='Process & Deadlines'!B5
A34: Daniel resolution | B34: ='Process & Deadlines'!B6
A35: Director review | B35: ='Process & Deadlines'!B7
A36: Current branch | B36: ='Process & Deadlines'!B8
A37: Official due date | B37: ='Process & Deadlines'!B9
A38: Days remaining | B38: ='Process & Deadlines'!B10
A39: Next formal step | B39: ='Process & Deadlines'!B11
A40: Seminar table target | B40: ='Process & Deadlines'!B13

Sheet Process & Deadlines
A1: Institutional Process & Deadlines
A2: Official generic time windows plus project-specific controls. Enter the exact official resubmission deadline when confirmed.
A4: Current project control
A5: Third jury report received | B5: Yes - Daniel Milia report dated 18-Sep-2026
A6: Daniel formal resolution | B6: Pasa a Defensa (favorable)
A7: Director review of Daniel | B7: Completed 24-Sep-2026 - less substantive; selective exposition/diagnostics/bibliography changes
A8: Current formal branch | B8: Awaiting official confirmation
A9: Official resubmission deadline
A10: Days remaining | B10: =IF(B9="","",B9-TODAY())
A11: Next formal step | B11: Confirm Ailin and Maximo formal resolutions, exact due date and whether a revised filing is formally required.
A12: Control note | B12: The user reports that a deadline exists, but the exact date is not in the process sheet.
A13: Paper/seminar table target | B13: 10-Oct-2026 - send Martin updated corrected FE-Driscoll-Kraay regressions (core models plus agreed robustness checks) and an updated, more visual/concise presentation. Planned joint review: week of 13-Oct-2026; refine presentation/abstract after seeing the new results.
A14: Official process and generic time windows
A15: Step | B15: Process stage | C15: Trigger | D15: Official time limit | E15: Current relevance | F15: Owner | G15: Status | H15: Evidence / next action
A16: 1 | B16: PTFM evaluation | C16: Formal receipt of project proposal | D16: 30 days | E16: Historical - not current | F16: Academic authority | G16: Not current | H16: Included for completeness.
A17: 2 | B17: PTFM correction, if required | C17: Authority requests project corrections | D17: 1 to 3 months | E17: Historical - not current | F17: Student + director | G17: Not current | H17: Not the current thesis-evaluation branch.
A18: 3 | B18: TFM review / jury convocation | C18: Formal receipt of TFM | D18: 45 days | E18: Completed | F18: Academic authority | G18: Completed | H18: The thesis was sent to three jurors.
A19: 4 | B19: Preliminary individual reports | C19: Jurors receive the TFM | D19: 45 days | E19: Completed - all three reports received | F19: Each juror | G19: Completed | H19: Daniel is the third report; dated 18-Sep-2026 and favorable.
A20: 5 | B20: Revision and resubmission, if formally required | C20: One or more resolutions require revision | D20: 1 to 4 months, set by authority | E20: Current only if official branch is revision | F20: Student + director | G20: Pending confirmation | H20: Enter the exact date in C9.
A21: 6 | B21: Second preliminary reports | C21: Revised TFM is formally resubmitted | D21: 45 days | E21: Contingent on revision branch | F21: Each juror | G21: Not started | H21: Jurors decide whether the revised version can pass to defense.
A22: 7 | B22: Oral and public defense | C22: Three favorable reports received | D22: Within 45 days | E22: Current if all three resolutions are favorable | F22: Program direction + student + jurors | G22: Pending confirmation | H22: Confirm Ailin/Maximo resolutions and coordinate defense date.
A24: Source: Proceso de presentacion y evaluacion del Trabajo Final de Maestria o Especializacion, Res.CD No. 1313/23 (Sep-2023). Daniel status: Devolucion DM - Daniel Milia, 18-Sep-2026. Director guidance: WhatsApp 24-27 Sep-2026 plus Zoom meeting 2-Oct-2026, including DK/PCSE, VIX, liquidity, ratings, stale-price/BVAL treatment and the updated 10-Oct delivery / week-of-13-Oct review sequence. Estimation template: Tabla para nuevas estimaciones panel, 25-Sep-2026.

Sheet Revision Tracker
A1: TFM Jury Revision Tracker
A2: Sixteen dependency-based work packages consolidate 34 master issues. Updated 9-Oct-2026 after closing WP-06 / the Econometric Panel Data Freeze Gate. The reproducible builder writes and validates a 4,648-row x 19-column panel (103 bonds, 48 issuers), implements the frozen SGS 13762 L2 fiscal timing and documented Sovereign Risk (BRL) mapping, and preserves the legacy workbook unchanged. Reconciliation passed and commit 23435a4 records the frozen package. CURRENT: WP-07 is In progress — reset inference to the single bond-FE / Driscoll-Kraay table. WP-08 follows with the director-requested core grid and targeted robustness.
A4: Current package | B4: =IFERROR(INDEX(B12:B100,MATCH("In progress",J12:J100,0)),"")
A5: Current task | B5: =IFERROR(INDEX(E12:E100,MATCH("In progress",J12:J100,0)),"")
A6: Completed packages | B6: =COUNTIF(J12:J100,"Done")
A7: Overall progress | B7: =B6/16
A8: Current status | B8: =IFERROR(INDEX(J12:J100,MATCH("In progress",J12:J100,0)),"")
A9: Gate before moving on | B9: =IFERROR(INDEX(K12:K100,MATCH("In progress",J12:J100,0)),"")
A11: Seq. | B11: WP ID | C11: Phase | D11: Master issue IDs | E11: Work package | F11: Why this is sequenced here | G11: Thesis location(s) | H11: Concrete deliverable | I11: Dependencies | J11: Status | K11: Gate / acceptance criterion | L11: Working notes
A12: 1 | B12: WP-01 | C12: Measurement | D12: MR-03 | E12: Recalculate the corporate spread using consistent compounding | F12: The dependent variable feeds every regression and conclusion. | G12: Sec. 2.2; Sec. 4.3; Sec. 4.5.2; Annex 8.7; all results | H12: Audited conventions; corrected spread series; old-vs-new comparison; unit tests. | I12: Submitted code/data and curve audit | J12: Done | K12: Approve formula, units, day-count, compounding and field types; benchmark/corporate inputs pass hand checks. | L12: Completed 25-Sep-2026: corrected the 2012-2013 NTN-B field contamination, revalidated the relevant government-curve inputs, checked corporate bond price/yield fields, and closed the corporate-spread measurement audit. Downstream estimates will be regenerated after WP-02.
A13: 2 | B13: WP-02 | C13: Measurement | D13: MR-01, MR-02 | E13: Verify Sovereign Risk (BRL) construction, common-reference logic and terminology | F13: Martin confirmed the intended sovereign regressor and preferred two-spread transmission specification. The nominal sovereign implementation was validated end-to-end: LTN and NTN-F government yields are compared with the same-date DI reference curve at exact BUS/252 residual tenor. Thesis terminology and documentation were subsequently aligned, including the distinction between the nominal sovereign DI benchmark and the IPCA-real corporate benchmark. | G13: Secs. 2.2, 4.3, 4.5.1-4.5.3, 5.2.3; Annex 8.3 and 8.8-8.9 | H13: COMPLETED: code/formula audit; 252 LTN + 330 NTN-F maturity-matched sovereign spreads; same-date exact-tenor DI benchmark; geometric annual-effective spread; exact-node interpolation guard; regression tests; variable rename to sovereign_spread_brl; removal of synthetic-CDS wording; explicit methodology/appendix formula; literature/two-spread rationale; corporate-IPCA versus nominal-DI indexation clarification; affected figures/tables relabeled. | I13: WP-01 | J13: Done | K13: Corporate Spread is documented against the matched IPCA-real reference curve and sovereign_spread_brl against the matched nominal DI reference curve, each at the appropriate date/tenor/indexation. The thesis explains why the two spreads are modeled separately rather than collapsed into a direct corporate-minus-sovereign spread; CDS terminology is removed. Any final search for unintended USD CDS usage is a pre-estimation integrity check and does not reopen WP-02. | L13: Closed 29-Sep-2026. Nominal Sovereign Risk (BRL) implementation validated on 582/582 observations with 0 missing benchmarks and max absolute benchmark difference 5.33e-13 bp; spread arithmetic independently verified; BZDIOVRA cash + liquid DI futures + Pre x DI swaps; exact BUS/252 tenor; pytest 5/5; commit b551414 pushed. Canonical source governance reconfirmed 9-Oct-2026: domestic_sovereign_curve_brazil.xlsx = government-bond characteristics/metadata; govt_ya_ande.v3.xlsx = ANDE normalized government YAS yields (retaining the earlier NTN-B 2012-2013 field correction). Follow-up builder audit found no frozen rule for mapping the 582 nominal observations onto all 4,648 corporate bond-months and insufficient historical/tenor coverage in the current nominal universe. That is tracked under WP-06 and does not reopen the validated WP-02 spread formula/source decision.
A14: 3 | B14: WP-03 | C14: Data audit | D14: MR-14 | E14: Audit amount_issued_to_bs_tot_asset and within-bond variation | F14: A time-invariant issue-size variable cannot be estimated in bond FE. | G14: Table 1 H6; Secs. 4.5.3 and 4.7; Table 3; Sec. 5.2.4; Annex 8.6.2 and Table 7; Figure 3 | H14: COMPLETED: raw-field trace from AMT_ISSUED and issuer BS_TOT_ASSET; full-panel reconstruction; within-bond variation diagnostics; timing/scaling audit; retain/rename decision; one-quarter-lagged denominator robustness construction; thesis wording/table/figure alignment. | I14: Raw panel and construction code | J14: Done | K14: PASSED: 4,229/4,229 panel observations reconstructed from raw sources; 98/103 bonds (95.15%) have within-bond variation; the regressor is identified in bond FE; ‰ units, quarterly timing and interpretation are documented; lagged-quarter timing robustness is available. | L14: Closed 30-Sep-2026. The jury concern applies to AMT_ISSUED in levels, but the estimated variable is AMT_ISSUED / BS_TOT_ASSET. AMT_ISSUED is fixed by bond; quarterly issuer assets generate within-bond variation. Raw-source reconstruction matched all 4,229 panel observations essentially exactly. 98/103 bonds vary within bond; five very-short-history bonds do not. The stored scale is per-mille (‰). A one-quarter-lagged BS_TOT_ASSET version retains 4,223/4,229 observations, correlates 0.9918 with the original, and preserves 98/103 varying bonds; its six missing observations are limited to two Serena bonds in 2022Q1 due to unavailable 2021Q4 assets. Decision: retain the existing contemporaneous relative-size variable in the main specification, reserve the lagged denominator as robustness, and interpret the coefficient as relative issue size versus issuer scale—not as a change in original amount issued. Thesis edits were completed across H6, methodology/FE identification, results, conclusions, Tables 3/7, Figure 3 and Annex 8.6.2. 2-Oct director confirmation: the numerator is static but the quarterly asset denominator varies. Martin agreed the audited ratio can remain. Turnover/amount outstanding is conceptually closer to secondary-market liquidity, but for these illiquid Brazilian bonds it may contain many zeros and little useful time variation. Frame the retained variable as relative issue size / primary-market issuance-liquidity, not a clean secondary-market turnover measure.
A15: 4 | B15: WP-04 | C15: Variables | D15: MR-04 | E15: Clarify SELIC baseline non-inclusion and run post-freeze Brazil 3M DI robustness checks | F15: SELIC anchors the short end of the local reference curve and its influence propagates through the curve; Martin's 3M Forward SELIC exercise is only a low-cost referee diagnostic, not a competing baseline specification. | G15: Secs. 3.1-3.3, 4.3, 4.5.3, 5.2-5.4, 6.1 | H15: Dual-rationale note plus post-freeze robustness: add the Brazil 3M DI proxy to the finalized model and compare the agreed specifications with nominal FED3M retained versus omitted, under the specified FX/sovereign exclusions. Keep the domestic short-rate exercise separate from the baseline and report only if informative. | I15: WP-01; final curve definitions | J15: Deferred | K15: Baseline omission is explicit; the local-curve embedding of SELIC is explained; any SELIC 3M Forward check follows the required exclusions, is labeled referee-only and does not replace the preferred model. | L15: 2-Oct meeting reconfirmed that the domestic 3M rate is a robustness exercise, not a baseline replacement. Data preparation is complete; run only after the Data Freeze Gate and core rerun. Include the with-FED3M / without-FED3M comparison in the 10-Oct package if the gate has passed.
A16: 5 | B16: WP-05 | C16: Jury response / Heterogeneity | D16: MR-06, MR-07 | E16: Prepare local-currency ratings evidence; keep heterogeneity extensions bounded | F16: 2-Oct guidance narrows the minimum reviewer response: ratings lag market spreads and are not the core object of the thesis; a descriptive local-currency issuer-rating table is sufficient to answer the point before considering extra regressions. | G16: Secs. 3.1, 3.3.2, 4.1, 4.3, 5.2.3, 6.1, 6.3 | H16: Use point-in-time issuer-rating evidence in the issuer/company table or appendix. Global LT local-currency issuer ratings are the conceptually closest measure but have insufficient exact-sample coverage for a baseline control; Brazilian national-scale LT issuer ratings are retained as clearly labelled complementary descriptive evidence only. Preserve agencies separately, document source/date/missing rules, distinguish issuer vs issue and global vs national scale, and do not silently substitute ultimate-parent ratings. Optional heterogeneity estimation remains post-core. | I16: Final issuer list; Bloomberg PIT rating audit; source/timing and missing-value rules | J16: Done | K16: Minimum response satisfied at the data/method level: exact-sample issuer ratings and coverage are documented; ratings are not forced into the baseline FE-DK regression; global and national scales remain separate; extra heterogeneity is optional. | L16: 7-Oct-2026 closure. Exact 4,229-row audit using bond_id + obs_date + RATING_AS_OF_DATE_OVERRIDE. Global LT LC usable coverage: S&P 1,572 (37.2%), Moody's 360 (8.5%), Fitch 1,461 (34.5%); >=1 agency 1,760 (41.6%), >=2 1,273 (30.1%), all three 360 (8.5%); 41/103 bonds and 17/48 legal issuers ever rated. Brazilian national-scale usable coverage: S&P 2,408 (56.9%), Moody's 542 (12.8%), Fitch 2,872 (67.9%); >=1 agency 3,204 (75.8%), >=2 2,105 (49.8%), all three 513 (12.1%); 84/103 bonds, 37/48 legal issuers, 26/27 parent groups; 82 bonds fully covered, 19 never covered, 2 partial. Eight Fitch AA(dza) rows were excluded as non-Brazil scale. Files: datos_y_modelos/db/ratings/issuer_ratings_global_lc_bond_level_panel_audit.xlsx and issuer_ratings_national_bond_level_panel_audit.xlsx. Commit b087203. ISSUER LC RATING CONTROL — FROZEN: descriptive evidence, not baseline regressor.
A17: 6 | B17: WP-06 | C17: Data Freeze Gate | D17: Baseline audits/decisions closed; reproducible 4,648 x 19 panel generated, reconciled and frozen | E17: Close the Econometric Panel Data Freeze Gate with one reproducible authoritative candidate panel | F17: Daniel asks for a direct H1-result link and better explanation of the negative sign. | G17: Secs. 3.1, 3.3.1, 4.1, 4.5.3, 5.2.1, 6.1 | H17: COMPLETED. Reproducible builder assembles the revised 4,648-row bond-month panel with corrected corporate spread; VIX/Fed3M/USD-BRL/GDP; SGS 13762 public debt/GDP under uniform L2 timing; PIT liquidity/leverage; relative issue size; BUS/252 residual maturity; and the frozen Sovereign Risk (BRL) same-date mapping. Sovereign mapping yields 3,918 populated rows from 2016 onward and 730 intentional pre-2016 missing rows with no backward time extrapolation. Candidate output panel_main_and_robustness_rebuilt.xlsx passes row/bond/issuer/key/missingness and variable-by-variable reconciliation. Legacy workbook remains untouched. | I17: Frozen builder + candidate 4,648 x 19 panel + reconciliation evidence + reproducibility commit 23435a4 | J17: Done | K17: PASSED 9-Oct-2026: sovereign mapping is documented/reproducible; SGS 13762 uses uniform L2; candidate panel passes structural and variable-level reconciliation; legacy workbook is preserved. FE-DK estimation may now proceed from the frozen rebuilt panel. | L17: Closed 9-Oct-2026. Final panel: 4,648 rows x 19 columns; 103 bonds; 48 issuers; 0 duplicate bond-month keys. Sovereign present 3,918 / missing 730, with missingness confined to pre-2016 dates. Sample reconciliation versus legacy: 4,226 common, 422 new, three intentional AN275276 Corp removals (May-Jul 2017) because the revised ANDE replacement series starts 29-Aug-2017. Metadata plus VIX/Fed3M/USD-BRL/GDP reconcile exactly on all common rows; relative issue size is exact; maturity max difference is 1/252 year; PIT accounting differences and revised spread/fiscal/sovereign constructs are documented and expected. Reproducibility commit: 23435a4 Build reproducible frozen econometrics panel.
A18: 7 | B18: WP-07 | C18: Estimator | D18: MR-16, MR-17, MR-23 | E18: Reset inference to one bond-FE Driscoll-Kraay table; remove plain FE and PCSE | F18: Martin confirmed the PCSE rationale and requested no separate conventional-FE or PCSE columns. | G18: Secs. 4.2, 4.6, 4.8, 5.1-5.3; Tables 2-3; Annex 8.10-8.11 | H18: Audit the exact FE/DK/PCSE commands and diagnostics; set the final DK lag/finite-sample choices; explain that bond FE defines the coefficient estimator while Driscoll-Kraay/PCSE address the covariance/inference layer; document which forms of heteroskedasticity, serial correlation and cross-sectional dependence each treatment is intended to handle; keep one main DK table. | I18: WP-01 to WP-06 final variable definitions | J18: In progress | K18: All main significance uses one DK setup; diagnostics are shown; the core table has no separate plain-FE or PCSE columns. | L18: Activated 9-Oct-2026 immediately after WP-06 Data Freeze PASS. Use panel_main_and_robustness_rebuilt.xlsx as the frozen estimation input. First task: audit the exact FE-DK commands/setup, choose and document the DK lag/finite-sample treatment, verify panel dimensions and covariance assumptions, and produce the single four-column core table. Plain FE/PCSE remain diagnostic/appendix only.
A19: 8 | B19: WP-08 | C19: Estimator | D19: MR-18 | E19: Produce the single four-model DK table and targeted robustness checks | F19: Updated director deliverable: corrected post-freeze regressions and presentation package by 10-Oct-2026. | G19: Secs. 4.6-4.8, 5.1-5.4; Annex 8.11 | H19: Four core bond-FE / Driscoll-Kraay columns using nominal FED3M; sovereign/local-macro and NER/RER variants as finalized; within R2/rho and diagnostics; Brazil 3M DI robustness with FED3M retained vs omitted; correlation matrix; pricing-data sensitivity where feasible. Use the frozen panel only. | I19: WP-01, WP-02, WP-04, WP-07; confirm template ambiguities | J19: Not started | K19: Core grid matches the director template; old FED3M Real is excluded; NER/RER and stacking ambiguities are confirmed; any SELIC columns are separate, referee-only diagnostics. | L19: 2-Oct meeting resets the old 30-Sep target. Aim to send Martin the new regressions plus an updated deck by 10-Oct-2026, then review in the week of 13-Oct. Keep the main table DK-only; alternative covariance outputs are appendix/internal diagnostics, not a horse race.
A20: 9 | B20: WP-09 | C20: Data quality / pre-freeze | D20: MR-25 | E20: Finalize stale-quote, BVAL and missing-price treatment before panel freeze | F20: Lagged quotes may mechanically create anomalous signs. | G20: Secs. 2.1.1, 4.5.2, 4.6, 5.2.1, 5.2.3, 6.1-6.3; Annex 8.2 and 8.5 | H20: Treat the revised corporate-pricing/source-selection workflow as the authoritative baseline input. The problematic BVAL/indicative observation was replaced by the next-best available source rather than retained under its odd convention; do not reopen that source decision absent material new evidence. Keep BVAL/indicative semantics explicit in the data appendix. Any alternative no-fill-forward/missing-price convention may be reported later as sensitivity, but it no longer blocks the reproducible panel build. | I20: WP-01 revised corporate pricing dataset; source-selection audit trail | J20: Done | K20: Pricing-source decision is explicit for the baseline and BVAL/indicative marks are not silently treated as executed transaction prices. Alternative missing-price treatment is sensitivity only and does not block the controlled panel reconstruction. | L20: 7-Oct-2026 governance closure based on the completed corporate-spread work: the affected BVAL value had already been replaced by the second-best available source because of its problematic convention. User/director discussion treated this issue as solved; do not reopen absent material evidence. Preserve the source hierarchy and rationale in the reproducible builder/data appendix.
A21: 10 | B21: WP-10 | C21: Identification | D21: MR-13, MR-15 | E21: Clarify identifying variation and panel imbalance | F21: Common regressors vary monthly; bond histories are unequal. | G21: Secs. 4.2-4.4, 4.7-4.8, 5.1, 5.3-5.4, 6.1; Annex 8.10 | H21: Variation-level table and T_i/coverage profile. | I21: WP-03 and WP-07 | J21: Not started | K21: Months, bonds, issuers, T_i distribution and FE limits are reported.
A22: 11 | B22: WP-11 | C22: Text/literature | D22: MR-11, MR-12, MR-21, MR-32, MR-34 | E22: Correct language and make bounded literature/theory updates | F22: Daniel's literature comments are secondary and should support, not expand, the empirical design. | G22: Introduction; Secs. 3-4; references; defense literature map | H22: Non-causal wording; citation corrections; construct-proxy table; closest-study comparison. | I22: Final empirical framing from WP-04, WP-08, WP-09 | J22: Not started | K22: Every citation supports the statement; the gap/proxies are demonstrated without theoretical overhaul.
A23: 12 | B23: WP-12 | C23: Reporting | D23: MR-22, MR-24 | E23: Build the single consolidated regression table and run table-to-text checks | F23: Final DK evidence must be readable and auditable. | G23: Table 3; Sec. 5.2.2; Annex Table 7 | H23: One FE-DK table with SE, N, panel dimensions, within R2, rho, DK lag/FE metadata and diagnostics panel. | I23: WP-08 final estimates | J23: Not started | K23: The requested four core columns and any optional SELIC columns are readable, auditable and matched exactly by the prose. | L23: Table design source: Martin's 25-Sep-2026 template.
A24: 13 | B24: WP-13 | C24: Interpretation | D24: MR-19, MR-26 | E24: Rewrite results and explain counterintuitive signs | F24: Daniel's central contribution is better H-result linkage; Brazil-specific mechanisms must be separated from evidence. | G24: Secs. 5.2-5.4 and 6.1-6.3 | H24: Robust/partial/null/unresolved hierarchy; H-result map; Brazil-specific mechanisms. | I24: WP-02, WP-04, WP-05, WP-08, WP-09, WP-12 | J24: Not started | K24: Every hypothesis and sign is tied to a final table or labeled as a mechanism/limitation.
A25: 14 | B25: WP-14 | C25: Narrative | D25: MR-30, MR-31, MR-32, MR-33 | E25: Rewrite gap, contribution, abstract/conclusions and final copy-edit | F25: Do this only after the empirical freeze; Daniel is treated selectively as exposition. | G25: Resumen/Abstract; Introduction; Secs. 5.4 and 6; entire-thesis QA | H25: Closest-study contribution; one central question; hypothesis scorecard; final language consistency. | I25: WP-13 | J25: Not started | K25: Question, contribution, tables and conclusions are consistent and appropriately bounded.
A26: 15 | B26: WP-15 | C26: Reproducibility | D26: MR-27, MR-28 | E26: Complete replication package and data provenance | F26: Ailin requests a runnable pipeline and Martin agrees. | G26: Secs. 4.4-4.5; Annex 8.1-8.14; source notes | H26: README, environment, scripts, queries, dates, hashes, consolidation rules, curve settings and clean-run evidence. | I26: All final code/outputs | J26: Not started | K26: A clean run regenerates every permitted output and provenance is complete.
A27: 16 | B27: WP-16 | C27: Resubmission | D27: MR-05, MR-08, MR-10, MR-20, MR-29; synthesis MR-30/31/32 | E27: Prepare response memo, defense and Bordeaux/Geneva materials | F27: All comments must receive a change, diagnostic, answer or reasoned non-change. | G27: Response memo; future research; defense/seminar deck; deadline checklist | H27: Issue-by-issue response memo; final single DK table; diagnostics; scoped non-changes; descriptive local-currency ratings evidence; confirmed deadlines; concise defense/Bordeaux/Geneva deck. After the 10-Oct regression package, make slides more visual and parsimonious, with the econometric results given adequate space and dense literature/method detail cut or moved to appendix. | I27: WP-01 to WP-15 | J27: Not started | K27: Every observation maps to evidence or a reasoned non-change; seminar materials use the agreed table; deadlines and formal branch are tracked. | L27: Updated near-term target: regressions + revised presentation to Martin by 10-Oct-2026; joint review planned for the week of 13-Oct-2026.

Sheet Master Matrix
A1: Master Revision Matrix
A2: One row per distinct issue across all three jurors. Updated through 9-Oct-2026: the Econometric Panel Data Freeze Gate has PASSED. The reproducible builder now writes panel_main_and_robustness_rebuilt.xlsx with 4,648 rows, 19 columns, 103 bonds and 48 issuers and preserves the legacy workbook unchanged. BCB SGS 13762 public debt/GDP uses the frozen uniform L2 timing. WP-02 remains closed at the sovereign source/formula level; WP-06 now provides a frozen same-date Sovereign Risk (BRL) panel mapping with 3,918 populated rows from 2016 onward and 730 intentional pre-2016 missing rows, with no backward time extrapolation. Full overlap reconciliation passed and commit 23435a4 records the reproducible package. CURRENT: WP-07 — bond-FE / Driscoll-Kraay inference reset and core table rerun.
A3: ID | B3: Source IDs | C3: Overlap group | D3: Priority | E3: Juror(s) | F3: Consolidated juror criticism | G3: Report location | H3: Martin position | I3: Martin annotation / evidence | J3: My diagnosis | K3: Revision category | L3: Thesis location | M3: Required action | N3: Estimation / work type | O3: Dependencies | P3: Acceptance criterion | Q3: Change required? | R3: Status | S3: Working notes
A4: MR-01 | B4: A-03, A-10, A-13; M-04, M-17, M-18; D-10, D-17 | C4: OG-01 | D4: Critical | E4: Ailin + Maximo + Daniel | F4: The sovereign-risk regressor and the dependent corporate spread share the IPCA benchmark. The jury asks whether this creates mechanical covariance and how the negative coefficient should be interpreted. | G4: Ailin pp. 2, 6-7 and M1; Maximo p. 2 sec. 1.2 and pp. 4-5; Daniel pp. 2-3 | H4: Agrees / strongly agrees | I4: 24-Sep-2026: Martin identifies this as the main priority and frames corporate excess/shortfall relative to the sovereign through the sovereign-ceiling hypothesis. 25-Sep: the sovereign regressor is a local BRL sovereign spread, government YTM minus the matched local risk-free/reference yield, not a CDS. 27-Sep: USD CDS 5Y was never part of the economic model. Corporate Spread and Sovereign Risk (BRL) should remain separate spreads over the same local reference curve so the model estimates the response of corporate spread to sovereign risk; a direct corporate-minus-sovereign spread is a related alternative, not the preferred econometric specification. | J4: Resolved. The jurors' shared-benchmark/mechanical-covariance concern was separated from the actual final implementation. Corporate spreads are measured against an IPCA-real reference curve, while sovereign_spread_brl uses nominal LTN/NTN-F minus the DI reference curve. The thesis now states that each spread is matched to its own instrument/indexation benchmark and explains why they remain separate variables in the sovereign-transmission regression. | K4: A - Methodological issue / additional estimation | L4: Sec. 2.2; Sec. 4.3; Sec. 4.5.1-4.5.3; Sec. 5.2.3; Annex 8.3 and 8.8-8.9 | M4: Completed: audit/document both formulas and tenor matching; distinguish the IPCA-real corporate benchmark from the nominal DI sovereign benchmark; explain the preferred two-spread transmission specification and the direct corporate-minus-sovereign alternative; remove synthetic-CDS terminology and align thesis figures/tables/appendix. Final model-panel integrity checks are deferred to the pre-estimation gate. | N4: Code/formula audit + terminology correction + re-estimation if implementation changes | O4: MR-03 measurement audit; local curve inputs; government-bond matching | P4: The thesis and code use explicit Corporate Spread and sovereign_spread_brl constructions with date/tenor/indexation matching appropriate to each instrument. The shared-benchmark concern is addressed without falsely claiming an identical curve; the two-spread specification is justified; no CDS label or pure-default interpretation remains. Final estimates will be refreshed only after the remaining regressor audits. | Q4: Yes | R4: Done | S4: Closed 29-Sep-2026. Sovereign code audit: 252 LTN + 330 NTN-F = 582 observations; 582/582 DI benchmarks reproduced; 0 missing; max abs diff 5.33e-13 bp; geometric spread verified; exact-node guard; pytest 5/5; commit b551414 pushed. Thesis edits completed across Resumen/Abstract, sovereign-risk literature/methodology, results terminology, annex construction, and Figures 3/4. Corporate IPCA-real versus nominal sovereign DI benchmark distinction is now explicit. 9-Oct-2026 follow-up: canonical metadata/YAS sources and the 582-observation WP-02 arithmetic remain valid, but full corporate-panel mapping was not part of that closure. Current nominal coverage is insufficient for a defensible 2010-2025 contemporaneous tenor match; this downstream blocker is assigned to WP-06. 9-Oct-2026 WP-06 closure: downstream panel mapping is now frozen and reproducible — same-date nominal mapping only, 3,918 populated rows from 2016 onward and 730 intentional pre-2016 missing rows; no backward time extrapolation. This closes the former coverage blocker without reopening WP-02.
A5: MR-02 | B5: A-03, A-13; M-04 | C5: OG-01 | D5: High | E5: Ailin + Maximo | F5: The labels synthetic CDS BRL and risk-free real curve overstate what is measured when the benchmark includes sovereign NTN-B yields and market-basis components. | G5: Ailin pp. 2, 6-7; Maximo p. 2 sec. 1.2 | H5: Agrees / strongly agrees | I5: 25-Sep-2026: Martin explicitly rejects the "synthetic CDS" label; there is no credit default swap in the construction. 27-Sep: he further clarifies that USD CDS 5Y was never part of the economic model and should not be introduced. The intended object remains a maturity-matched local-currency sovereign spread: government-bond yield minus the relevant futures/swap/interpolated local reference curve yield. | J5: Resolved. The final variable is sovereign_spread_brl / local-currency sovereign spread, not a CDS. The nominal DI reference curve and exact-tenor matching are documented, and language that could imply a pure default-protection measure was removed. The corporate IPCA-real benchmark is described separately so the indexation treatment is transparent. | K5: B - Clarification / reframing | L5: Resumen/Abstract; Sec. 2.2; Sec. 4.5.1-4.5.3; Sec. 5.2.3; Annex 8.3 and 8.8-8.9; Glossary | M5: Completed: rename the variable consistently as sovereign_spread_brl / sovereign risk in local currency; define it algebraically as government YTM versus the matched nominal DI reference yield; explain the DI curve construction and tenor matching; remove synthetic CDS BRL from thesis text, diagrams and table labels. Keep the director-confirmed USD CDS 5Y non-use as a final pre-estimation code-integrity check only. | N5: Terminology correction + code/formula verification | O5: MR-01 measurement decision | P5: One name and one formula are used throughout; the variable is never described as a CDS; the nominal DI reference curve and maturity matching are transparent; the implementation reproduces the documented construction; the IPCA-real corporate benchmark is separately identified. No USD CDS variable is to be introduced into the model. | Q5: Yes | R5: Done | S5: Thesis terminology/documentation closed 29-Sep-2026: sovereign_spread_brl replaced synthetic-CDS language in text, tables/diagrams and Annex construction. Implementation reconciliation closed 4-Oct-2026: the existing econometric panel/Stata synthetic_cds_brl field was proven to be a different legacy fixed-curve proxy and is NOT the validated sovereign_spread_brl series. Replacement with the validated control is required during the controlled final panel rebuild before new estimates. 9-Oct-2026 follow-up: do not rename or revive any legacy synthetic surface. The current task is to obtain/document a reproducible full-panel sovereign mapping consistent with the validated nominal LTN/NTN-F-vs-DI definition; coverage resolution is tracked under WP-06, not as a reopening of MR-02 terminology. 9-Oct-2026 WP-06 closure: the final rebuilt panel uses sovereign_spread_brl, not synthetic CDS; same-date mapping is documented and legacy latest-curve/NSS logic remains rejected. Sovereign values are intentionally unavailable pre-2016 rather than backfilled.
A6: MR-03 | B6: A-05 | C6: OG-02 | D6: Critical | E6: Ailin | F6: Spreads were computed by linear subtraction of yields despite compounding conventions. Ailin requests a geometric or log-consistent spread on matched curves. | G6: Ailin p. 2 sec. 2(c), p. 7, M2 | H6: Agrees / strongly agrees | I6: Martin explicitly instructed the spread recalculation. 2-Oct-2026: he expects the geometric-vs-arithmetic compounding correction itself to have only a small quantitative effect; the corrected price/yield field problems can matter more. Re-estimate only after the explanatory-variable Data Freeze Gate passes. | J6: Genuine dependent-variable measurement correction. Exact units, signs, field types and compounding must be audited before coding. | K6: A - Methodological issue / additional estimation | L6: Sec. 2.2 eq. (1); Sec. 4.3; Sec. 4.5.2 eq. (3); Annex 8.7; all empirical outputs | M6: Recompute each bond-month spread with consistent compounding, matched tenor and consistent YTM/zero conventions. Unit-test hand cases, compare old versus new series, and regenerate all estimates, tables and conclusions. | N6: Dependent-variable rebuild + full re-estimation | O6: Curve and yield convention audit | P6: Formula, units, day count and compounding are documented; old/new summary statistics and hand checks reproduce; all downstream outputs use the corrected series. | Q6: Yes | R6: In progress | S6: Corporate-spread measurement stage completed 25-Sep-2026: NTN-B 2012-2013 field contamination corrected and corporate yield inputs rechecked. 2-Oct director expectation: geometric compounding alone should barely move results; price/yield corrections may matter. MR-03 remains open only because downstream estimates/tables still need regeneration on the frozen panel. Reproducible builder now calculates the corrected corporate spread for all 4,648 revised bond-month rows; MR-03 remains open only for the post-freeze regression/table regeneration and final old-vs-new results interpretation.
A7: MR-04 | B7: A-02, A-04, A-14 | C7: OG-02 | D7: High | E7: Ailin | F7: Subtracting the real curve implicitly imposes unit exposure to the curve factor; the level/slope of Brazilian real rates may be omitted. | G7: Ailin p. 2 sec. 2(b), pp. 5-7, M3 | H7: Partially agrees | I7: 25-Sep: baseline SELIC non-inclusion rests on UIP overlap with FED3M plus expected BRL depreciation and on SELIC anchoring the short end of the local reference curve. 27-Sep: the Brazil 3M rate is referee-only. 2-Oct meeting reconfirmed the robustness exercise: after panel freeze, add the Brazil 3M DI proxy and compare the specified model with nominal FED3M retained versus omitted. | J7: Baseline omission is economically defensible and the referee-only domestic short-rate proxy is now fully sourced/documented. Because Models 5-6 depend on the final common regressor set, the regression stage is intentionally parked until all baseline explanatory variables are audited and the authoritative panel is frozen. | K7: A - Methodological issue / additional estimation | L7: Secs. 3.1-3.3; Sec. 4.3; Sec. 4.5.3; Sec. 5.2-5.4; Sec. 6.1 | M7: Keep SELIC/Brazil 3M DI out of the baseline and explain both reasons. After the Data Freeze Gate, merge the validated 3M DI series only into the robustness panel and run the agreed with-FED3M / without-FED3M checks under the specified exclusions. Report correlations/VIF/incremental information and show the exercise only if informative. | N7: Clarification + diagnostics + optional two-column robustness | O7: MR-03; final curve definitions | P7: The baseline SELIC omission is explicit and tied to both UIP overlap and the curve construction; any SELIC 3M Forward columns obey the required exclusions, are labeled referee-only, and are not treated as a baseline replacement. | Q7: Yes - clarification / minimum scope | R7: Deferred | S7: Data package is complete. Regression-dependent closure remains deferred until the panel is frozen. The 2-Oct meeting makes the robustness comparison part of the intended new-estimates package rather than a pre-freeze task.
A8: MR-05 | B8: A-02, A-04, A-14 | C8: OG-02 | D8: Low | E8: Ailin | F8: Ailin proposes a full two-step Fama-MacBeth factor model with bond-specific betas to the real curve. | G8: Ailin pp. 5-7, M3 | H8: Disagrees / not endorsed | I8: Martin does not endorse a full theoretical redesign; treat it as a future extension. Current work should use bounded grouped heterogeneity tests. | J8: Interesting but disproportionate as a mandatory revision. | K8: D - Not endorsed / optional / response only | L8: Potentially Sec. 4.3-4.8 and Annex A | M8: Do not redesign the TFM around Fama-MacBeth. Mention it as future research and address the core concern through MR-04 and MR-06. | N8: No mandatory estimation | O8: MR-04 and MR-06 | P8: Response memo explains the scoped remedy and future extension. | Q8: No - response only | R8: Not started
A9: MR-06 | B9: A-07; M-01, M-16, M-17; D-10, D-18 | C9: OG-03 | D9: Critical | E9: Ailin + Maximo + Daniel | F9: The theory allows heterogeneous sovereign transmission, but the submitted model estimates one average coefficient and then invokes heterogeneous issuers to explain the sign. | G9: Ailin pp. 2, 9-10; Maximo pp. 1, 4; Daniel pp. 2-3 | H9: Partially agrees | I9: Earlier guidance supported bounded heterogeneity. In the 2-Oct meeting, when asked specifically about rating/sector grouping, Martin narrowed the immediate response: do not turn the thesis into a rating study; provide a small local-currency rating table for the reviewer/defense and keep any issuer/bond/sector heterogeneity exercises optional and subject to power. | J9: The jury concern should still be answered, but the minimum response is now descriptive evidence plus disciplined interpretation. Do not invoke issuer heterogeneity ex post as a proven explanation unless a powered test is actually run. | K9: A - Methodological issue / additional estimation | L9: Secs. 3.1, 3.3.2, 4.1, 4.3, 5.2.3, 6.1, 6.3 | M9: Use the completed point-in-time rating evidence descriptively in the jury response/appendix. Do not claim issuer heterogeneity as a proven mechanism unless a later powered test is run. Global and national rating scales must remain separate; additional sector/issuer/bond heterogeneity is optional post-core work. | N9: Descriptive evidence + optional bounded heterogeneity estimation | O9: MR-01, MR-03, MR-16; group definitions | P9: Rating evidence is documented with exact-sample coverage and explicit scale/source rules; the response no longer relies on an untested rating mechanism. Optional heterogeneity estimates, if any, are clearly secondary and powered. | Q9: Yes - response/descriptive minimum scope; extra estimation optional | R9: In progress | S9: 7-Oct-2026: rating data/method audit completed. Global LT LC >=1-agency coverage is 41.6%; Brazilian national-scale >=1-agency coverage is 75.8% but is a distinct descriptive scale. Baseline rating control rejected due coverage/selection; files committed as b087203. Remaining work is presentation in the issuer/company table or appendix and jury-response wording.
A10: MR-07 | B10: A-07; M-01, M-16, M-17 | C10: OG-03 | D10: High | E10: Ailin + Maximo | F10: Local-currency credit quality is used ex post to explain the sovereign coefficient but is absent from the model. | G10: Ailin pp. 2, 9-10; Maximo pp. 1, 4 | H10: Partially agrees | I10: 2-Oct-2026: Martin does not want ratings to become a core regression dimension. Ratings are slower-moving and may lag spread information; use a compact table of long-term local-currency issuer ratings to answer the reviewer. Do not assume the sample is uniformly AA/AAA; retrieve the actual ratings. | J10: A descriptive rating table is the appropriate minimum response. A rating interaction is optional only if timing, coverage, within-sample cells and economic interpretation are defensible after the core results are frozen. | K10: A - Methodological issue / additional estimation | L10: Sec. 5.2.3; Sec. 6.1 and 6.3; variable section 4.5.3 | M10: Add the completed issuer-rating evidence to the company/issuer table or appendix. Preserve S&P/Moody/Fitch separately. Use global LT local-currency issuer ratings where available and clearly labelled Brazilian national-scale LT issuer ratings only as complementary descriptive evidence; no parent/issue fallback and no synthetic composite. Baseline regression remains rating-free. | N10: New descriptive data field; optional additional estimation | O10: MR-06; rating source/timing rule | P10: Actual point-in-time issuer ratings and coverage are documented without assuming a uniformly high-grade sample; global and national scales are not mixed; missing values remain explicit; the reviewer receives a direct descriptive answer. | Q10: Yes - descriptive minimum scope; regression optional | R10: In progress | S10: 7-Oct-2026 audit closure: exact 4,229-row bond-date extraction with Bloomberg RATING_AS_OF_DATE_OVERRIDE. Global fields: RTG_SP_LT_LC_ISSUER_CREDIT, RTG_MDY_LC_CURR_ISSUER_RATING, RTG_FITCH_LT_LC_ISSUER_DEFAULT. National complement: RTG_SP_NATIONAL_LT_ISSUER_CREDIT, RTG_MDY_NSR_ISSUER, RTG_FITCH_NATIONAL_LT. Coverage supports descriptive use only; no baseline control. Audit workbooks stored under datos_y_modelos/db/ratings/ and committed b087203.
A11: MR-08 | B11: M-16, M-17, M-18 | C11: OG-03 | D11: Low | E11: Maximo | F11: Test flight-to-quality explanations with crisis/event dummies and interactions. | G11: Maximo p. 4 and defense questions | H11: Disagrees / not endorsed | I11: Useful but optional/future research; the thesis must have a bounded end. | J11: Potentially informative but secondary after ratings, sectors and stale-price checks. | K11: D - Not endorsed / optional / response only | L11: Sec. 5.2.1, 5.2.3, 6.1, 6.3 | M11: Keep as future research unless a pre-specified low-cost robustness can be added. Do not present flight-to-quality as a finding. | N11: Optional interaction estimation | O11: MR-06 and MR-07 | P11: Narrative labels this as a possible mechanism unless directly tested. | Q11: No - response only | R11: Not started
A12: MR-09 | B12: A-01, A-06; M-03, M-10, M-18; D-09, D-18 | C12: OG-04 | D12: High | E12: Ailin + Maximo + Daniel | F12: VIX differs from the proxy in the cited reference, is not pure risk aversion, and its negative sign relative to H1 requires an explicit conditional interpretation. | G12: Ailin pp. 1, 7-8; Maximo pp. 1, 3, 5; Daniel pp. 2-3 | H12: Agrees / strongly agrees | I12: 24-Sep: keep VIX if justified and explain the sign carefully. 2-Oct meeting: defend VIX academically with the broad literature that uses it as a global volatility/financial-stress proxy; other authors may use high-yield/junk-bond spreads, but this does not by itself require changing the proxy or running new econometrics. Final sign interpretation still waits for the frozen-panel DK rerun. | J12: Retain VIX as a global volatility/financial-stress proxy, not pure risk aversion, and interpret it conditionally after sequential models. | K12: B - Clarification / reframing | L12: Secs. 3.1, 3.3.1, H1/Table 1, Sec. 4.5.3, Sec. 5.2.1, Sec. 6.1 | M12: CLOSED PRE-FREEZE. VIX source/monthly history/panel mapping/scaling/economic label are validated and the thesis frames VIX as expected S&P 500 implied volatility used as a proxy for global financial stress, not pure risk aversion. The companion Fed 3M Forward audit also passed all six stages: Bloomberg USSOC Curncy / PX_LAST (3M USD OIS), daily history, month-end convention, 164/164 exact panel match, native percentage-point scaling and corrected technical definition. Final coefficient-movement/correlation diagnostics and final VIX sign/H1 prose are downstream tasks under MR-18/MR-19 after the frozen-panel DK rerun; they do not keep MR-09 open. | N12: Data/source audit + text revision + diagnostic; optional alternative proxy | O12: MR-18 correlation matrix | P12: PASSED: the VIX construct/proxy is justified and accurately labeled; its source, monthly mapping and scaling are validated. The companion nominal Fed control is independently sourced and reproduced end-to-end, including 164/164 exact panel-month matches and a technically correct OIS definition. Any post-freeze correlation table and final sign interpretation are assigned to MR-18/MR-19. | Q12: Yes | R12: Done | S12: Closed pre-freeze. 2-Oct director meeting reinforces the non-change decision: retain VIX, support it with literature, and avoid claiming it is pure risk aversion. No alternative proxy is required solely to answer the reviewer.
A13: MR-10 | B13: A-06 | C13: OG-04 | D13: Low | E13: Ailin | F13: Replace or complement VIX with a large composite PCA index. | G13: Ailin pp. 7-8, M4 | H13: Disagrees / not endorsed | I13: No mandatory replacement. Acknowledge alternatives; at most use one transparent proxy. | J13: Large extension with substantial discretion; not necessary to resolve the core criticism. | K13: D - Not endorsed / optional / response only | L13: Would affect Sec. 4.5.3, all regressions and Annex A | M13: Do not build the PCA as a mandatory revision. Mention as future research; optionally show one simple alternative proxy. | N13: No mandatory estimation | O13: MR-09 | P13: Response memo explains the narrower remedy. | Q13: No - response only | R13: Not started
A14: MR-11 | B14: A-02, A-04, A-12; D-03, D-15 | C14: OG-05 | D14: High | E14: Ailin + Daniel | F14: The literature bridge to factor exposure, stale OTC pricing and the closest empirical studies is too descriptive or incomplete. | G14: Ailin pp. 1, 3, 5-7; Daniel pp. 1-3 | H14: Partially agrees | I14: 24-Sep-2026: Daniel is less substantial than the other reports; bibliography is a minor, targeted correction. Add only literature that supports the actual specification, tests and limits. | J14: A concise, critical comparison is warranted; no theoretical overhaul. | K14: C - Presentation / structure / literature / documentation | L14: Secs. 3.1-3.3, 4.6-4.7, 5.2-5.4; References | M14: Add a concise factor/stale-price bridge and directly compare the closest local-currency corporate-debt and panel-method papers. Correct minor bibliography issues. | N14: Literature and interpretation rewrite | O14: MR-04, MR-25, MR-34 | P14: Each added reference is tied to a specific construct, test or limitation. | Q14: Yes | R14: Not started
A15: MR-12 | B15: M-02; D-07, D-17 | C15: OG-06 | D15: High | E15: Maximo + Daniel | F15: The thesis sometimes uses causal language although the design is observational and correlational. | G15: Maximo p. 1; Daniel pp. 2-3 | H15: No explicit position | I15: No direct Martin comment; consistent with the general instruction to avoid overstatement. | J15: Valid, low-cost wording correction. | K15: B - Clarification / reframing | L15: Sec. 4.3, 4.7; Resumen/Abstract; Conclusions | M15: Audit causal verbs and replace them with conditional-association language unless a specific identification argument supports causality. | N15: Text-only global edit | O15: Final model wording after MR-19 | P15: Abstract, methods, results and conclusions use consistent non-causal language. | Q15: Yes | R15: Not started
A16: MR-13 | B16: M-05; D-05, D-17 | C16: OG-07 | D16: High | E16: Maximo + Daniel | F16: The 4,229 rows do not equal 4,229 independent macro observations; the panel is strongly unbalanced with unequal bond histories. | G16: Maximo p. 2; Daniel pp. 2-3 | H16: Agrees / strongly agrees | I16: Clarify the effective monthly dimension and the panel-balance profile; do not overstate precision or generalizability. | J16: Does not invalidate panel estimation, but affects inference and exposition. | K16: B - Clarification / reframing | L16: Secs. 4.2-4.4, 5.1; Annex 8.10 | M16: Report observations, months, bonds and issuers separately; add T_i distribution, entry/exit years and annual coverage. | N16: Method clarification + table metadata | O16: MR-16 and MR-24 | P16: Methods and tables distinguish all dimensions and state unequal coverage clearly. | Q16: Yes | R16: Not started
A17: MR-14 | B17: M-06, M-17; D-11, D-18 | C17: OG-07 | D17: Critical | E17: Maximo + Daniel | F17: A time-invariant issue-size variable should be absorbed by bond fixed effects, yet a coefficient is reported; the sign also changes under PCSE. | G17: Maximo pp. 2, 4; Daniel pp. 2-3 | H17: Agrees / strongly agrees | I17: Audit completed. 2-Oct meeting: Martin agrees AMT_ISSUED is fixed but the quarterly asset denominator varies. He suggested turnover/amount outstanding as a conceptually cleaner secondary-market liquidity measure, then accepted that sparse trading would generate many zeros and little useful time variation. The retained ratio is defensible as a relative issue-size / primary-issuance-liquidity proxy. | J17: Resolved. The time-invariance concern applies to AMT_ISSUED in levels, not to the estimated ratio. The actual regressor is AMT_ISSUED / BS_TOT_ASSET; quarterly issuer assets create time variation. In the estimation sample 98/103 bonds (95.15%) exhibit within-bond variation, so the ratio is identified under bond fixed effects. The coefficient measures changes in relative issue size versus issuer scale, not changes in the original issue amount. | K17: A - Methodological issue / additional estimation | L17: Table 1 H6; Secs. 4.5.3 and 4.7; Table 3; Sec. 5.2.4; Sec. 6.1-6.2.2; Annex 8.6.2 and Table 7; Figure 3 | M17: Completed: trace AMT_ISSUED and issuer BS_TOT_ASSET from raw inputs; reconstruct the full panel; quantify within/between variation and quarterly timing; document the ‰ scale; retain and rename/define the variable consistently; revise FE identification and interpretation; keep a one-quarter-lagged denominator as timing robustness. | N17: Data audit + possible model revision | O17: Raw panel and code | P17: Passed: 4,229/4,229 observations reproduce from raw sources; 98/103 bonds vary within bond; the final variable name and ‰ units match construction; the thesis states that identification comes from the time-varying denominator and does not interpret the coefficient as the effect of changing AMT_ISSUED. | Q17: Yes | R17: Done | S17: Closed 30-Sep-2026 and reaffirmed 2-Oct. Keep contemporaneous AMT_ISSUED / BS_TOT_ASSET in the main model, Q-1 denominator as timing robustness, and clarify that the variable is not a clean secondary-market turnover measure. Low secondary-market trading is part of the rationale for the second-best primary issuance proxy. 9-Oct builder update: revised 4,648-row sample resolves relative issue size on every row using its own frozen timing rule: 4,602 same-quarter, 35 q-1 and 11 q-2 rows; 98/103 bonds retain within-bond variation. The q-2 rows are the documented IVPR3B BZ 2025Q2 case where both newer asset quarters are absent.
A18: MR-15 | B18: M-06; D-05 | C18: OG-07 | D18: Medium | E18: Maximo + Daniel | F18: Most regressors vary at month or firm-month level while same-firm bonds can have different spreads; substantial bond-time variation remains unexplained. | G18: Maximo p. 2; Daniel p. 2 | H18: Partially agrees | I18: Clarify what fixed effects do and do not absorb; no model can cover every bond-time factor. | J18: Primarily a scope and interpretation issue. | K18: B - Clarification / reframing | L18: Secs. 4.7-4.8, 5.3-5.4, 6.1 and limitations | M18: Explain identification at month, firm-month and bond-month levels; interpret low within R2 without claiming model failure. | N18: Clarification; optional controls | O18: MR-13 and MR-14 | P18: The thesis states FE limits and unexplained variation transparently. | Q18: Yes | R18: Not started
A19: MR-16 | B19: M-07, M-08, M-10, M-17, M-18; D-06, D-17 | C19: OG-08 | D19: Critical | E19: Maximo + Daniel | F19: Issuer-clustered errors ignore common shocks. Heteroskedasticity, cross-sectional dependence, serial autocorrelation and imbalance make inference estimator-sensitive. | G19: Maximo pp. 3-5; Daniel pp. 2-3 | H19: Agrees / strongly agrees | I19: 24-Sep: Driscoll-Kraay is the preferred reference inference. 25-Sep: remove separate conventional FE and PCSE columns. 2-Oct meeting: explicitly distinguish the bond-FE coefficient estimator from Driscoll-Kraay/PCSE treatment of the variance-covariance matrix, and verify/document what each covariance method handles (heteroskedasticity, serial correlation and cross-sectional dependence) for this highly unbalanced panel. | J19: Genuine inference correction. DK should anchor all significance claims, while its limitations are stated. | K19: A - Methodological issue / additional estimation | L19: Secs. 4.2, 4.6, 4.8, 5.1-5.3; Tables 2-3; Annex 8.10-8.11 | M19: Estimate coefficients with bond fixed effects and use Driscoll-Kraay covariance/standard errors for the sole main inference. Document DK lag/finite-sample choices and panel dimensions/diagnostics. Add a precise methods note distinguishing FE from the covariance correction and summarizing why DK is preferred to PCSE here. Keep PCSE/plain-FE outputs internal or appendix-only. | N19: Full re-estimation / inference reset | O19: MR-03 and final variable set | P19: One bond-FE/Driscoll-Kraay main table drives significance claims; the methods section accurately distinguishes coefficient estimation from covariance estimation and states the panel-structure rationale without overclaiming what DK solves. | Q19: Yes | R19: Not started | S19: 2-Oct meeting confirms the prior one-table decision and adds a technical documentation task: explain the exact DK-versus-PCSE covariance properties using a standard econometrics reference. Do not describe DK as a different coefficient estimator from FE.
A20: MR-17 | B20: M-09, M-17, M-18; D-06, D-11 | C20: OG-08 | D20: Critical | E20: Maximo + Daniel | F20: PCSE coefficients differ from FE even though the thesis presents PCSE as merely another error correction; sign/significance changes need explanation. | G20: Maximo pp. 3, 5; Daniel p. 2 | H20: Agrees / strongly agrees | I20: 25-Sep: highly unbalanced panel and limited common temporal overlap weaken the PCSE covariance estimate. 2-Oct: Martin asks for a technically precise comparison of PCSE and Driscoll-Kraay at the covariance/inference layer; PCSE should not be a main results competitor once DK is selected as the preferred approach. | J20: The old comparison is internally inconsistent. The code should be audited only to document what was run; the preferred output must not invite a FE-versus-PCSE horse race. | K20: A - Methodological issue / additional estimation | L20: Secs. 4.2, 4.6, 4.8, 5.1-5.3; Tables 3 and 7 | M20: Recover the exact PCSE command for internal audit, state its assumed covariance/error treatment accurately, contrast it with Driscoll-Kraay using a standard reference, and explain why panel imbalance/common overlap favor the chosen DK presentation. Remove PCSE from the main thesis/seminar table; retain only as a qualified appendix/internal diagnostic if useful. | N20: Code audit + table redesign | O20: Original do-file/logs; MR-16 | P20: The response memo states the panel-structure rationale precisely; the main results contain no PCSE column and make no unsupported claim that PCSE is merely an error correction. | Q20: Yes | R20: Not started | S20: 2-Oct meeting reaffirms exclusion from the main table and requires a precise technical rationale rather than a generic claim that PCSE merely corrects errors.
A21: MR-18 | B21: M-16, M-17; A-18 via Martin | C21: OG-08 | D21: Critical | E21: Maximo; reinforced by Martin | F21: The full model does not show how correlated aggregate regressors alter one another. Sequential specifications and correlation diagnostics are required. | G21: Maximo p. 4; Martin annotations/messages 24-25 Sep-2026; attached four-model table dated 25-Sep-2026 | H21: Agrees / strongly agrees | I21: 25-Sep: one consolidated four-column FE-DK table with nominal FED3M. 27-Sep: SELIC/Brazil 3M is referee-only. 2-Oct meeting: complete the explanatory-variable freeze first, then generate the new corrected DK regressions and robustness results for Martin by 10-Oct-2026; interpret/rewrite only after seeing the new estimates. | J21: This is now an exact paper/seminar output design rather than a generic robustness request. Two source ambiguities must be confirmed instead of silently resolved: Model 1 marks both NER and RER, and the text asks for sequential stacking while the template includes firm/bond controls in all four columns. | K21: A - Methodological issue / additional estimation | L21: Secs. 4.6-4.8, 5.1-5.4; Annex 8.11 | M21: After the panel is frozen, implement the four core bond-FE/DK columns using the finalized regressors and nominal FED3M. Report correlations/coefficient movements and required statistics. Then run the scoped Brazil 3M DI robustness with FED3M retained vs omitted. Keep covariance alternatives out of the main table. Deliver the new-results package by 10-Oct-2026. | N21: Additional estimation + single consolidated table + optional robustness | O21: MR-01, MR-03, MR-04, MR-16; confirmed model grid | P21: One pre-specified FE-DK table uses nominal FED3M Forward, documents every included block, reports diagnostics/statistics, and does not silently resolve the NER/RER or stacking ambiguities. Any SELIC columns are clearly separated and labeled referee-only. | Q21: Yes | R21: Not started | S21: Old 30-Sep target superseded. New director target: corrected regressions plus revised deck by 10-Oct-2026; review together during the week of 13-Oct-2026.
A22: MR-19 | B22: M-10, M-18; A-10, A-16; D-06, D-09, D-11, D-12, D-18 | C22: OG-08 | D22: Critical | E22: Ailin + Maximo + Daniel | F22: The submitted narrative relies on estimator-sensitive significance. Daniel asks that hypotheses be tied explicitly to final results and counterintuitive signs be explained better. | G22: Ailin pp. 3-4; Maximo pp. 3-5; Daniel pp. 2-3 | H22: Agrees / strongly agrees | I22: 24-Sep-2026: treat Daniel mainly as an exposition task after the core spread and DK work. Rebuild interpretations only after final estimates. | J22: Required downstream rewrite, not a separate empirical choice. | K22: B - Clarification / reframing | L22: Resumen/Abstract; Secs. 5.2-5.4; Secs. 6.1-6.4; Tables 3 and 7 | M22: After the estimation freeze, classify every hypothesis/result as robust, partial/sensitive, null or unresolved. Explain counterintuitive signs against the final DK sequence and avoid carrying old PCSE/FE claims forward. | N22: Results/abstract/conclusions rewrite | O22: MR-01 through MR-18 finalized | P22: A hypothesis-to-result and table-to-text audit confirms every sign, magnitude and significance statement. | Q22: Yes | R22: Not started
A23: MR-20 | B23: M-11; D-08, D-17 | C23: OG-09 | D23: Low | E23: Maximo + Daniel | F23: Persistence, serial correlation and inability to apply standard unit-root tests raise questions about dynamics and stationarity. | G23: Maximo pp. 3-4; Daniel pp. 2-3 | H23: Disagrees / not endorsed | I23: Do not convert the thesis to a dynamic panel or add a monthly lagged spread; markets are forward-looking. Acknowledge the limitation and answer it. | J23: The concern is real, but DK does not solve non-stationarity. A bounded explanation is required; first-difference work remains optional. | K23: D - Not endorsed / optional / response only | L23: Sec. 4.6; Sec. 5.1; Annex 8.11 | M23: Explain the static monthly specification, acknowledge persistence/unit-root limits and avoid claiming they are tested away. Keep first-difference robustness optional. | N23: No mandatory estimation; optional robustness | O23: MR-16 and MR-25 | P23: The response memo justifies the non-change and the thesis states the limitation accurately. | Q23: No - response only | R23: Not started
A24: MR-21 | B24: M-12 | C24: OG-09 | D24: Medium | E24: Maximo | F24: Collin-Dufresne, Goldstein and Martin (2001) is cited to justify levels although it studies spread changes. | G24: Maximo p. 3 | H24: Agrees / strongly agrees | I24: 24-Sep-2026: bibliography corrections are minor but should be made. | J24: Valid citation-accuracy correction independent of the model debate. | K24: C - Presentation / structure / literature / documentation | L24: Secs. 3.3 and 4.6; References | M24: Correct the citation and retain only sources that actually support the chosen specification. | N24: Literature correction | P24: The paper is described accurately and no unsupported citation claim remains. | Q24: Yes | R24: Not started
A25: MR-22 | B25: M-13 | C25: OG-10 | D25: Medium | E25: Maximo | F25: Debt/GDP is described as significant at 1 percent in text while the DK table reports 5 percent. | G25: Maximo pp. 3-4 | H25: No explicit position | I25: Covered by the instruction to rewrite results after final DK estimates. | J25: The original significance discrepancy is a reporting error. The deeper semantic issue is now resolved pre-freeze: legacy debt_gdp is Bloomberg EHBBBR fiscal/budget balance (% GDP), while the thesis H8 / variable definition and Martin's requested macro block require a public-debt/GDP stock. Decision: replace EHBBBR with official BCB SGS 13762 Gross General Government Debt (% GDP) using the selected uniform L2 timing rule during the controlled rebuild. The remaining MR-22 task is to reconcile the coefficient/significance wording against the final frozen-panel DK estimates. | K25: C - Presentation / structure / literature / documentation | L25: Sec. 5.2.2; Table 3; Annex Table 7 | M25: During the one controlled reproducible panel rebuild, replace legacy debt_gdp/EHBBBR with BCB SGS 13762 and use the final field name public_debt_gdp with the selected uniform L2 reference-month mapping; update data/code/table/thesis labels consistently. After the frozen-panel FE-DK rerun, reconcile the reported significance level and run a complete table-to-text audit. | N25: Text correction | O25: WP-06 fiscal-control decision; MR-19 | P25: Economic concept/label is correct and the final coefficient/significance wording matches the final DK table exactly. | Q25: Yes | R25: In progress | S25: 3-Oct audit traced legacy debt_gdp to Bloomberg EHBBBR fiscal/budget balance, not public debt/GDP. 5-Oct decision selected BCB SGS 13762 Gross General Government Debt (% GDP) with uniform L2 timing. 9-Oct-2026 WP-06 closure: the reproducible builder now implements the uniform L2 mapping across all 175 revised months and the frozen candidate panel contains the corrected debt-stock control. Implementation/reproducibility is closed under commit 23435a4. MR-22 remains In progress only for the post-freeze coefficient/significance wording and final table-to-text audit after WP-07/WP-08 estimates.
A26: MR-23 | B26: M-14 | C26: OG-10 | D26: Medium | E26: Maximo | F26: The thesis says PCSE corrects serial correlation, which is not necessarily true without an explicit autoregressive transformation. | G26: Maximo p. 4 | H26: Agrees / strongly agrees | I26: Remove PCSE from the main thesis/seminar and delete unsupported claims. 2-Oct meeting adds that FE defines the coefficient estimation while PCSE/DK primarily alter covariance/inference; verify the exact correlation/heteroskedasticity assumptions before writing the methods text. | J26: Valid technical correction. | K26: C - Presentation / structure / literature / documentation | L26: Secs. 4.8, 5.1; Annex 8.10.4 | M26: Delete the unsupported statement that PCSE automatically corrects serial correlation. If PCSE is mentioned in an appendix, state the exact command/error structure and limitations. In the main methods discussion, distinguish FE coefficient estimation from DK/PCSE covariance treatment and cite an appropriate econometrics reference. | N26: Technical text correction | O26: MR-17 | P26: No unsupported PCSE statement remains. | Q26: Yes | R26: Not started
A27: MR-24 | B27: M-15 | C27: OG-10 | D27: High | E27: Maximo | F27: The main regression table omits standard errors and N. | G27: Maximo p. 4 | H27: Agrees / strongly agrees | I27: 25-Sep-2026: the director-provided table explicitly requests Within R-squared and rho under each of the four FE-DK models. Existing matrix requirements for SE, N, panel dimensions and DK metadata remain. | J27: Essential reporting standard. | K27: C - Presentation / structure / literature / documentation | L27: Table 3; Annex Table 7; table notes | M27: Build one consolidated FE-DK table reporting coefficient, standard error, N, bonds, issuers, months, within R2, rho, FE type, DK lag, units and significance legend; place diagnostic-test information immediately below or in a linked panel. | N27: Table redesign | O27: MR-16 and MR-18 | P27: A reader can evaluate every coefficient and model statistic in the single consolidated table and compare specifications directly. | Q27: Yes | R27: Not started | S27: The attached 25-Sep template names Within R-squared and rho explicitly.
A28: MR-25 | B28: A-10, A-12; M-11, M-16 | C28: OG-11 | D28: High | E28: Ailin + Maximo | F28: Stale or lagged OTC quotes may mechanically compress measured spreads when the liquid reference curve moves quickly. | G28: Ailin pp. 3, 5-6; Maximo pp. 3-4 | H28: Partially agrees | I28: Earlier guidance: add the limitation and a bounded diagnostic. 2-Oct meeting: first try the regenerated model without the prior-value fill-forward. If the no-fill sample is impractical because of illiquidity/coverage, explain the technical/data constraint and the rationale for a last-observed-quote convention. Thiago also described excluding Bloomberg BVAL/Bival indicative/model marks; document this rule explicitly. | J28: Serious OTC measurement limitation that now has a concrete data-treatment audit: observed-source hierarchy/BVAL treatment plus fill-forward sensitivity. Excluding BVAL does not make every remaining quote a transaction, so source semantics must be precise. | K28: B - Clarification / reframing | L28: Secs. 2.1.1, 4.5.2, 4.6, 5.2.1, 5.2.3, 6.1-6.3; Annex 8.2 and 8.5 | M28: Treat the revised corporate pricing/source hierarchy as the frozen baseline rule. The problematic BVAL/indicative observation was already replaced by the next-best available source rather than retained under its odd convention; document this explicitly. Do not reopen the source-selection decision absent material new evidence. Any no-fill-forward or alternative missing-price convention is sensitivity only after the authoritative panel is built. | N28: Data-treatment audit + sensitivity estimation + text | O28: MR-03; source fields; Data Freeze Gate / final panel build | P28: Pricing-source semantics and the baseline source hierarchy are explicit and reproducible; BVAL/indicative marks are not silently treated as executed prices. The baseline source decision is frozen before the controlled panel rebuild; alternative missing-price treatment, if run, is clearly sensitivity. | Q28: Yes - minimum scope | R28: In progress | S28: 7-Oct governance closure froze the revised corporate-pricing/source hierarchy and BVAL replacement rule. 9-Oct-2026 Data Freeze PASS embeds that authoritative pricing input in the reproducible 4,648-row panel under commit 23435a4. No pre-freeze pricing decision remains open. Remaining MR-25 work is documentation and, only if useful after the core rerun, a separately labelled no-fill-forward/missing-price sensitivity.
A29: MR-26 | B29: A-10, A-11, A-16; M-16, M-18 | C29: OG-11 | D29: High | E29: Ailin + Maximo | F29: Unexpected signs are discussed with generic emerging-market narratives rather than Brazil-specific institutions. | G29: Ailin pp. 3-4; Maximo pp. 4-5 | H29: Agrees / strongly agrees | I29: Use Selic/DI/IPCA structure, institutional investors, indexed liabilities and Law 12.431 in interpretation. 25-Sep-2026: Martin reports nominal and real exchange rates give almost the same result/significance; RER remains meaningful as a relative price. 27-Sep: the local reference curve already embeds SELIC at the short end; any direct SELIC 3M Forward regression is only a referee diagnostic. | J29: Valid reframing; mechanisms must be distinguished from tested evidence. | K29: B - Clarification / reframing | L29: Secs. 2.1.1, 3.1, 5.2.1, 5.2.3, 5.4, 6.1-6.3; Glossary | M29: Rewrite mechanisms around Brazilian real-rate institutions, distinguish evidence from plausible channels, and explain the RER robustness as a relative-price channel. Do not add SELIC mechanically to the baseline or reintroduce inflation without a clear identification role. | N29: Interpretation rewrite | O29: MR-01, MR-04, MR-06/07, MR-19, MR-25 | P29: Every counterintuitive sign has a Brazil-specific but appropriately qualified interpretation. | Q29: Yes | R29: Not started | S29: NER/RER similarity is a reported director observation to verify in the regenerated estimates.
A30: MR-27 | B30: A-08, A-09 | C30: OG-12 | D30: Critical | E30: Ailin | F30: The thesis lacks a complete computational replication package, including source consolidation, queries, dates, code and Nelson-Siegel settings. | G30: Ailin p. 2, p. 10, M7 | H30: Agrees / strongly agrees | I30: Deliver the complete package, subject to data licensing. | J30: Mandatory submission deliverable. | K30: C - Presentation / structure / literature / documentation | L30: Secs. 4.4-4.5; Annex 8.1-8.14 | M30: Create README, environment, ordered scripts, queries, extraction dates, hashes, OTC source rules, missing/outlier treatment, accounting timing and curve-estimation settings. Clean-run all outputs. | N30: Replication package / documentation | O30: Final code and outputs | P30: A clean run regenerates every permitted table and figure. | Q30: Yes | R30: Not started
A31: MR-28 | B31: A-08 | C31: OG-12 | D31: Medium | E31: Ailin | F31: Bloomberg is sometimes described as the original source where it is an access vendor or aggregator. | G31: Ailin p. 2 | H31: No explicit position | I31: Covered within the broader replication package. | J31: Valid provenance issue. | K31: C - Presentation / structure / literature / documentation | L31: Secs. 2.1.1, 4.5.2-4.5.3; figure notes; References; Annex A | M31: Create a data dictionary separating original producer, access channel, ticker/query, field, frequency, transformation and extraction date. | N31: Source and documentation revision | O31: MR-27 | P31: Every variable and figure has a traceable provenance chain. | Q31: Yes | R31: Not started
A32: MR-29 | B32: A-15 | C32: OG-13 | D32: Low | E32: Ailin | F32: Build a new sovereign-versus-corporate breakeven analysis including synthetic fixed-rate equivalents for CDI-linked debentures. | G32: Ailin pp. 8-10, M6 | H32: Disagrees / not endorsed | I32: This is a separate research project; the thesis must have a bounded end. | J32: Not proportionate to the current TFM revision. | K32: D - Not endorsed / optional / response only | L32: Would require major new material beyond Secs. 4-6 and Annex A | M32: Do not add the full exercise. Mention it as a future research extension and explain scope in the response memo. | N32: No thesis modification beyond future research | P32: Future-research paragraph captures the idea without implying it was estimated. | Q32: No - response only | R32: Not started
A33: MR-30 | B33: A-10, A-11, A-16, A-18; M-10, M-16, M-18; D-01, D-04, D-09, D-10, D-12, D-13, D-16, D-18 | C33: OG-11 | D33: Critical | E33: Ailin + Maximo + Daniel | F33: The abstract, results and conclusions over-center anomalous signs and imply broader hypothesis confirmation than the estimator sensitivity supports. | G33: Ailin pp. 3-4; Maximo pp. 3-5; Daniel pp. 1-3 | H33: Agrees / strongly agrees | I33: 24-Sep-2026: Daniel is less substantial, but his main expositional requests are valid: link hypotheses to results and explain counterintuitive signs. For seminars emphasize external versus internal factors and show only the final DK evidence. | J33: Final synthesis task after empirical freeze. | K33: B - Clarification / reframing | L33: Resumen/Abstract; Introduction; Secs. 5.2-5.4 and 6.1-6.4; defense/seminar deck | M33: Rewrite around a robust/partial/null/unresolved hierarchy; add a hypothesis scorecard; emphasize external versus internal determinants; explain scoped non-changes and future extensions. | N33: Full narrative rewrite + response memo | O33: All empirical and literature revisions complete | P33: Thesis, response memo and seminar deck classify each hypothesis consistently and do not overstate results. | Q33: Yes | R33: Not started
A34: MR-31 | B34: D-01, D-02, D-13, D-16 | C34: OG-14 | D34: High | E34: Daniel | F34: The research gap and originality are asserted more than demonstrated, and three broad questions obscure the central contribution. | G34: Daniel pp. 1-3 | H34: Partially agrees | I34: 24-Sep-2026: Martin reads Daniel as less substantial than Ailin and Maximo. Address this as a selective exposition improvement after the spread and estimator issues, not as a redesign. | J34: Valid framing correction; final wording should match the revised evidence. | K34: B - Clarification / reframing | L34: Resumen/Abstract; Introduction; literature/framework; Sec. 6; defense/PPT | M34: State one primary question, subordinate secondary questions, and demonstrate the contribution against the closest empirical studies. Link data, curve and empirical design to concrete contributions. | N34: Introduction/contribution rewrite | O34: Final results; MR-30 and MR-34 | P34: One central question and two or three evidence-backed contributions are stated clearly. | Q34: Yes | R34: Not started | S34: Secondary to Maximo-driven measurement and estimator work.
A35: MR-32 | B35: D-03, D-04, D-18 | C35: OG-14 | D35: High | E35: Daniel | F35: The theoretical framework is descriptive; nine hypotheses may exceed the identifying capacity of one panel and some proxies are contestable. | G35: Daniel pp. 1, 3 | H35: Partially agrees | I35: Keep the paper empirical. Rationalize the theory-to-variable chain and link hypotheses to final results without a structural-theory redesign. | J35: The issue is sharper architecture, not more theory. | K35: C - Presentation / structure / literature / documentation | L35: Sec. 3; Sec. 4.1; variable definitions; results and defense | M35: Create a construct-to-proxy table; designate core versus secondary hypotheses; produce a final supported/partial/not-confirmed scorecard. | N35: Theory-to-specification mapping | O35: Final variable definitions; MR-11, MR-19, MR-30 | P35: Every retained hypothesis has a defensible proxy and maps to a final result. | Q35: Yes | R35: Not started
A36: MR-33 | B36: D-14 | C36: OG-15 | D36: Medium | E36: Daniel | F36: A final academic-language and consistency review is needed for causal wording, econometric phrasing, repetition and multilingual terminology. | G36: Daniel p. 2 | H36: Partially agrees | I36: Treat as a minor final-stage correction after all estimates and tables are frozen. | J36: Low methodological risk but worthwhile for submission quality. | K36: C - Presentation / structure / literature / documentation | L36: Entire thesis | M36: Run a controlled final terminology, language, acronym, table-text and cross-reference QA pass. | N36: Final copy-edit / QA | O36: All empirical outputs and narrative revisions complete | P36: No inconsistent variable names, undefined acronyms, causal overclaims or table-text mismatch remain. | Q36: Yes | R36: Not started
A37: MR-34 | B37: D-15 | C37: OG-16 | D37: Medium | E37: Daniel | F37: The literature review should be more critical and current; bibliometrics do not replace direct comparison with comparable empirical work. | G37: Daniel pp. 2-3 | H37: Partially agrees | I37: 24-Sep-2026: bibliography issues are minor. Make bounded, purpose-driven updates; do not turn the thesis into a new survey. | J37: Efficient remedy is a direct comparison tied to data, benchmark, estimator, identification and findings. | K37: C - Presentation / structure / literature / documentation | L37: Literature review; methods justification; introduction contribution; bibliography; defense | M37: Add a compact closest-study comparison and recent method references directly supporting DK, local-currency debt and macrofinance identification. | N37: Targeted literature review | O37: MR-11, MR-31, MR-32; final method choice | P37: Closest studies are compared critically and new citations support actual model choices. | Q37: Yes | R37: Not started

Sheet Juror Log
A1: Juror-by-Juror Source Log
A2: Traceability sheet: every distinct criticism from all three reports maps to one or more consolidated master issues. Daniel dispositions reflect Martin's review on 24-Sep-2026.
A3: Source ID | B3: Juror | C3: Report location | D3: Original criticism - concise | E3: Master issue ID(s) | F3: Overlap group | G3: Martin position / disposition
A4: A-01 | B4: Ailin | C4: p. 1; pp. 7-8 | D4: VIX operationalization differs from Gonzalez-Rozada and Levy-Yeyati (2008) and is not justified. | E4: MR-09, MR-10 | F4: OG-04 | G4: Partial agreement: justify VIX; no mandatory replacement.
A5: A-02 | B5: Ailin | C5: p. 1; p. 3; pp. 5-7 | D5: Missing SDF/Euler, Fama (1984), Lustig et al. (2011) and related asset-pricing bridge. | E5: MR-04, MR-05, MR-11 | F5: OG-02 / OG-05 | G5: Partial agreement: concise bridge, no theoretical redesign.
A6: A-03 | B6: Ailin | C6: p. 2; p. 6; M1 | D6: Sovereign indicator reuses the IPCA curve; long end may be near zero by construction and short end a market basis. | E6: MR-01, MR-02 | F6: OG-01 | G6: Now high priority: answer through sovereign-ceiling framing, matching and robustness.
A7: A-04 | B7: Ailin | C7: p. 2; pp. 5-7; M3 | D7: Implicit beta=1 to the real-curve factor; domestic real rate omitted. | E7: MR-04, MR-05 | F7: OG-02 | G7: SELIC not added separately; bounded real-curve diagnostic only.
A8: A-05 | B8: Ailin | C8: p. 2; p. 7; M2 | D8: Arithmetic spread calculation is inconsistent with compounding conventions. | E8: MR-03 | F8: OG-02 | G8: Agrees: recalculate geometrically/log-consistently.
A9: A-06 | B9: Ailin | C9: p. 2; pp. 7-8; M4 | D9: VIX is not pure risk aversion; use a composite PCA index. | E9: MR-09, MR-10 | F9: OG-04 | G9: No mandatory PCA; justify VIX and acknowledge alternatives.
A10: A-07 | B10: Ailin | C10: p. 2; pp. 9-10; M5 | D10: Rating heterogeneity must be modeled, not used ex post. | E10: MR-06, MR-07 | F10: OG-03 | G10: Agrees on bounded rating/sector tests.
A11: A-08 | B11: Ailin | C11: p. 2 | D11: Bloomberg is an access channel, not always the primary source. | E11: MR-28 | F11: OG-12 | G11: Handle within data provenance.
A12: A-09 | B12: Ailin | C12: p. 2; p. 10; M7 | D12: No complete replication package. | E12: MR-27 | F12: OG-12 | G12: Agrees: deliver complete package.
A13: A-10 | B13: Ailin | C13: p. 3 | D13: Central signs have plausible mechanical explanations that are not ruled out. | E13: MR-01, MR-25, MR-30 | F13: OG-01 / OG-11 | G13: Rewrite after spread/DK work; test or qualify mechanisms.
A14: A-11 | B14: Ailin | C14: p. 3; p. 4; M8 | D14: Interpretation omits Selic, real curve, investors and Law 12.431. | E14: MR-26, MR-30 | F14: OG-11 | G14: Deepen Brazil-specific interpretation; no mechanical SELIC inclusion.
... A57: D-18 | B57: Daniel | C57: p. 3 | D57: Defense must discuss counterintuitive signs, issue-size sensitivity and non-robust firm variables. | E57: MR-09, MR-14, MR-19, MR-30, MR-32 | F57: OG-04 / OG-07 / OG-11 / OG-14 | G57: Use final H-result scorecard and robust/partial/null hierarchy.

Sheet Director Guidance
A1: Director Follow-up Guidance
A2: Traceability for Martin Grandes' September 2026 audio/text guidance. Entries through 27-Sep-2026 update disposition, scope and the exact estimation output; they are not additional juror criticisms.
A3: Guidance ID | B3: Source / date | C3: Topic | D3: Director guidance - condensed | E3: Master issue / WP | F3: Disposition | G3: Required incorporation
A4: MG-01 | B4: WhatsApp audio, Sep-2026 | C4: Dynamic panel / lagged spread | D4: A one-month lag of price/spread has no clear economic role in a forward-looking market at monthly frequency; answer the juror but do not make the model dynamic. | E4: MR-20 / WP-16 | F4: Not endorsed for main model | G4: Add a concise static-model rationale, acknowledge persistence and include the non-change in the response memo/PPT.
A5: MG-02 | B5: WhatsApp audio, Sep-2026 | C5: SELIC - first rationale | D5: Do not add SELIC mechanically; it may duplicate the U.S. forward rate plus expected BRL depreciation. | E5: MR-04, MR-26 / WP-04 | F5: Diagnostic first | G5: Document overlap and incremental information before any robustness use.
A6: MG-03 | B6: WhatsApp audio, Sep-2026 | C6: Sovereign risk measure | D6: The relevant object is Brazil sovereign risk in local currency, not international USD CDS; this is why local curves were built. 27-Sep-2026 clarification: USD CDS 5Y was never part of the economic model and should not be introduced. | E6: MR-01, MR-02 / WP-02 | F6: Core clarification | G6: Keep the primary benchmark local and matched; verify USD CDS 5Y is absent from the model and remove any secondary-control language suggesting otherwise.
A7: MG-04 | B7: WhatsApp audio, Sep-2026 | C7: Heterogeneity | D7: Differences across bonds or groups by sector/industry may be important, but the revision should remain bounded. | E7: MR-06, MR-07 / WP-05 | F7: Endorsed parsimoniously | G7: Use pre-specified rating/sector groups and equality tests; avoid an unlimited battery.
A8: MG-05 | B8: WhatsApp audio, Sep-2026 | C8: Theoretical scope | D8: Acknowledge what theory can derive, but the thesis/paper is empirical and should not be redesigned as a theoretical model. | E8: MR-05, MR-11, MR-32, MR-34 / WP-11 | F8: Bounded clarification | G8: Strengthen the theory-to-specification bridge only where it supports the empirical design.
A9: MG-06 | B9: WhatsApp audio/text, Sep-2026 | C9: Geneva presentation | D9: Shorten the deck; remove excessive methodology/literature; emphasize external versus internal factors and state what was not estimated and why. | E9: MR-30, MR-31 / WP-14, WP-16 | F9: Presentation requirement | G9: Build the concise narrative after final results.
A10: MG-07 | B10: Follow-up text, Sep-2026 | C10: Issuer/bond point estimates | D10: Issuer-level and, where sufficiently powered, bond-level heterogeneous estimates may be informative; small-T slopes can be imprecise. | E10: MR-05, MR-06 / WP-05, WP-16 | F10: Extension / bounded test | G10: Prioritize grouped tests; disclose precision limits and do not delay the TFM for 103 separate slopes.
A11: MG-08 | B11: WhatsApp audio, Sep-2026 | C11: Revision scope | D11: Respond to every comment, but not every suggested extension must be implemented; the thesis must have a bounded end. | E11: All / Action Sequence | F11: Scope-control principle | G11: Map each point to a change, diagnostic, defense answer or reasoned non-change.
A12: MG-09 | B12: WhatsApp text, 24-Sep-2026 | C12: Daniel report triage | D12: Daniel is less substantive than Ailin and Maximo. His main points are better hypothesis-result links, clearer explanations of counterintuitive signs, visible treatment of estimation problems already addressed, and minor bibliography corrections. | E12: MR-09, MR-11, MR-16, MR-19, MR-30-MR-34 / WP-07, WP-11, WP-13, WP-14 | F12: Selective / secondary priority | G12: Do not redesign the model for Daniel. Implement targeted exposition, diagnostics visibility and bibliography clean-up after the core empirical work.
A13: MG-10 | B13: WhatsApp text, 24-Sep-2026 | C13: SELIC - final disposition | D13: Do not include SELIC as a separate baseline regressor: beyond the redundancy argument, it anchors the short end of the local reference curve. A 3M Forward SELIC may be run only as a referee diagnostic under the later specified exclusions. | E13: MR-04, MR-26 / WP-04 | F13: Baseline excluded; referee diagnostic only | G13: Explain the non-inclusion in the thesis/response; do not add SELIC mechanically. If run, keep SELIC 3M Forward outside the preferred baseline.
A14: MG-11 | B14: WhatsApp text, 24-Sep-2026 | C14: Sovereign ceiling and matched-yield formulation | D14: Corporate excess or shortfall relative to the sovereign is closely related to the sovereign-ceiling hypothesis. 27-Sep-2026 clarification: the preferred econometric model keeps Corporate Spread = corporate YTM - local reference yield and Sovereign Risk = government YTM - the same local reference yield as separate variables, because the objective is to estimate how the first responds to the second. A direct corporate-minus-sovereign spread is a related alternative, not an identical econometric specification. | E14: MR-01, MR-02 / WP-02 | F14: Top substantive priority | G14: Add sovereign-ceiling framing, matching audit and literature justification for the preferred two-spread transmission specification; do not replace the dependent corporate spread with a direct corporate-sovereign differential.
... A32: MG-29 | B32: Zoom meeting, 2-Oct-2026 | C32: Delivery and presentation sequence | D32: Finish explanatory-variable audits first, then rerun the corrected models and robustness checks. Send the new estimates and an updated presentation by 10-Oct-2026. Review results together during the week of 13-Oct. Make the presentation more visual and parsimonious, with results given adequate space and dense methodology/literature reduced or moved to appendix. | E32: MR-18, MR-24, MR-30 / WP-08, WP-12, WP-16 | F32: Updated milestone | G32: Use 10-Oct as the working empirical/deck target; revise interpretation, abstract and final presentation after seeing the new results.

Sheet Overlap Map
A1: Overlap Map
A2: Shows where jurors raise the same underlying problem and defines one unified resolution to prevent duplicate work.
A3: Overlap group | B3: Cross-juror overlap? | C3: Theme | D3: What the reports/director say | E3: Master issue IDs | F3: Unified resolution | G3: Duplication-control note
A4: OG-01 | B4: Yes | C4: Sovereign measure construction, sovereign ceiling and interpretation | D4: Ailin questions the shared benchmark; Maximo shows the algebra; Daniel asks for a better negative-sign explanation. Martin clarified that Sovereign Risk (BRL) is a government-minus-local-reference spread, not a CDS, and that the preferred model keeps Corporate Spread and Sovereign Risk separate to estimate transmission. The final implementation/documentation now distinguishes the IPCA-real corporate benchmark from the nominal DI sovereign benchmark rather than asserting an identical curve. | E4: MR-01, MR-02 | F4: Upstream sovereign construction closed 29-Sep-2026: nominal formula, same-date exact-tenor DI matching, source hierarchy and geometric spread validated; sovereign_spread_brl terminology adopted and CDS language removed. Panel-field reconciliation closed 4-Oct-2026: legacy synthetic_cds_brl is not equivalent and must be replaced in the controlled rebuild. Final coefficient refresh remains downstream of the remaining pre-freeze decisions. | G4: Do not create a new CDS-like proxy. Do not reopen WP-02 when final regressions are rerun; only refresh coefficients/interpretation using the frozen explanatory-variable set.
A5: OG-02 | B5: No - Ailin | C5: Spread construction and real-curve exposure | D5: Arithmetic spread, implicit beta=1, missing real-rate factors and full Fama-MacBeth ideal. | E5: MR-03, MR-04, MR-05 | F5: Recalculate spreads; justify baseline SELIC non-inclusion; if useful, run only the two scoped SELIC 3M Forward referee checks; use bounded real-curve diagnostics; leave Fama-MacBeth as future research. | G5: MR-03 precedes every re-estimation; SELIC 3M Forward is diagnostic only, not a baseline redesign.
A6: OG-03 | B6: Yes | C6: Heterogeneous sovereign transmission and ratings | D6: Ailin/Maximo/Daniel criticize one average coefficient followed by heterogeneous explanations. | E6: MR-06, MR-07, MR-08 | F6: Use parsimonious rating and sector groups; issuer/bond slopes only where powered; events optional. | G6: One grouped table can answer multiple comments.
A7: OG-04 | B7: Yes | C7: VIX and global-risk proxy | D7: Both main jurors question the proxy; Daniel asks for direct hypothesis/sign interpretation. | E7: MR-09, MR-10 | F7: Closed proxy/data-definition portion: retain VIX as an S&P 500 implied-volatility / global-financial-stress proxy, not pure risk aversion; large PCA rebuild rejected. VIX data mapping/scaling and the companion Fed 3M Forward control are fully audited. Post-freeze correlations/sequential DK and final VIX sign interpretation are handled under MR-18/MR-19. | G7: Do not reopen MR-09 during the final rerun; use MR-18 for correlations/coefficient movement and MR-19 for the final hypothesis/sign narrative.
A8: OG-05 | B8: Ailin + Daniel | C8: Asset-pricing and literature bridge | D8: Ailin asks for factor/stale-price literature; Daniel asks for a more critical review. | E8: MR-11 | F8: Add concise, purpose-driven literature tied to actual tests and closest studies. | G8: Do not turn the revision into a theory survey.
A9: OG-06 | B9: Maximo + Daniel | C9: Causality versus association | D9: Both reports flag causal overstatement. | E9: MR-12 | F9: Global wording audit after final results. | G9: Low effort, high credibility.
A10: OG-07 | B10: Maximo + Daniel | C10: Identifying variation and issue-size identification | D10: Monthly common factors, unbalanced bond histories and possible time-invariant issue size. | E10: MR-13, MR-14, MR-15 | F10: WP-03/MR-14 closed 30-Sep-2026: relative issue size reconstructed and shown to vary within 98/103 bonds; units/timing/FE interpretation documented. Remaining MR-13/MR-15 work is to report panel dimensions/coverage and state FE limits in WP-10. | G10: Do not reopen the issue-size construction audit in WP-10; use the completed WP-03 evidence and focus WP-10 on broader identifying variation and panel imbalance.
A11: OG-08 | B11: Cross-juror synthesis | C11: Estimator, diagnostics, sequential specifications and final significance | D11: Maximo provides the detailed DK/PCSE critique; Daniel asks for estimator-problem visibility; Martin specifies the exact 25-Sep one-table output. | E11: MR-16, MR-17, MR-18, MR-19 | F11: Use one FE-DK table only, show diagnostics, discard PCSE/plain FE columns, use nominal FED3M, run the specified sovereign/macro and FX variants, then rewrite results. | G11: Do this once after the spread is frozen; confirm the two source-template ambiguities before coding.
A12: OG-09 | B12: Maximo + Daniel | C12: Persistence, levels and citation support | D12: Questions on stationarity/dynamics plus inaccurate citation use. | E12: MR-20, MR-21 | F12: Correct the citation; provide a bounded static-model response; no dynamic redesign. | G12: Separate the valid citation fix from the non-endorsed extension.
A13: OG-10 | B13: Maximo; reinforced by Daniel sensitivity | C13: Regression-table accuracy and completeness | D13: Significance mismatch, PCSE claim and missing SE/N. | E13: MR-22, MR-23, MR-24 | F13: One final consolidated FE-DK table with SE/N/panel dimensions, within R2, rho, DK metadata and a table-to-text QA pass. | G13: Do not repair old tables before final estimates.
A14: OG-11 | B14: Yes | C14: Untested narratives, Brazil mechanisms and final contribution | D14: Ailin emphasizes stale pricing/Brazil institutions; Maximo demands tests; Daniel asks for sign and hypothesis-result clarity. | E14: MR-25, MR-26, MR-30 | F14: Test what is feasible, label mechanisms, and rewrite contribution around final evidence. | G14: One integrated final narrative addresses all three.
... A19: OG-16 | B19: Daniel; complements Ailin | C19: Critical and recent comparable literature | D19: Bibliometrics do not replace direct comparison with relevant empirical work. | E19: MR-34; linked MR-11 and MR-31 | F19: Make minor, targeted bibliography corrections and a compact closest-study comparison. | G19: Keep additions purpose-driven and bounded.

Sheet Action Sequence
A1: Action Sequence
A2: Dependency-based workflow updated 9-Oct-2026 after the Econometric Panel Data Freeze Gate PASSED. Order now: frozen 4,648-row reproducible panel -> CURRENT bond-FE / Driscoll-Kraay inference reset and core table -> targeted robustness/sensitivity -> interpret/rewrite -> presentation/replication. WP-02 source/formula remains closed and WP-06 has resolved the downstream sovereign mapping plus public-debt L2 timing. Reproducibility commit 23435a4 records the builder and candidate panel.
A3: Order | B3: Phase | C3: Master issue IDs | D3: Core tasks | E3: Deliverable | F3: Dependency | G3: Gate / decision rule
A4: 0 | B4: Governance and baseline | C4: MR-27, MR-30 | D4: Freeze the submitted thesis, code, data and outputs; maintain a response memo keyed to master IDs. | E4: Baseline archive + response memo shell | G4: Do not edit the only submitted copy.
A5: 1 | B5: Data and measurement audit | C5: MR-01, MR-02, MR-03, MR-14, MR-28 | D5: WP-01 corporate-spread measurement, WP-02 Sovereign Risk (BRL) formula/source, WP-03 relative issue-size identification and baseline explanatory-variable audits are closed. The reproducible builder has now implemented most panel fields. Do not manually patch the legacy XLSX. WP-02 remains closed, but WP-06 must still resolve how the canonical 582-observation nominal sovereign package can support the intended 2010-2025 corporate panel without invalid extrapolation/latest-curve logic. | E5: Verified corporate spread + frozen WP-02 sovereign definition + closed relative issue-size audit; sovereign full-panel mapping handled under WP-06 | F5: Phase 0 | G5: Measurement/source decisions remain frozen. New distinction: the 582/582 sovereign validation establishes arithmetic/source integrity for available observations, not full panel coverage. The reproducibility gate must solve that downstream mapping explicitly.
A6: 2 | B6: Explanatory-variable audit and Econometric Panel Data Freeze Gate | C6: Data Freeze Gate PASSED; baseline explanatory-variable audits complete; MR-04 robustness parked until after core rerun | D6: COMPLETED. Reproducible construction replaces manual panel assembly: 4,648-row spine, corrected corporate spread, macro block, SGS 13762 uniform-L2 fiscal control, PIT accounting controls, relative issue size, BUS/252 maturity and frozen sovereign mapping. Candidate panel passes structural and variable-level reconciliation; legacy workbook remains archival/unchanged. Sovereign is populated contemporaneously from 2016 onward (3,918 rows) with 730 documented pre-2016 missing rows and no backward time extrapolation. | E6: Frozen panel_main_and_robustness_rebuilt.xlsx + reconciliation record + commit 23435a4 | F6: Phase 1 | G6: PASSED 9-Oct-2026. WP-07/WP-08 may now use the frozen rebuilt panel; do not silently revert to legacy definitions.
A7: 3 | B7: Econometric reset - CURRENT | C7: MR-16, MR-17, MR-18, optional MR-20 | D7: CURRENT after Data Freeze PASS: use one bond-FE table with Driscoll-Kraay covariance/standard errors as the main inference. Audit exact FE/DK/PCSE commands, lock DK lag/finite-sample choices and panel diagnostics, then run the four-model core grid on the frozen rebuilt panel. Plain-FE/PCSE comparison columns remain outside the main table. After the core rerun, execute Brazil 3M DI and other targeted robustness; alternate missing-price treatment remains sensitivity only. | E7: Single four-model DK table + agreed robustness/sensitivity package + diagnostics; target delivery to Martin 10-Oct-2026 | F7: Phase 2 | G7: Proceed now on the frozen panel. Confirm remaining NER/RER and stacking ambiguities, then execute the core DK table before optional robustness.
A8: 4 | B8: Literature, methods and framing | C8: MR-11, MR-12, MR-13, MR-15, MR-21, MR-26, MR-31, MR-32, MR-34 | D8: Rating evidence is already audited and frozen as descriptive-only; integrate the resulting coverage/table into the jury response/appendix. In parallel or after core estimates: clarify panel imbalance/identifying variation; document pricing/BVAL source semantics; correct causal/citation language and bounded literature/theory framing. Extra rating/sector/issuer/bond heterogeneity estimation remains optional only if powered. | E8: Revised Introduction and Chapters 3-4 | F8: Can proceed partly in parallel; final wording after Phase 3 | G8: Keep evidence separate from mechanisms; no theoretical redesign.
A9: 5 | B9: Results and conclusion rewrite | C9: MR-19, MR-22, MR-24, MR-30, MR-33 | D9: Rebuild tables; link every hypothesis to final results; explain counterintuitive signs; add scorecard and final QA. | E9: Revised Chapters 5-6, abstract/resumen and copy-edit | F9: Phases 3 and 4 | G9: Run table-to-text, hypothesis-to-result and terminology checks.
A10: 6 | B10: Replication, response and seminars | C10: MR-27, MR-30, MR-31, MR-32; response-only MR-05, MR-08, MR-10, MR-20, MR-29 | D10: Clean-run the package; finalize the three-juror response memo; prepare the agreed DK table and a concise visual defense/Bordeaux/Geneva deck. First package to Martin by 10-Oct-2026; review in the week of 13-Oct, then refine presentation/abstract and final thesis narrative. | E10: Submission-ready thesis + package + response memo + agreed seminar table/deck + deadline checklist | F10: All prior phases | G10: Every comment has a change or reasoned non-change; deadlines and formal resolutions are confirmed.

Sheet Estimation Plan
A1: Paper/Seminar Estimation Plan - updated 9-Oct-2026 (Data Freeze passed; WP-07 core FE-DK active)
A2: Source: Martin Grandes guidance through the 2-Oct-2026 Zoom meeting plus completed measurement/data audits and the reproducible panel freeze through 9-Oct. The Econometric Panel Data Freeze Gate has PASSED. Frozen estimation input: panel_main_and_robustness_rebuilt.xlsx, 4,648 rows x 19 columns, 103 bonds, 48 issuers, generated by scripts/build_econometrics_panel.py and committed under 23435a4. SGS 13762 uses uniform L2 timing. Sovereign Risk (BRL) keeps the closed WP-02 nominal LTN/NTN-F-vs-DI definition and a documented same-date panel mapping: 3,918 populated rows from 2016 onward, 730 intentional pre-2016 missing rows, no backward time extrapolation. Full reconciliation passed against the legacy panel. CURRENT: execute WP-07 — one bond-FE table with Driscoll-Kraay covariance/standard errors — then WP-08 targeted robustness. Ratings remain descriptive only.
A4: Core four-model template (attachment transcribed exactly; implementation notes flag unresolved points)
A5: Variable / statistic | B5: Model 1 | C5: Model 2 | D5: Model 3 | E5: Model 4 | F5: Decision | G5: Implementation note
A6: Estimator | B6: FE-DK | C6: FE-DK | D6: FE-DK | E6: FE-DK | F6: Required | G6: Bond fixed effects determine the coefficient estimator; Driscoll-Kraay is the covariance/standard-error treatment used for main inference. 2-Oct guidance: document this distinction explicitly, including heteroskedasticity, serial correlation and cross-sectional dependence handling; PCSE/plain-FE alternatives are appendix/internal diagnostics only if retained.
A7: VIX | B7: x | C7: x | D7: x | E7: x | F7: Core | G7: Pre-freeze MR-09/WP-06 audit passed: VIX Index source/ticker, 187/187 monthly history, month-end convention, 4,229/4,229 panel mapping, raw index-point scaling and economic label/H1 wording are validated. Keep VIX in all four core columns. Raw/partial correlations and final sign/H1 interpretation wait for post-freeze DK results.
A8: FED3M Forward (nominal) | B8: x | C8: x | D8: x | E8: x | F8: Core | G8: PRE-FREEZE AUDIT PASSED. Baseline fed_3m_forward is Bloomberg USSOC Curncy / PX_LAST, the 3M USD OIS fixed rate. Native daily history and last-available month-end convention validated; 164/164 distinct panel months match exactly (0 mismatches; max abs diff 0.0). Baseline uses Bloomberg percentage-point values directly with no rescaling/log/standardization; D.fed_3m_forward exists only in the separate macro-differences robustness. Keep the thesis-facing label “Fed 3M Forward” for readability, but define it technically as the 3M USD OIS and state explicitly that it is forward-looking in economic content, not a forward-starting 3Mx3M rate. Keep the nominal market rate; do not reintroduce the old real construction.
A9: FED3M Forward Real (old construction) | B9: - | C9: - | D9: - | E9: - | F9: Exclude | G9: Do not use: inflation adjustment was not horizon-consistent with the 3-month forward rate.
A10: USD/BRL NER | B10: x | F10: Attachment | G10: PRE-FREEZE AUDIT PASSED FOR CURRENT NOMINAL NER. Source workbook identifies USDBRL Curncy (BRL per USD); 187 uninterrupted monthly source observations from Jan-2010 to Jul-2025; all timestamps follow the last-weekday month-end convention; panel usd_brl maps exactly across 4,229 rows / 164 months with 0 blanks, 0 within-month conflicts, 0 missing source months and 0 mismatches. Baseline uses the level directly with no log/rescaling/standardization; D.usd_brl is macro-differences robustness only. Label as nominal USD/BRL (BRL per USD); an increase denotes BRL depreciation. Original Bloomberg formula/raw layer is not retained in the values-only workbook.
A11: USD/BRL RER | B11: x | C11: x | E11: x | F11: Confirm | G11: RER remains a separate construction from the audited nominal NER. If Martin's final specification replaces NER with RER, complete a separate six-step RER audit before the panel is frozen; do not infer RER validity from the nominal USD/BRL audit.
A12: GDP growth (YoY) | B12: x | C12: x | E12: x | F12: Attachment | G12: PRE-FREEZE AUDIT PASSED. Source workbook identifies Real GDP (yoy %) / BZGDYOY% Index; duplicate columns 7 and 17 are identical. Raw workbook stores quarterly values on quarter-end rows with zero placeholders between quarter ends; panel carries the latest quarterly value forward monthly. All 164 distinct panel months match the reconstructed source series exactly (0 mismatches; 0 within-month conflicts). Baseline uses native percentage-point units with no rescaling/log/standardization, and gdp_yoy remains in levels in the macro-differences robustness. Economic label: Brazil real GDP growth, year-on-year (%). Quarter-end reference-period alignment is validated; real-time release-vintage timing was not separately audited.
A13: Public debt / GDP (BCB SGS 13762; replaces legacy debt_gdp/EHBBBR) | B13: x | C13: x | E13: x | F13: Frozen - replace legacy EHBBBR with BCB SGS 13762 using uniform L2 in reproducible rebuild | G13: SPECIFICATION DECISION CLOSED 5-Oct-2026. The existing panel debt_gdp is Bloomberg EHBBBR Index / Brazil Budget Balance (% GDP), SA, quarterly: its source/mapping/scaling audit passed, but it is a fiscal-flow variable and does not match the thesis H8 / requested Public debt-GDP stock construct. Baseline replacement: official Banco Central do Brasil SGS 13762, “Dívida bruta do governo geral (% PIB) - Metodologia utilizada a partir de 2008”, monthly, native percentage points of GDP, BCB-DSTAT. Archived raw file: datos_y_modelos/db/brazil_macroeconomic_data/public_debt_gdp/sgs_13762_public_debt_gdp.csv; official source page: https://www3.bcb.gov.br/sgspub/consultarvalores/consultarValoresSeries.do?method=visualizarValores. Snapshot covers 2010-01 through 2026-08 and therefore all 164 panel months through 2025-06. Uniform L2 reference-month mapping selected as a conservative/reproducible timing convention: 0 missing across 164 months; L1-L2 corr 0.997613; mean abs difference 0.5295 pp; max 2.92 pp. Do not claim this reproduces the exact historical BCB publication-vintage calendar. Bloomberg AI cross-check reported WGPDCBRA Index as the closest Bloomberg alternative but not an exact monthly SGS feed; it is not selected. Final field name should be public_debt_gdp. No panel modification yet; implement only in the single controlled reproducible rebuild. 7-Oct-2026: FISCAL CONTROL — FROZEN. No conceptual reopening; implementation is pending only in the reproducible panel builder.
A14: Sovereign Risk (BRL) | B14: x | C14: x | D14: x | F14: Core - upstream validated; legacy panel field failed reconciliation; replacement required pre-freeze | G14: WP-02 source/formula audit remains the validated Sovereign Risk (BRL) construction: sovereign_spread_brl = nominal LTN/NTN-F government YTM versus same-date DI reference yield at exact BUS/252 tenor, geometric bps; 252 LTN + 330 NTN-F = 582/582 reproduced. 4-Oct DATA-FREEZE RECONCILIATION CLOSED: current panel/Stata synthetic_cds_brl is not equivalent. Legacy surface lineage pools nominal LTN/NTN-F with 1,107 NTN-B real-curve spreads, panel injection uses only the latest curve (archived 2025-08-04, after sample end), and current values are essentially a deterministic function of residual maturity. Reproduction error is about 0.000104 bp max; 6-month is parsed as 6.0 years and tau2 is inactive in the simplified fit. Units remain bps, but date/transformation mapping is invalid. Final rebuild must replace the legacy field with validated sovereign_spread_brl; do not interpret legacy coefficients as the corrected sovereign result. Corporate IPCA-real benchmark remains distinct.
A15: Cash flow / assets | B15: x | C15: x | D15: x | E15: x | F15: Retain - audited; PIT timing rule CLOSED; rebuild pending | G15: PRE-FREEZE SIX-STEP AUDIT PASSED FOR LINEAGE/DATA AND TIMING DECISION CLOSED. Exact source fields are issuer-level Bloomberg Fundamentals CF_CASH_FROM_OPER and BS_TOT_ASSET; bond-to-issuer mapping uses ULT_PARENT_TICKER_EXCHANGE. The legacy panel assigns each quarter's eventual current-restated ratio to all three months of the same calendar quarter, which is not observation-date defensible. Final rule for the controlled rebuild: query Bloomberg historical point-in-time quarterly fundamentals as of each exact obs_date and select the most recent fiscal quarter jointly complete across CF_CASH_FROM_OPER, BS_TOT_ASSET, SHORT_AND_LONG_TERM_DEBT and EBITDA; if the newest reported quarter is incomplete, step back one quarter. Compute cf_cash_oper_to_tot_asset from the selected same-period PIT CFO/assets components and retain the validated x1000 scaling, i.e. per mille (‰). Exact-panel test across the shared accounting rule resolves 1,959/1,959 issuer-date pairs; 14 pairs require one-quarter fallback and 0 are unresolved. At bond level the fallback affects 29/4,229 rows across 12 bonds; no sample loss. Do not edit the legacy panel ad hoc; implement during the one reproducible controlled rebuild and archive/reuse the PIT extraction/provenance.
A16: Relative issue size (AMT_ISSUED / BS_TOT_ASSET, ‰) | B16: x | C16: x | D16: x | E16: x | F16: Retain - audited | G16: Closed WP-03 and reaffirmed 2-Oct. AMT_ISSUED is fixed but quarterly BS_TOT_ASSET varies, so the ratio is identified in bond FE. Interpret as relative issue size / primary issuance-liquidity. Secondary turnover/amount-outstanding would be conceptually cleaner for market liquidity but is likely sparse/zero-heavy in this market. Q-1 denominator remains timing robustness.
A17: Financial leverage (short- and long-term debt / EBITDA, x) | B17: x | C17: x | D17: x | E17: x | F17: Retain - audited; PIT timing rule CLOSED; rebuild pending | G17: SIX-STEP PRE-FREEZE AUDIT PASSED FOR LINEAGE/MAPPING/SCALING AND TIMING DECISION CLOSED. Historical source fields are issuer-level Bloomberg Fundamentals SHORT_AND_LONG_TERM_DEBT and EBITDA; mapping uses ULT_PARENT_TICKER_EXCHANGE. The legacy panel assigns each quarter's eventual current-restated debt/EBITDA ratio to all three months of that same calendar quarter, creating look-ahead. Final rule for the controlled rebuild is identical to the cash-flow/assets rule: at each exact obs_date use Bloomberg historical point-in-time quarterly fundamentals and select the most recent fiscal quarter jointly complete across CFO, assets, debt and EBITDA; if the newest reported quarter is incomplete, use the immediately preceding quarter. Compute tot_debt_to_ebitda from debt and EBITDA in that same selected period/vintage and retain the validated raw leverage multiple (x), with no x100, log, standardization or winsorization. Exact-panel shared-rule validation: 1,959/1,959 issuer-date pairs resolved; 14 fallback pairs; 0 unresolved; 29/4,229 bond rows affected by fallback across 12 bonds; zero sample loss. Implement only in the one reproducible controlled rebuild and preserve PIT extraction/provenance.
A18: Residual bond maturity | B18: x | C18: x | D18: x | E18: x | F18: Retain - audited; BUS/252 helper consistency CLOSED | G18: PRE-FREEZE SIX-STEP AUDIT PASSED. Source field is contractual MATURITY in universo_brazil_deb_des.xlsx / db_values_only. All 103 panel bonds map uniquely with valid maturity dates. The legacy econometric panel field days_to_maturity is residual maturity in BUS/252 years and its previously audited historical construction remains documented separately; do not alter those stored values ad hoc. Separate reusable-helper audit CLOSED 6-Oct: compute_spreads(), NTN-B YTM pricing, Nelson-Siegel-Svensson cash-flow timing/weighting and WLA boundary logic all use the same DayCounts('bus/252', calendar='cdr_anbima') [start,end) convention. WLA production dates/maturities and the 21 corrected trading-date blocks were validated. Before the calendar patch, 2,214/3,144 WLA Term rows matched and 930 differed by integer business days; adding 20-Nov as a national holiday from 2024 onward to cdr_anbima produces 3,144/3,144 exact matches with max gap 0. Targeted day-count/spread/interpolation tests pass 5/5; commit 2447da2. No endpoint change to the shared helper and no edits to ntnb_real_curve.py, spread_calculator.py or the WLA workbook are required.
A19: Within R-squared | B19: report | C19: report | D19: report | E19: report | F19: Required | G19: Explicitly requested in the attachment.
A20: rho | B20: report | C20: report | D20: report | E20: report | F20: Required | G20: Explicitly requested in the attachment.
A21: Diagnostics / DK metadata | B21: below | C21: below | D21: below | E21: below | F21: Required | G21: Show diagnostic tests, DK lag and panel dimensions with the table.
A24: Optional SELIC 3M Forward robustness checks (secondary to the core four models)
A25: Element | B25: Model 5 | C25: Model 6 | D25: Status | E25: Required exclusion | F25: Open point | G25: Implementation note
A26: SELIC 3M Forward | B26: include | C26: include | D26: Prepared; eligible after core frozen-panel rerun | E26: - | F26: Proxy sourced/documented: YCSW0089 Index 3M (Brazil 3M DI). Data Freeze has passed; run Models 5-6 only after the core WP-07 DK table is validated. | G26: Referee/director robustness, not baseline. Use validated YCSW0089 Index 3M after the core frozen-panel rerun; compare nominal FED3M retained versus omitted under the specified FX/sovereign exclusions.
A27: FED3M Forward (nominal) | B27: retain | C27: omit | D27: Specified | E27: Model 6 omits it | F27: - | G27: Second SELIC variant removes FED3M as well.
A28: FX (NER/RER) | B28: omit | C28: omit | D28: Specified | E28: Both models omit FX | F28: - | G28: Required by Martin.
A29: Sovereign Risk (BRL) | B29: omit | C29: omit | D29: Specified | E29: Both models omit sovereign spread | F29: - | G29: Required by Martin.
A30: Other macro and firm/bond controls | B30: base set | C30: base set | D30: Confirm | E30: - | F30: Exact retained block not fully stated | G30: Use the selected base column only after confirmation.
A32: Implementation controls and unresolved source points
A33: # | B33: Control / ambiguity | C33: Status | D33: Required decision or evidence | E33: Owner | F33: Target | G33: Source
A34: 1 | B34: Use nominal FED3M Forward; exclude old real series | C34: Resolved | D34: Implement nominal series in all four core models | E34: Thiago | F34: Before estimation | G34: Martin 25-Sep
A35: 2 | B35: One table only; no separate plain-FE or PCSE columns | C35: Resolved | D35: Use FE-DK columns and place diagnostics below | E35: Thiago | F35: 10-Oct-2026 package | G35: Main output remains DK-only. 2-Oct meeting reaffirms no main-table plain-FE/PCSE horse race; alternatives may appear only as qualified appendix/internal diagnostics.
A36: 3 | B36: PCSE rationale | C36: Resolved | D36: Document the exact FE/DK/PCSE distinction: FE defines coefficient estimation; DK/PCSE address covariance/inference. Verify the heteroskedasticity, serial-correlation and cross-sectional-dependence treatment and explain why the highly unbalanced panel / limited common overlap supports DK as the preferred main inference. | E36: Thiago | F36: Response memo | G36: Martin 25-Sep
A37: 4 | B37: Model 1 contains both NER and RER in attachment | C37: Confirm | D37: Ask whether Model 1 should contain NER, RER or both | E37: Thiago + Martin | F37: Before final code | G37: Attached table
A38: 5 | B38: Stacking text versus controls in all attached columns | C38: Confirm | D38: Map external -> domestic/sovereign -> firm/bond sequence to final columns | E38: Thiago + Martin | F38: Before final code | G38: Martin + table
A39: 6 | B39: No separate inflation term in paper exercise | C39: Clarify wording | D39: Verify consistency with IPCA-linked yield units and thesis notation | E39: Thiago + Martin | F39: Before writing | G39: Martin 25-Sep
A40: 7 | B40: NER and RER reportedly similar | C40: Verify | D40: Confirm on regenerated corrected-spread estimates | E40: Thiago | F40: With core table | G40: Martin 25-Sep
A41: 8 | B41: Core table delivery | C41: Target | D41: Send one consolidated table with diagnostics and statistics | E41: Thiago | F41: 10-Oct-2026 | G41: Old 30-Sep target superseded. Send corrected core DK regressions, agreed robustness results and an updated presentation to Martin by 10-Oct; joint review week of 13-Oct.
A42: 9 | B42: Sovereign Risk (BRL) definition / old synthetic-CDS label | C42: Resolved/frozen under WP-06 | D42: Legacy synthetic_cds_brl remains invalid and is replaced by sovereign_spread_brl. WP-02 source/formula stays fixed: domestic_sovereign_curve_brazil.xlsx metadata + govt_ya_ande.v3.xlsx ANDE normalized YAS; 252 LTN + 330 NTN-F = 582 government observations against same-date exact-tenor DI. WP-06 now supplies the panel mapping: same-date mapping only; flat-forward interpolation between tenor nodes; endpoint-flat mapping outside the observed same-date tenor range; single-node flat mapping where only one nominal bond exists. No backward time extrapolation into 2010-2015. Final rebuilt panel: sovereign present 3,918, missing 730; all missing rows are pre-2016. | E42: Thiago | F42: Closed before estimation | G42: Martin audio 25-Sep
A43: 10 | B43: USD CDS 5Y in the economic model | C43: Deferred final-panel integrity check | D43: Martin confirms USD CDS 5Y was never part of the economic model. Keep a final code/specification search immediately before estimation to confirm it is absent everywhere; do not add it as a main or secondary control. This is a final-panel integrity check and no longer an open WP-02 closure condition. | E43: Thiago | F43: Before final estimation | G43: Martin audio 25 & 27-Sep
A44: 11 | B44: Common-reference two-spread specification | C44: Specification intent resolved; reconciliation pending | D44: Document the preferred two-spread transmission specification, but first reconcile the phrase 'same local reference curve' with the implemented data: the corporate dependent variable is IPCA-linked and benchmarked to the real IPCA reference curve, while the validated nominal sovereign series uses LTN/NTN-F versus the DI curve. Do not claim an identical benchmark unless the indexation-consistent mapping is explicitly demonstrated. Then support the chosen formulation with literature. | E44: Thiago | F44: Before final estimation/write-up | G44: Martin audio 27-Sep
A45: 12 | B45: SELIC 3M Forward role | C45: Resolved - referee only | D45: Run only as an optional referee diagnostic under the specified exclusions; do not treat it as baseline; decide whether to show/publish only if informative. | E45: Thiago | F45: After data freeze and core table / if time permits | G45: Martin audio 27-Sep
... A51: 18 | B51: Updated delivery sequence | C51: Target | D51: Data Freeze PASSED -> CURRENT core DK audit/rerun -> agreed robustness/sensitivity -> send regressions + revised deck to Martin. | E51: Thiago | F51: 10-Oct-2026; review week of 13-Oct | G51: Martin Zoom 2-Oct

Sheet v4 Change Log
A1: v4 Change Log
A2: Exact changes merged from Martin Grandes' 24-Sep-2026 messages after he read Daniel Milia's report.
A3: Change ID | B3: Date | C3: Topic | D3: Sheets / rows affected | E3: What changed
A4: v4-01 | B4: 24-Sep-2026 | C4: Daniel overall priority | D4: Director Guidance; README; Dashboard | E4: Recorded Martin's assessment that Daniel is less substantive than Ailin and Maximo and should be handled selectively after the core empirical work.
A5: v4-02 | B5: 24-Sep-2026 | C5: Hypothesis-result linkage | D5: MR-09, MR-19, MR-30, MR-31, MR-32; WP-06, WP-13, WP-14 | E5: Added an explicit requirement to link each hypothesis to final results and classify evidence as robust, partial/sensitive, null or unresolved.
A6: v4-03 | B6: 24-Sep-2026 | C6: Counterintuitive signs | D6: MR-01, MR-09, MR-19, MR-26, MR-30 | E6: Made clearer sign explanations a required downstream narrative task.
A7: v4-04 | B7: 24-Sep-2026 | C7: Heteroskedasticity and diagnostics | D7: MR-16; WP-07 | E7: Recorded that the problem was already treated in substance; the revision must make diagnostics and the correction visible.
A8: v4-05 | B8: 24-Sep-2026 | C8: Minor bibliography | D8: MR-11, MR-21, MR-34; WP-11 | E8: Reclassified Daniel bibliography requests as bounded, targeted corrections rather than a literature overhaul.
A9: v4-06 | B9: 24-Sep-2026 | C9: SELIC disposition | D9: MR-04, MR-26; MG-10; WP-04 | E9: Changed SELIC from a possible robustness variable to an explicit separate-regressor non-inclusion: it is part of the short end and potentially redundant.
A10: v4-07 | B10: 24-Sep-2026 | C10: Sovereign ceiling | D10: MR-01, MR-02; MG-11; WP-02 | E10: Added Martin's sovereign-ceiling framing and its link to the corporate excess/shortfall over the sovereign.
A11: v4-08 | B11: 24-Sep-2026 | C11: Matched YTM alternative | D11: MR-01; WP-02; Action Sequence | E11: Added the alternative corporate-YTM-on-sovereign-YTM interpretation with same tenor, currency and approximately the same coupon, plus literature justification.
A12: v4-09 | B12: 24-Sep-2026 | C12: DK-only main estimator | D12: MR-16, MR-17, MR-23; MG-12; WP-07 | E12: Specified Driscoll-Kraay as the only main estimator and added a short explanation for discarding PCSE.
A13: v4-10 | B13: 24-Sep-2026 | C13: Seminar specifications | D13: MR-18; MG-12; WP-08, WP-16 | E13: Added real exchange rate and with/without macro controls correlated with local sovereign risk for Bordeaux/Geneva.
A14: v4-11 | B14: 24-Sep-2026 | C14: Priority sequence | D14: Dashboard; Action Sequence | E14: Kept WP-01 current, then elevated Maximo-driven spread/sovereign construction before Daniel-only exposition.
A15: v4-12 | B15: 24-Sep-2026 | C15: Source-of-truth update | D15: All tabs | E15: Merged the latest WhatsApp guidance without adding duplicate master issues or work packages.

Sheet v5 Change Log
A1: v5 Change Log
A2: Exact changes merged from Martin Grandes' 25-Sep-2026 messages and attached estimation table.
A3: Change ID | B3: Date | C3: Topic | D3: Sheets / rows affected | E3: What changed
A4: v5-01 | B4: 25-Sep-2026 | C4: PCSE rationale confirmed | D4: MR-16, MR-17; MG-13; WP-07 | E4: Recorded Martin's acceptance of the imbalance/common-overlap rationale and retained PCSE only for internal audit, not the main output.
A5: v5-02 | B5: 25-Sep-2026 | C5: Single FE-DK table | D5: MR-16, MR-18, MR-24; MG-14; WP-07/08/12 | E5: Specified one consolidated FE-Driscoll-Kraay table and removed separate plain-FE and PCSE columns.
A6: v5-03 | B6: 25-Sep-2026 | C6: FED3M variable correction | D6: MR-18; MG-15; WP-08; Estimation Plan | E6: Replaced the old FED3M Forward Real construction with nominal FED3M Forward for the requested exercise.
A7: v5-04 | B7: 25-Sep-2026 | C7: SELIC baseline and optional checks | D7: MR-04, MR-26; MG-16; WP-04/08 | E7: Preserved SELIC exclusion from the baseline but added two explicitly scoped optional SELIC 3M Forward robustness columns.
A8: v5-05 | B8: 25-Sep-2026 | C8: Exact four-model grid | D8: MR-18, MR-24; MG-17/19; Estimation Plan | E8: Transcribed the attached four-column variable grid and required Within R-squared/rho outputs.
A9: v5-06 | B9: 25-Sep-2026 | C9: FX and inflation treatment | D9: MR-01, MR-18, MR-26; MG-18 | E9: Recorded the requested RER robustness, NER/RER similarity to verify, and the instruction not to add a separate inflation term.
A10: v5-07 | B10: 25-Sep-2026 | C10: Source ambiguities preserved | D10: MR-18; WP-08; Estimation Plan | E10: Flagged Model 1 NER+RER and stacking-versus-all-controls inconsistencies for confirmation rather than silently changing the source.
A11: v5-08 | B11: 25-Sep-2026 | C11: Near-term target | D11: Process & Deadlines; Dashboard; WP-08/16 | E11: Added the requested Wednesday target of 30-Sep-2026 for the consolidated result table.
A12: v5-09 | B12: 25-Sep-2026 | C12: New Estimation Plan sheet | D12: README; Estimation Plan | E12: Added an implementation-ready grid with core models, optional SELIC checks, controls, ambiguities and source traceability.
A13: v5-10 | B13: 25-Sep-2026 | C13: Source-of-truth update | D13: All relevant tabs | E13: Merged the latest director instructions without creating duplicate jury issues or work packages.

Sheet v6 Change Log
A1: v6 Change Log
A2: Changes merged from Martin Grandes' 25-Sep-2026 audio clarifying the sovereign-risk construction and the transition from WP-01 to WP-02.
A3: Change ID | B3: Date | C3: Topic | D3: Sheets / rows affected | E3: What changed
A4: v6-01 | B4: 25-Sep-2026 | C4: Definitive Sovereign Risk (BRL) definition | D4: MR-01, MR-02; MG-03, MG-11, MG-20; WP-02; Estimation Plan | E4: Resolved the conceptual ambiguity: the sovereign regressor is government-bond YTM minus the matched local risk-free/reference curve yield, not a CDS.
A5: v6-02 | B5: 25-Sep-2026 | C5: Synthetic CDS terminology removed from design | D5: MR-02; WP-02; Overlap Map; Estimation Plan | E5: Reclassified "synthetic CDS BRL" as a misnomer and required consistent renaming to Sovereign Risk (BRL) / local-currency sovereign spread.
A6: v6-03 | B6: 25-Sep-2026 | C6: Dependent-variable interpretation corrected | D6: MR-01; MG-11; WP-02 | E6: Superseded the v5 ambiguity: Corporate YTM versus matched Sovereign YTM is an equivalent sovereign-ceiling framing/check, not a replacement for the corporate-spread dependent variable.
A7: v6-04 | B7: 25-Sep-2026 | C7: USD CDS 5Y main-model treatment | D7: MR-01, MR-02; MG-03, MG-20; Estimation Plan | E7: Recorded Martin's stronger instruction that the external USD sovereign CDS should not enter the main model.
A8: v6-05 | B8: 25-Sep-2026 | C8: WP-01 to WP-02 workflow handoff | D8: README; Dashboard; Revision Tracker; Action Sequence | E8: Marked the corporate-spread measurement audit as closed and activated the sovereign-risk code/formula audit as the current work package.
A9: v6-06 | B9: 25-Sep-2026 | C9: Implementation gate before re-estimation | D9: WP-02; Estimation Plan; Action Sequence | E9: Added an explicit pre-estimation gate: verify government-minus-reference formula, maturity/tenor matching and currency/indexation consistency in code before running the DK table.
A10: v6-07 | B10: 25-Sep-2026 | C10: Director traceability | D10: Director Guidance | E10: Added MG-20 with the definitive construction and strengthened earlier sovereign-risk guidance without erasing the historical record.
A11: v6-08 | B11: 25-Sep-2026 | C11: Source-of-truth reconciliation | D11: README; Master Matrix; Overlap Map; v6 Change Log | E11: Merged the latest audio into existing issues rather than creating duplicate jury items; v5 remains preserved as the prior snapshot.

Sheet v7 Change Log
A1: v7 Change Log
A2: Changes merged from Martin Grandes' 27-Sep-2026 audio clarifying the preferred two-spread specification, USD CDS status and SELIC referee check.
A3: Change ID | B3: Date | C3: Topic | D3: Sheets / rows affected | E3: What changed
A4: v7-01 | B4: 27-Sep-2026 | C4: USD CDS 5Y status | D4: MR-01, MR-02; MG-03, MG-20, MG-21; WP-02; Estimation Plan | E4: Corrected the record: USD CDS 5Y was never part of the economic model. The workbook now requires verification of absence rather than treating it as a possible secondary/main control.
A5: v7-02 | B5: 27-Sep-2026 | C5: Preferred common-reference two-spread model | D5: MR-01; MG-11, MG-20, MG-21; WP-02; Overlap Map; Action Sequence | E5: Specified Corporate Spread = corporate YTM - local reference yield and Sovereign Risk = government YTM - the same matched reference yield, kept as separate variables so the model estimates the response of corporate spread to sovereign risk.
A6: v7-03 | B6: 27-Sep-2026 | C6: Direct corporate-sovereign differential reclassified | D6: MR-01; MG-11; WP-02; Estimation Plan | E6: Replaced the earlier shorthand that the matched corporate-sovereign formulation was econometrically equivalent. It is a related alternative, but not the preferred specification.
A7: v7-04 | B7: 27-Sep-2026 | C7: Literature justification added | D7: MR-01, MR-02; WP-02; Action Sequence; Estimation Plan | E7: Added an explicit requirement to justify the common-reference two-spread transmission specification with literature before final re-estimation/write-up.
A8: v7-05 | B8: 27-Sep-2026 | C8: SELIC embedded in local curve | D8: MR-02, MR-04, MR-26; MG-10, MG-16, MG-21; WP-04 | E8: Strengthened the explanation that SELIC anchors the short end of the local reference curve and its influence is already embedded in the curve used by the model.
A9: v7-06 | B9: 27-Sep-2026 | C9: SELIC 3M Forward is referee-only | D9: MR-04, MR-18; MG-16, MG-21; WP-04, WP-08; Estimation Plan | E9: Narrowed the SELIC 3M Forward exercise to an optional referee diagnostic. It is not a baseline extension and should be shown/published only if informative.
A10: v7-07 | B10: 27-Sep-2026 | C10: Director traceability | D10: Director Guidance | E10: Added MG-21 and updated earlier guidance rows to preserve the latest director interpretation without creating new juror issues or work packages.
A11: v7-08 | B11: 27-Sep-2026 | C11: Source-of-truth reconciliation | D11: README; Dashboard; Revision Tracker; Master Matrix; Overlap Map; Action Sequence; Process & Deadlines | E11: Updated version/date/source notes and kept WP-02 as the active package; v6 remains preserved as the prior snapshot.

Sheet v8 Change Log
A1: v8 Change Log
A2: Changes from the 29-Sep-2026 nominal sovereign-risk implementation audit, exact-node interpolation fix, and WP-02 status reconciliation.
A3: Change ID | B3: Date | C3: Topic | D3: Sheets / rows affected | E3: What changed
A4: v8-01 | B4: 29-Sep-2026 | C4: Nominal sovereign implementation validated | D4: WP-02; MR-01, MR-02; Estimation Plan; Action Sequence | E4: Validated 252 LTN + 330 NTN-F observations (582 total): same-date DI benchmark at exact BUS/252 residual tenor, 0 missing benchmarks, 582/582 reproduced to numerical precision, and geometric spread arithmetic independently confirmed.
A5: v8-02 | B5: 29-Sep-2026 | C5: DI exact-node interpolation hardened | D5: Interpolation helper; WP-02 evidence | E5: Added an exact/near-node guard after identifying floating-point behavior when a requested tenor coincides with a raw DI market node. Regenerated outputs and re-audited the full sample.
A6: v8-03 | B6: 29-Sep-2026 | C6: WP-02 status split | D6: README; Dashboard; Revision Tracker; Master Matrix | E6: Kept WP-02 In progress while explicitly closing the implementation/code component. Remaining closure items are thesis terminology, equations/literature, USD CDS code-absence verification, and reference-curve/indexation reconciliation.
A7: v8-04 | B7: 29-Sep-2026 | C7: Common-reference wording flagged | D7: MR-01; WP-02; Overlap Map; Estimation Plan | E7: Flagged that the implemented corporate dependent variable is IPCA-linked and uses the real IPCA benchmark, while the validated nominal sovereign series uses LTN/NTN-F versus the DI curve. The thesis must reconcile this before claiming both spreads use an identical local reference curve.
A8: v8-05 | B8: 29-Sep-2026 | C8: Validation and Git milestone | D8: WP-02 evidence | E8: Full pytest suite passed 5/5 after the interpolation fix. Commit b551414 (Refactor nominal DI interpolation and sovereign spreads) was pushed to branch jury-revision-recalculate-corporate-spread.

Sheet v9 Change Log
A1: v9 Change Log
A2: Changes from the 29-Sep-2026 WP-02 closure, thesis terminology/indexation cleanup, and workflow handoff to WP-03.
A3: Change ID | B3: Date | C3: Topic | D3: Sheets / rows affected | E3: What changed
A4: v9-01 | B4: 29-Sep-2026 | C4: WP-02 closed | D4: README; Dashboard; Revision Tracker; Master Matrix | E4: Closed WP-02 after validated 582/582 nominal sovereign observations, formula/unit tests, exact-node hardening, thesis terminology cleanup, and documentation of the nominal DI sovereign versus IPCA-real corporate benchmark distinction.
A5: v9-02 | B5: 29-Sep-2026 | C5: Sovereign variable terminology finalized | D5: WP-02; MR-01, MR-02; thesis edits | E5: Adopted sovereign_spread_brl / sovereign risk in local currency. Removed synthetic-CDS language from methodology, appendix, results labels, diagrams and Mermaid source; clarified that the measure is a local BRL sovereign spread, not a CDS.
A6: v9-03 | B6: 29-Sep-2026 | C6: Reference-curve/indexation wording reconciled | D6: MR-01; Overlap Map; Action Sequence | E6: Replaced the inaccurate claim that corporate and sovereign spreads use an identical reference curve. Corporate spread uses an IPCA-real matched benchmark; sovereign_spread_brl uses nominal LTN/NTN-F versus the DI reference curve. Each is matched to its own indexation/tenor.
A7: v9-04 | B7: 29-Sep-2026 | C7: WP-03 activated | D7: Revision Tracker; Dashboard; Action Sequence | E7: Set WP-03 to In progress. Next gate is to audit amount_issued_to_asset construction and within-bond variation before deciding whether it is identified in bond fixed effects.
A8: v9-05 | B8: 29-Sep-2026 | C8: Regression rerun deferred | D8: Estimation Plan; Action Sequence | E8: Confirmed sequencing: finish all explanatory-variable audits first, freeze the final panel, then rerun FE/Driscoll-Kraay once. USD CDS 5Y absence is retained only as a final pre-estimation integrity check and does not keep WP-02 open.

Sheet v10 Change Log
A1: v10 Change Log
A2: Changes from the 30-Sep-2026 WP-03 issue-size audit closure, thesis consistency update, and workflow handoff to WP-04.
A3: Change ID | B3: Date | C3: Topic | D3: Sheets / rows affected | E3: What changed
A4: v10-01 | B4: 30-Sep-2026 | C4: WP-03 closed | D4: README; Dashboard; Revision Tracker; Master Matrix; Action Sequence | E4: Closed the issue-size identification package after tracing AMT_ISSUED and BS_TOT_ASSET through the final panel, reconstructing 4,229/4,229 observations, and confirming within-bond variation for 98/103 bonds (95.15%).
A5: v10-02 | B5: 30-Sep-2026 | C5: Relative issue-size interpretation and units finalized | D5: MR-14; WP-03; Estimation Plan; thesis edits | E5: Retained amount_issued_to_bs_tot_asset as relative issue size rather than time-invariant amount issued; documented that within variation comes from quarterly issuer assets; standardized the scale as per-mille (‰) and the coefficient interpretation as relative size versus issuer scale.
A6: v10-03 | B6: 30-Sep-2026 | C6: Timing robustness documented | D6: WP-03; MR-14; Estimation Plan | E6: Constructed a one-quarter-lagged BS_TOT_ASSET denominator check: 4,223/4,229 observations available, correlation 0.9918 with the original ratio, and the same 98/103 bonds with within variation. Kept it as robustness rather than replacing the main regressor.
A7: v10-04 | B7: 30-Sep-2026 | C7: Thesis-side WP-03 consistency confirmed | D7: MR-14 thesis locations; Tables 3/7; Figure 3; Annex 8.6.2 | E7: Confirmed the latest thesis aligns H6, methodology, FE identification, results, conclusions, tables, Figure 3 and the annex with the audited construction and cautious liquidity-proxy interpretation.
A8: v10-05 | B8: 30-Sep-2026 | C8: WP-04 activated | D8: README; Dashboard; Revision Tracker; Master Matrix; Action Sequence; Estimation Plan | E8: Set WP-04/MR-04 to In progress. Current task is the baseline SELIC non-inclusion rationale plus the bounded referee-only SELIC 3M Forward diagnostic(s). Final regression rerun remains deferred until the remaining explanatory-variable audits are complete.

Sheet v11 Change Log
A1: TFM Master Revision Matrix - v11 Change Log
A2: Changes introduced on 1-Oct-2026 after inserting the WP-04 SELIC baseline non-inclusion rationale into thesis Section 4.5.3. WP-04 is not yet closed because the referee-only SELIC 3M Forward diagnostics remain pending.
A4: ID | B4: Date | C4: Change | D4: Affected items | E4: Detail
A5: v11-01 | B5: 1-Oct-2026 | C5: SELIC baseline rationale inserted | D5: WP-04; MR-04; thesis Sec. 4.5.3 | E5: Added an explicit rationale immediately after Fed 3M Forward: SELIC is excluded from the baseline because domestic monetary conditions are partly embedded in the short end of the local reference curve and may overlap with the external-rate/FX block.
A6: v11-02 | B6: 1-Oct-2026 | C6: WP-04 remains open | D6: Dashboard; Revision Tracker; Action Sequence | E6: Did not close WP-04. Remaining gate is to identify/audit the SELIC 3M Forward series and run the two scoped referee-only diagnostics before moving to WP-05.
A7: v11-03 | B7: 1-Oct-2026 | C7: SELIC diagnostic scope preserved | D7: Estimation Plan | E7: Model 5: include SELIC 3M Forward and retain nominal FED3M; Model 6: include SELIC 3M Forward and omit FED3M. Both omit FX and Sovereign Risk (BRL). Review correlations/VIF and incremental information before deciding whether to report.

Sheet v12 Change Log
A1: TFM Master Revision Matrix - v12 Change Log
A2: Changes introduced on 1-Oct-2026 after identifying, validating, downloading and documenting the Brazil 3M DI referee-only robustness proxy for WP-04. WP-04 remains open pending panel merge, diagnostics and Models 5-6.
A4: ID | B4: Date | C4: Change | D4: Affected items | E4: Detail
A5: v12-01 | B5: 1-Oct-2026 | C5: Brazil 3M DI proxy identified | D5: WP-04; MR-04; Estimation Plan | E5: Operationalized the referee-only domestic short-rate proxy as the 3M point of Bloomberg BM&F Pre x DI curve YCSW0089 Index. Explicitly distinguished it from a literal 3Mx6M forward-starting SELIC rate.
A6: v12-02 | B6: 1-Oct-2026 | C6: Historical series downloaded | D6: WP-04; data acquisition | E6: Validated YCSW0089 Index 3M in BQNT and downloaded the complete monthly Dec-2010 to Dec-2025 series. Historical DI curve-member tickers were retained for auditability.
A7: v12-03 | B7: 1-Oct-2026 | C7: Reproducibility package added | D7: WP-04; data documentation | E7: Created TFM_WP04_Brazil_3M_DI_YCSW0089.ipynb and README.md documenting Bloomberg/BQL source, units, construction, terminology, and intended referee-only use.
A8: v12-04 | B8: 1-Oct-2026 | C8: WP-04 remains open | D8: Dashboard; Revision Tracker; Action Sequence; Estimation Plan | E8: Data acquisition is complete, but WP-04 is not closed. Remaining gate: merge brazil_3m_di into the panel, validate date/scaling consistency, review correlations/VIF, run Model 5 and Model 6, and assess incremental information before reporting.

Sheet v13 Change Log
A1: TFM Master Revision Matrix - v13 Change Log
A2: Changes introduced on 1-Oct-2026 after adopting the Econometric Panel Data Freeze Gate. WP-04 data/rationale preparation is complete but its regression stage is parked until post-freeze robustness; WP-06 / MR-09 (VIX) is now the active audit.
A4: ID | B4: Date | C4: Change | D4: Affected items | E4: Detail
A5: v13-01 | B5: 1-Oct-2026 | C5: Econometric Panel Data Freeze Gate adopted | D5: README; Dashboard; Action Sequence; Estimation Plan | E5: Final baseline, diagnostics and robustness regressions are blocked until all baseline explanatory-variable audits are closed or explicitly accepted unchanged and panel_main_and_robustness.xlsx is rebuilt/frozen as the authoritative input.
A6: v13-02 | B6: 1-Oct-2026 | C6: WP-04 regression stage parked | D6: WP-04; MR-04; Estimation Plan | E6: Kept the completed SELIC rationale and Brazil 3M DI data/reproducibility package, but changed the regression-dependent stage to Deferred. Models 5-6 will run only after the data freeze and core baseline rerun.
A7: v13-03 | B7: 1-Oct-2026 | C7: VIX audit activated | D7: WP-06; MR-09; Dashboard; Estimation Plan | E7: Activated VIX as the current explanatory-variable audit. Required sequence is source/ticker -> raw series -> monthly convention -> panel match -> transformation/scaling -> economic label; final sign interpretation waits for post-freeze DK results.
A8: v13-04 | B8: 1-Oct-2026 | C8: Estimation sequence revised to avoid rework | D8: Revision Tracker; Action Sequence; Estimation Plan | E8: New sequence: audit/finalize explanatory variables -> freeze authoritative panel -> rerun baseline FE-DK once -> diagnostics -> targeted robustness, including the referee-only Brazil 3M DI exercise.

Sheet v14 Change Log
A1: TFM Master Revision Matrix - v14 Change Log
A2: Changes introduced on 2-Oct-2026 after completing the pre-freeze VIX data/proxy audit, correcting the thesis VIX/H1 wording, and continuing the Econometric Panel Data Freeze Gate with the remaining baseline-regressor audits.
A4: ID | B4: Date | C4: Change | D4: Affected items | E4: Detail
A5: v14-01 | B5: 2-Oct-2026 | C5: VIX source and monthly-history audit completed | D5: WP-06; MR-09; README; Dashboard | E5: Confirmed macro_explanatory_variables.xlsx / VIX Index. Bloomberg field metadata is not preserved in the values-only workbook. Independent validation found 187/187 monthly values from Jan-2010 to Jul-2025 equal to FRED VIXCLS at the last available daily close; workbook dates use the last weekday of each month as the monthly label.
A6: v14-02 | B6: 2-Oct-2026 | C6: VIX panel mapping and scaling validated | D6: WP-06; MR-09; Estimation Plan | E6: Matched 4,229/4,229 panel rows exactly across 164 distinct panel months, with no missing or conflicting within-month VIX values. Stata uses VIX in raw index points; no log, standardization, divide-by-100 or differencing is applied.
A7: v14-03 | B7: 2-Oct-2026 | C7: VIX terminology and H1 framing corrected | D7: WP-06; MR-09; thesis Sections 3-5 | E7: Reframed VIX as expected 30-day S&P 500 implied volatility used as a parsimonious proxy for global financial stress, not pure risk aversion. H1/Table 1 and VIX result labels were updated accordingly while preserving the positive ex-ante sign prediction.
A8: v14-04 | B8: 2-Oct-2026 | C8: Data Freeze Gate handed to remaining regressors | D8: Dashboard; Action Sequence; Estimation Plan | E8: MR-09 remains In progress only for post-freeze raw/partial correlations and final DK sign/H1 interpretation. No final sign narrative is accepted yet. Continue the pre-freeze audit with nominal Fed 3M Forward, then the remaining baseline regressors; do not rerun final baseline or robustness models before the gate passes.

Sheet v15 Change Log
A1: v15 Change Log
A2: Changes introduced on 2-Oct-2026 after identifying and independently validating the Bloomberg source for nominal Fed 3M Forward and completing the raw-series and monthly-convention stages of the Data Freeze Gate.
A4: ID | B4: Date | C4: Change | D4: Affected items | E4: Detail
A5: v15-01 | B5: 2-Oct-2026 | C5: Fed 3M Forward Bloomberg source identified | D5: WP-06; MR-09; Estimation Plan | E5: Identified the baseline panel series as Bloomberg USSOC Curncy, field PX_LAST, the 3M USD OIS fixed rate. BQNT reproduces panel spot-check values exactly to four decimals. FEDL01 Index is explicitly rejected as the source because it is the effective Fed Funds rate and does not match the panel series.
A6: v15-02 | B6: 2-Oct-2026 | C6: Fed raw-series audit completed | D6: WP-06; MR-09 | E6: Validated the native daily USSOC Curncy history over 2010-2025. The series is quoted in percentage points, has normal non-quotation-day gaps, and provides continuous coverage across the thesis sample.
A7: v15-03 | B7: 2-Oct-2026 | C7: Fed monthly convention validated | D7: WP-06; MR-09 | E7: Validated calendar-month-end extraction with the previous available quote used when month-end is not a quotation day. The resulting 2011 monthly values reproduce the panel exactly, including months whose panel date is the last business day.
A8: v15-04 | B8: 2-Oct-2026 | C8: Fed reproducibility package archived; audit remains open | D8: WP-06; MR-09; Dashboard; Action Sequence | E8: Committed the BQNT replication notebook and README in fb7748d under datos_y_modelos/db/brazil_macroeconomic_data/fed_3m_forward/. MR-09 remains In progress: Step 4 full-sample panel match, Step 5 transformation/scaling and Step 6 economic-label review still precede panel freeze and any regression rerun.

Sheet v16 Change Log
A1: TFM Master Revision Matrix - v16 Change Log
A2: Changes introduced on 2-Oct-2026 after completing the full six-step Fed 3M Forward Data Freeze audit, closing MR-09 as a proxy/data-definition issue, and handing the pre-freeze sequence to USD/BRL and the remaining baseline regressors.
A4: ID | B4: Date | C4: Change | D4: Affected items | E4: Detail
A5: v16-01 | B5: 2-Oct-2026 | C5: Fed full-sample panel match passed | D5: WP-06; MR-09; Data Freeze Gate | E5: Compared every distinct panel month to Bloomberg USSOC Curncy / PX_LAST by calendar month: 164/164 matched, 0 missing Bloomberg rows, 164 exact matches, 0 mismatches, maximum absolute difference 0.0.
A6: v16-02 | B6: 2-Oct-2026 | C6: Fed transformation/scaling validated | D6: WP-06; MR-09; Estimation Plan | E6: Confirmed the baseline uses fed_3m_forward directly in Bloomberg native percentage-point units. No divide-by-100, multiply-by-100, log, standardization or z-score is applied; D.fed_3m_forward is created only for the separate macro-differences robustness specification.
A7: v16-03 | B7: 2-Oct-2026 | C7: Fed economic label corrected without renaming shorthand | D7: WP-06; MR-09; thesis Sec. 4.5.3 | E7: Retained “Fed 3M Forward” as the intuitive thesis-facing shorthand, but replaced the inaccurate forward-curve construction text with the exact definition: Bloomberg USSOC Curncy / PX_LAST, 3M USD OIS fixed rate referencing EFFR, last available monthly close, forward-looking in economic content but not a forward-starting rate.
A8: v16-04 | B8: 2-Oct-2026 | C8: MR-09 closed; Data Freeze Gate moves to USD/BRL | D8: MR-09; WP-06; Dashboard; Action Sequence | E8: Closed MR-09 as a VIX/global-proxy data-definition issue after the VIX audit and companion Fed six-step audit. Post-freeze raw/partial correlations and final VIX sign/H1 interpretation are consolidated under MR-18/MR-19. WP-06 remains the active Data Freeze Gate container, with USD/BRL next; no final regression rerun yet.

Sheet v17 Change Log
A1: v17 Change Log
A2: Changes introduced on 2-Oct-2026 after completing the six-step nominal USD/BRL Data Freeze audit, documenting its provenance limitation, and handing the pre-freeze sequence to GDP YoY while preserving the separate RER audit dependency.
A4: ID | B4: Date | C4: Change | D4: Affected items | E4: Detail
A5: v17-01 | B5: 2-Oct-2026 | C5: USD/BRL source, raw series and month-end convention validated | D5: WP-06; Data Freeze Gate; Estimation Plan | E5: Macro workbook identifies “USDBRL Spot Exchange Rate - Price of 1 USD in BRL” / USDBRL Curncy. Original Bloomberg formula/raw source layer is not retained and repo search found no second ticker trace. Thesis-window source series has 187 uninterrupted monthly observations Jan-2010 to Jul-2025, no zeros/blanks/duplicate months, and all dates are the last weekday of the month.
A6: v17-02 | B6: 2-Oct-2026 | C6: USD/BRL full panel match passed | D6: WP-06; Data Freeze Gate | E6: Panel ts.usd_brl contains 0 blanks across 4,229 rows and 164 unique months (Dec-2010 to Jun-2025). Each month has one common FX value; no panel months are absent from the macro source; month-by-month comparison produced 0 mismatches.
A7: v17-03 | B7: 2-Oct-2026 | C7: USD/BRL scaling and economic label validated | D7: WP-06; Estimation Plan; thesis FX wording | E7: Baseline Stata uses usd_brl directly in nominal BRL-per-USD levels, with no log, /100, *100, z-score or standardization. D_usd_brl = D.usd_brl exists only for the macro-differences robustness. Economic label frozen as nominal USD/BRL (BRL per USD), month-end spot; an increase denotes BRL depreciation.
A8: v17-04 | B8: 2-Oct-2026 | C8: Data Freeze Gate moves to GDP YoY; RER dependency preserved | D8: Dashboard; Revision Tracker; Action Sequence; Estimation Plan | E8: Next audit is GDP YoY under the same six-step sequence. No final regressions may be rerun yet. The completed nominal NER audit does not validate RER; if RER replaces NER in the final core table, RER must be audited separately before panel freeze.

Sheet v18 Change Log
A1: TFM Master Revision Matrix - v18 Change Log
A2: Changes introduced on 2-Oct-2026 after integrating the Zoom meeting with Martin Grandes: updated scope, liquidity/rating guidance, DK/PCSE technical framing, pricing-data robustness and the 10-Oct delivery / week-of-13-Oct review sequence.
A4: ID | B4: Date | C4: Change | D4: Affected items | E4: Detail
A5: v18-01 | B5: 2-Oct-2026 | C5: Director meeting integrated and revision scope reset | D5: README; Director Guidance; Action Sequence | E5: Not every jury suggestion requires a new regression. Preserve the Data Freeze Gate, prioritize the data/econometric contribution, and map each comment to change, diagnostic, descriptive evidence, defense answer or reasoned non-change.
A6: v18-02 | B6: 2-Oct-2026 | C6: Liquidity proxy interpretation reaffirmed | D6: WP-03; MR-14; Estimation Plan | E6: Keep AMT_ISSUED / BS_TOT_ASSET. The numerator is static but quarterly assets create within-bond variation. Frame it as relative issue size / primary issuance-liquidity; turnover/amount-outstanding is conceptually cleaner for secondary liquidity but likely sparse/zero-heavy.
A7: v18-03 | B7: 2-Oct-2026 | C7: VIX and Brazil 3M DI roles confirmed | D7: MR-09; MR-04; WP-04; WP-06 | E7: Retain VIX and defend it with literature; no proxy replacement is required solely for the review. Keep Brazil 3M DI/SELIC outside the baseline and run it only post-freeze as the specified robustness exercise with FED3M retained versus omitted.
A8: v18-04 | B8: 2-Oct-2026 | C8: DK/PCSE inference framing tightened | D8: MR-16; MR-17; MR-23; WP-07; Estimation Plan | E8: Main output remains bond FE with Driscoll-Kraay covariance/SE. Explicitly distinguish FE coefficient estimation from covariance treatment, document the heteroskedasticity/serial/cross-sectional-dependence rationale, and keep PCSE/plain-FE alternatives appendix/internal only.
A9: v18-05 | B9: 2-Oct-2026 | C9: Ratings scope narrowed to descriptive evidence | D9: MR-06; MR-07; WP-05; Dashboard | E9: Minimum response is a sourced table/column of long-term local-currency issuer ratings. Do not assume all issuers are AA/AAA. Rating/sector interactions and issuer/bond slopes are optional only if powered and useful after the core estimates.
A10: v18-06 | B10: 2-Oct-2026 | C10: Pricing-data QA expanded | D10: MR-25; WP-09; Estimation Plan | E10: Before panel freeze, attempt the corrected baseline without prior-value fill-forward and choose the authoritative missing-price rule. If no-fill coverage is impractical, justify carry-forward and retain the alternative as sensitivity. Document Bloomberg BVAL/Bival indicative/model pricing and its exclusion/handling explicitly.
A11: v18-07 | B11: 2-Oct-2026 | C11: Delivery target and deck sequence updated | D11: Process & Deadlines; WP-08; WP-16; Action Sequence; Estimation Plan | E11: Old 30-Sep target superseded. Send corrected post-freeze DK regressions, agreed robustness/sensitivity results and an updated presentation to Martin by 10-Oct-2026; review together in the week of 13-Oct, then refine abstract/presentation/interpretation.

Sheet v19 Change Log
A1: TFM Master Revision Matrix - v19 Change Log
A2: Changes introduced on 3-Oct-2026 after completing the full six-step GDP YoY Data Freeze audit and handing the pre-freeze sequence to Public debt/GDP.
A4: ID | B4: Date | C4: Change | D4: Affected items | E4: Detail
A5: v19-01 | B5: 3-Oct-2026 | C5: GDP YoY source/ticker validated | D5: WP-06; Data Freeze Gate; Estimation Plan | E5: Macro workbook identifies Real GDP (yoy %) / BZGDYOY% Index. The same ticker appears in columns 7 and 17; both contain 430 non-null observations and are exactly identical row by row. The workbook has only a values_only sheet, so no surviving Bloomberg formula layer is available beyond the stored ticker metadata.
A6: v19-02 | B6: 3-Oct-2026 | C6: GDP raw series characterized | D6: WP-06; Data Freeze Gate | E6: Dated macro coverage is Oct-1989 to Jul-2025. In 2010-2025 the grid has 187 monthly rows: 61 nonzero GDP observations, 126 literal zero placeholders and 0 blanks. There are four nonzero quarter-end observations per year in 2010-2024 and one Q1 observation in 2025 through the workbook cutoff.
A7: v19-03 | B7: 3-Oct-2026 | C7: GDP monthly convention validated | D7: WP-06; Data Freeze Gate | E7: Panel gdp_yoy is a common monthly macro variable and carries each quarter-end GDP YoY observation forward until the next quarterly observation. The raw workbook zeros between quarter ends are placeholders and are not interpreted as 0% GDP growth.
A8: v19-04 | B8: 3-Oct-2026 | C8: GDP full-sample panel match passed | D8: WP-06; Data Freeze Gate | E8: Reconstructed the panel from raw BZGDYOY% quarter-end observations using the carry-forward rule. All 164 distinct panel months from Dec-2010 to Jun-2025 matched exactly: 164/164 exact matches, 0 mismatches and 0 within-month cross-sectional conflicts.
A9: v19-05 | B9: 3-Oct-2026 | C9: GDP transformation/scaling validated | D9: WP-06; Estimation Plan | E9: Panel gdp_yoy ranges from -10.14 to 12.4 and is stored directly in percentage-point units. No divide-by-100, multiply-by-100, log, z-score or standardization is applied. Stata uses gdp_yoy in levels; the macro-differences robustness differences Fed, FX and debt/GDP but not gdp_yoy.
A10: v19-06 | B10: 3-Oct-2026 | C10: GDP economic label standardized | D10: WP-06; thesis macro-variable wording | E10: Standard label frozen as “Brazil real GDP growth, year-on-year (%)”; Spanish: “crecimiento interanual del PIB real (%)”. Coefficients are interpreted per 1 percentage-point change in YoY real GDP growth. Caveat: mechanical reference-period dating is validated, but real-time release-vintage alignment was not separately audited.
A11: v19-07 | B11: 3-Oct-2026 | C11: Data Freeze Gate moves to Public debt/GDP | D11: Dashboard; Revision Tracker; Action Sequence; Estimation Plan | E11: GDP YoY is fully passed with no panel modification required. Next audit is Public debt/GDP under the same six-step sequence. Do not rerun regressions or modify the frozen-candidate panel until all remaining baseline regressors and the corporate-pricing source/missing-value rule are closed.

Sheet v20 Change Log
A1: TFM Master Revision Matrix - v20 Change Log
A2: Changes introduced on 3-Oct-2026 after completing the six-step audit of legacy debt_gdp, identifying the fiscal-balance/public-debt semantic mismatch, and handing the next baseline audit to cf_cash_oper_to_tot_asset.
A4: ID | B4: Date | C4: Change | D4: Affected items | E4: Detail
A5: v20-01 | B5: 3-Oct-2026 | C5: debt_gdp source lineage corrected | D5: WP-06; Data Freeze Gate; Estimation Plan | E5: Distinctive panel debt_gdp values were traced exactly to macro workbook column 21, “Budget Surplus/Deficit (% GDP)” / EHBBBR Index. GDDBBRAZ Index is a separate public-debt/GDP candidate and is not the source of the existing panel variable.
A6: v20-02 | B6: 3-Oct-2026 | C6: Actual Bloomberg fiscal series validated | D6: WP-06; Data Freeze Gate | E6: Bloomberg DES identifies EHBBBR Index as Brazil Budget Balance (% GDP), seasonally adjusted, Percent, Quarterly, source Bloomberg, start Q4 1995; Bloomberg also references underlying ticker BZPBNO% Index. The economic concept is fiscal/budget balance, not debt stock.
A7: v20-03 | B7: 3-Oct-2026 | C7: Raw EHBBBR series and vintage validated | D7: WP-06; Data Freeze Gate | E7: Direct BQL history confirms a complete quarterly series across 2010Q1-2025Q4. The local macro workbook contains 62 nonzero quarterly observations from 2010Q1-2025Q2 and is a coherent older Bloomberg vintage: it matches current BQL through 2023, with only small later revisions in 2024-2025. The frozen-candidate panel uses the local snapshot; no automatic refresh was made.
A8: v20-04 | B8: 3-Oct-2026 | C8: Monthly convention and full panel match passed | D8: WP-06; Data Freeze Gate | E8: Quarter-end EHBBBR observations are carried forward monthly until the next quarter. All 164 distinct panel months reproduce exactly. Full row audit covers 4,229 observations from Dec-2010 to Jun-2025: 0 missing debt_gdp values, 0 row-level mismatches and 0 months with cross-sectional conflicts.
A9: v20-05 | B9: 3-Oct-2026 | C9: Scaling and economic label corrected | D9: WP-06; Estimation Plan; thesis macro-variable wording | E9: The panel uses EHBBBR in levels and native percentage points of GDP with no /100, *100, log, z-score, sign reversal or standardization. Correct label: fiscal/budget balance (% GDP); Spanish: saldo fiscal (% del PIB). Negative values denote fiscal deficits.
A10: v20-06 | B10: 3-Oct-2026 | C10: Material semantic/specification issue flagged | D10: MR-22; WP-06; Estimation Plan; final panel rebuild | E10: Legacy variable name debt_gdp and existing “No debt/GDP” output labels are semantically wrong. Because Martin’s core template calls for Public debt/GDP, the Data Freeze Gate must explicitly decide whether to retain/relabel fiscal balance, replace it with a properly sourced true public-debt/GDP control, or otherwise reconcile the macro specification. Do not silently substitute GDDBBRAZ.
A11: v20-07 | B11: 3-Oct-2026 | C11: Data Freeze Gate moves to firm-liquidity audit | D11: Dashboard; Revision Tracker; Action Sequence; Estimation Plan | E11: Next six-step audit is cf_cash_oper_to_tot_asset, followed by the remaining baseline controls. The fiscal-control specification decision remains an open pre-freeze gate item. Do not modify/rebuild the authoritative panel or rerun final regressions until all remaining variable audits, the fiscal-control decision and the corporate-pricing source/missing-value rule are closed.

Sheet v21 Change Log
A1: TFM Master Revision Matrix - v21 Change Log
A2: Changes introduced on 4-Oct-2026 after completing the six-step audit of cf_cash_oper_to_tot_asset, identifying the same-quarter accounting-timing issue, and handing the next baseline audit to tot_debt_to_ebitda.
A4: ID | B4: Date | C4: Change | D4: Affected items | E4: Detail
A5: v21-01 | B5: 4-Oct-2026 | C5: Cash-flow/assets source lineage validated | D5: WP-06; Data Freeze Gate; Estimation Plan | E5: Exact issuer-level Bloomberg fundamental inputs are CF_CASH_FROM_OPER.xlsx / field CF_CASH_FROM_OPER and BS_TOT_ASSET.xlsx / field BS_TOT_ASSET. Bond metadata column 24 is ULT_PARENT_TICKER_EXCHANGE. Normalizing the trailing Bloomberg “Equity” suffix aligns all 27 parent tickers represented in the thesis panel with both source workbooks.
A6: v21-02 | B6: 4-Oct-2026 | C6: Raw quarterly fundamentals characterized | D6: WP-06; Data Freeze Gate | E6: Both source workbooks use the same quarterly issuer-ticker layout on a 1999Q1-2025Q4 grid and contain time-varying accounting observations; negative operating cash flow values are preserved. The thesis-panel parent tickers required for the 2010-2025 sample are present in both inputs.
A7: v21-03 | B7: 4-Oct-2026 | C7: Monthly convention identified; timing blocker raised | D7: WP-06; Data Freeze Gate; final panel rebuild | E7: The current monthly panel assigns each quarter’s CF_CASH_FROM_OPER / BS_TOT_ASSET ratio contemporaneously to all three months of that calendar quarter, with no interpolation or publication lag. This can place eventual Q1 financial-statement information into January/February and therefore creates a potential look-ahead/information-availability problem that must be remediated before freeze.
A8: v21-04 | B8: 4-Oct-2026 | C8: Full 4,229-row panel match passed | D8: WP-06; Data Freeze Gate | E8: Full audit covers all 4,229 panel observations and all 27 mapped parent tickers: 4,229/4,229 rows have a source quarter, 4,229/4,229 panel values are nonmissing, 4,229/4,229 match the reconstructed source series within 1e-4, maximum absolute difference is 5.68e-14, with 0 missing source quarters and 0 mismatches.
A9: v21-05 | B9: 4-Oct-2026 | C9: Transformation/scaling and economic label validated | D9: WP-06; Estimation Plan; thesis firm-control wording | E9: The implied scale is exactly 1000 for every comparable observation: cf_cash_oper_to_tot_asset = 1000 x CF_CASH_FROM_OPER / BS_TOT_ASSET. Stored units are per mille (‰), not a raw fraction or percentage points. Standard label: operating cash flow / total assets (‰), an issuer-level proxy for internal liquidity and short-term financial strength.
A10: v21-06 | B10: 4-Oct-2026 | C10: Cash-flow audit complete but freeze readiness blocked | D10: WP-06; Data Freeze Gate; final panel rebuild | E10: The six-step lineage/data audit is complete, but the variable is not yet freeze-ready because the monthly information timing is not observation-date defensible. Choose and document an information-availability/lag convention together with the fiscal-control and pricing-rule decisions, then rebuild the authoritative panel once. No ad hoc panel edit and no regression rerun yet.
A11: v21-07 | B11: 4-Oct-2026 | C11: Data Freeze Gate moves to Debt / EBITDA | D11: Dashboard; Revision Tracker; Action Sequence; Estimation Plan | E11: Next six-step audit is tot_debt_to_ebitda, followed by any remaining baseline controls. Continue the sequence source/field -> raw series -> monthly convention -> panel match -> transformation/scaling -> economic label. Final estimation remains blocked until all variable audits and the fiscal-control, cash-flow timing and corporate-pricing decisions are closed.

Sheet v22 Change Log
A1: TFM Master Revision Matrix - v22 Change Log
A2: Changes introduced on 4-Oct-2026 after completing the six-step audit of tot_debt_to_ebitda, identifying a second same-quarter accounting-timing issue, and handing the next baseline audit to days_to_maturity.
A4: ID | B4: Date | C4: Change | D4: Affected items | E4: Detail
A5: v22-01 | B5: 4-Oct-2026 | C5: Debt / EBITDA historical source lineage reconstructed | D5: WP-06; Data Freeze Gate; Estimation Plan | E5: The panel series is not the static Bloomberg TOT_DEBT_TO_EBITDA snapshot in universo_brazil_deb_des.xlsx. Historical values are reconstructed from issuer-level Bloomberg Fundamentals SHORT_AND_LONG_TERM_DEBT.xlsx / field SHORT_AND_LONG_TERM_DEBT divided by EBITDA.xlsx / field EBITDA. Bond metadata maps through ULT_PARENT_TICKER_EXCHANGE; all 103 panel bonds map to 27 parent equity tickers present in both source workbooks.
A6: v22-02 | B6: 4-Oct-2026 | C6: Raw quarterly leverage inputs characterized | D6: WP-06; Data Freeze Gate | E6: Both source workbooks use the same quarterly Bloomberg equity-ticker layout on a 1999Q1-2025Q4 grid. For the 27 parent issuers relevant to the 2010-2025 thesis sample there are 1,728 possible issuer-quarter cells: 1,510 have both debt and EBITDA numeric, 2 have EBITDA numeric with debt missing, 5 have debt numeric with EBITDA missing, and 211 have neither; no paired numeric EBITDA equals zero.
A7: v22-03 | B7: 4-Oct-2026 | C7: Monthly convention identified; second timing blocker raised | D7: WP-06; Data Freeze Gate; final panel rebuild | E7: The current monthly panel assigns SHORT_AND_LONG_TERM_DEBT / EBITDA from the same calendar quarter to all three months of that quarter. All 4,229 panel observations match the same-quarter ratio exactly and zero match the previous-quarter ratio. This can place eventual quarterly accounting information into months before quarter-end/publication, creating a separate look-ahead/information-availability blocker.
A8: v22-04 | B8: 4-Oct-2026 | C8: Full 4,229-row leverage panel match passed | D8: WP-06; Data Freeze Gate | E8: All 4,229 econometric-panel observations have nonmissing tot_debt_to_ebitda and reproduce exactly from the mapped issuer-quarter SHORT_AND_LONG_TERM_DEBT / EBITDA source ratio. There are 0 missing panel values and 0 source-to-panel mismatches.
A9: v22-05 | B9: 4-Oct-2026 | C9: Transformation/scaling and economic label validated | D9: WP-06; Estimation Plan; thesis firm-control wording | E9: The panel stores the raw leverage multiple in x-times units with no x100, log, standardization, winsorization or other transformation. Current panel range is -400.6213x to 662.2234x, with 158 negative observations. Standard label: financial leverage (short- and long-term debt / EBITDA); Spanish: apalancamiento financiero (deuda de corto y largo plazo / EBITDA).
A10: v22-06 | B10: 4-Oct-2026 | C10: Debt / EBITDA audit complete but freeze readiness blocked | D10: WP-06; Data Freeze Gate; final panel rebuild | E10: The six-step lineage/data audit is complete, but the variable is not yet freeze-ready because the contemporaneous same-quarter monthly assignment is not observation-date defensible. Keep this blocker separate from the existing cf_cash_oper_to_tot_asset timing issue; choose and document availability/lag conventions during the controlled final panel rebuild. No ad hoc panel edit and no regression rerun yet.
A11: v22-07 | B11: 4-Oct-2026 | C11: Data Freeze Gate moves to residual maturity | D11: Dashboard; Revision Tracker; Action Sequence; Estimation Plan | E11: Next six-step audit is days_to_maturity, followed by any remaining baseline controls. Continue source/field -> raw series -> monthly convention -> panel match -> transformation/scaling -> economic label. Final estimation remains blocked until all variable audits and the fiscal-control, both accounting-timing, and corporate-pricing decisions are closed.

Sheet v23 Change Log
A1: TFM Master Revision Matrix - v23 Change Log
A2: Changes introduced on 4-Oct-2026 after completing the six-step audit of days_to_maturity, identifying the exact BUS/252 residual-maturity convention and code-helper discrepancy, and handing the final baseline-regressor reconciliation to synthetic_cds_brl / Sovereign Risk (BRL).
A4: ID | B4: Date | C4: Change | D4: Affected items | E4: Detail
A5: v23-01 | B5: 4-Oct-2026 | C5: Residual-maturity source lineage validated | D5: WP-06; Data Freeze Gate; Estimation Plan | E5: Underlying source is contractual MATURITY in datos_y_modelos\Domestic\universo_brazil_deb_des.xlsx, sheet db_values_only. load_corp_bond_data reads the field directly; filter_corporate_universe parses it to datetime. All 103 econometric-panel bond IDs match uniquely to source metadata with 0 missing maturity dates; matched maturity range is 2015-01-15 to 2041-12-15.
A6: v23-02 | B6: 4-Oct-2026 | C6: Raw maturity metadata characterized | D6: WP-06; Data Freeze Gate | E6: The full 6,926-security source has 67 nonblank MATURITY values that coerce to NaT because they are Bloomberg sentinel strings (#N/A Field Not Applicable), but none survive into the relevant filtered IPCA corporate universe: 835 filtered IPCA bonds have 0 MATURITY NaT. The 103 thesis-panel bonds are therefore clean and complete.
A7: v23-03 | B7: 4-Oct-2026 | C7: Monthly observation-date convention validated | D7: WP-06; Data Freeze Gate | E7: Residual maturity is measured from the actual authoritative monthly obs_date, not a mechanically imposed calendar month-end. The corporate monthly-YTM file and real_curve_surface_corp.xlsx each contain exactly the same 175 unique obs_dates from 2010-12-30 to 2025-06-30, one date per month. 113 are literal calendar month-end and 62 are earlier dates.
A8: v23-04 | B8: 4-Oct-2026 | C8: Full 4,229-row residual-maturity panel match passed | D8: WP-06; Data Freeze Gate | E8: The legacy panel name days_to_maturity is misleading: every stored value multiplied by 252 is an integer business-day count. All 4,229/4,229 rows reproduce exactly as ANBIMA business days from obs_date through contractual maturity, including the maturity date when it is a valid business day, divided by 252, with 20 November included as a holiday from 2024 onward. Maximum numerical difference is floating-point noise only (5.33e-15).
A9: v23-05 | B9: 4-Oct-2026 | C9: Transformation/scaling and economic label validated | D9: WP-06; Estimation Plan; thesis bond-control wording | E9: The econometric variable is residual maturity in BUS/252 years and enters Stata directly in levels; there is no log, standardization, differencing or further rescaling. Preferred label: residual bond maturity (BUS/252 years); Spanish: plazo residual al vencimiento (años, BUS/252). Thesis text already describes the measure as business-day-normalized / equivalent years, so the substantive concept is consistent even though the technical column name says days.
A10: v23-06 | B10: 4-Oct-2026 | C10: Day-count code-consistency blocker documented | D10: WP-06; final panel rebuild; code integrity | E10: Current DayCounts("bus/252", calendar="cdr_anbima") does not reproduce the frozen panel convention because the hard-coded cdr_anbima list omits 20 November from 2024 onward and numpy.busday_count excludes the terminal date. Do not alter the historical 4,229 values ad hoc; align/document the reusable day-count helper during the controlled final rebuild and verify that any curve-tenor use remains consistent.
A11: v23-07 | B11: 4-Oct-2026 | C11: Data Freeze Gate moves to sovereign panel-field reconciliation | D11: Dashboard; Revision Tracker; Action Sequence; Estimation Plan | E11: Next focused audit is the existing synthetic_cds_brl field in panel_main_and_robustness.xlsx / current Stata baseline. Reconcile it with the already-validated Sovereign Risk (BRL) / sovereign_spread_brl construction, remove residual synthetic-CDS terminology, and verify final source/date/units/panel mapping. After that, resolve fiscal-control, accounting-timing and corporate-pricing blockers before the one controlled panel rebuild and final FE-DK rerun.

Sheet v24 Change Log
A1: TFM Master Revision Matrix - v24 Change Log
A2: Changes introduced on 4-Oct-2026 after completing the synthetic_cds_brl / Sovereign Risk (BRL) reconciliation, identifying the fixed post-sample curve and tenor-parser defects, and moving the Data Freeze Gate to the fiscal-control specification decision.
A4: ID | B4: Date | C4: Change | D4: Affected items | E4: Detail
A5: v24-01 | B5: 4-Oct-2026 | C5: Legacy sovereign-field lineage reconstructed | D5: WP-06; Data Freeze Gate; Estimation Plan | E5: Current synthetic_cds_brl is not a CDS and not a simple old name for sovereign_spread_brl. Its upstream pipeline builds a sovereign spread surface from government-bond summaries and pools three universes: LTN versus DI, NTN-F versus DI, and NTN-B versus the real IPCA reference curve.
A6: v24-02 | B6: 4-Oct-2026 | C6: Validated nominal raw package separated from legacy real component | D6: WP-02; WP-06; Data Freeze Gate | E6: Validated Sovereign Risk (BRL) raw series is exactly 582/582 nominal observations: 252 LTN observations across 13 bonds plus 330 NTN-F observations across 5 bonds. Legacy synthetic surface additionally includes 1,107 NTN-B observations across 12 bonds, benchmarked to the real curve, making the pooled object economically heterogeneous.
A7: v24-03 | B7: 4-Oct-2026 | C7: Monthly convention passed upstream but failed at panel injection | D7: WP-06; final panel rebuild | E7: LTN, NTN-F and NTN-B raw files each contain one common observation date per calendar month, consistent with an EOM/last-business-day convention. However add_synthetic_cds_to_panel.py discards the historical date dimension by selecting cds_surface.iloc[-1] and fitting only that latest curve before mapping every corporate-panel observation.
A8: v24-04 | B8: 4-Oct-2026 | C8: Current 4,229-row panel mapping proved non-contemporaneous | D8: WP-06; Data Freeze Gate | E8: All 4,229 panel rows contain synthetic_cds_brl, but the field is a deterministic maturity function rather than contemporaneous sovereign risk: there are 1,542 unique days_to_maturity values and exactly 1,542 unique synthetic values; among 994 repeated maturity groups, none has more than one synthetic value. Thus identical maturity always implies identical legacy sovereign value regardless of observation date.
A9: v24-05 | B9: 4-Oct-2026 | C9: Legacy fixed-curve transformation reproduced and defects documented | D9: WP-06; code integrity; Estimation Plan | E9: Re-fitting the archived latest surface dated 2025-08-04 reproduces the current panel synthetic_cds_brl almost exactly (max absolute difference about 0.000104 bp; mean about 0.0000067 bp), even though the regression sample ends 2025-06-30. Units remain bps, so there is no simple x100 scaling error. The legacy tenor parser maps 6-month to 6.0 years, creating duplicate 6-year inputs; the simplified NSS fit also leaves tau2 inactive, consistent with the optimization covariance warning.
A10: v24-06 | B10: 4-Oct-2026 | C10: Economic label decision: legacy proxy invalid; validated sovereign_spread_brl retained | D10: WP-02; WP-06; thesis/econometric consistency | E10: Repository labels such as Synthetic CDS-BRL are misleading: no CDS contract enters the construction. Thesis wording is already correct and explicitly defines sovereign_spread_brl as nominal LTN/NTN-F versus same-date exact-tenor DI and not a CDS. Decision: mark current synthetic_cds_brl NOT FREEZE-READY / REPLACEMENT REQUIRED. Do not reinterpret its existing regression coefficient as the validated sovereign result.
A11: v24-07 | B11: 4-Oct-2026 | C11: Data Freeze Gate moves to fiscal-control specification decision | D11: Dashboard; Revision Tracker; Action Sequence; Estimation Plan | E11: All baseline-regressor six-step audits/reconciliations are now complete. Next dedicated task is the fiscal-control decision for legacy debt_gdp, already traced to Bloomberg EHBBBR Brazil Budget Balance (% GDP), not public debt/GDP: explicitly decide retain+relabel versus replace with a true debt/GDP series. Then close both accounting-information timing conventions, residual-maturity helper consistency and the corporate-pricing rule before the one controlled panel rebuild/freeze and final FE-DK rerun. No panel edits or regressions were run during the sovereign audit.

Sheet v25 Change Log
A1: TFM Master Revision Matrix - v25 Change Log
A2: Changes introduced on 5-Oct-2026 after closing the fiscal-control specification decision, selecting official BCB SGS 13762 Public debt/GDP with a uniform L2 timing convention, documenting the missing legacy panel-builder reproducibility path, and moving the Data Freeze Gate to the two accounting-information timing rules.
A4: ID | B4: Date | C4: Change | D4: Affected items | E4: Detail
A5: v25-01 | B5: 5-Oct-2026 | C5: Fiscal-control economic specification closed | D5: WP-06; MR-22; Estimation Plan | E5: Thesis H8 / variable definitions and Martin's requested macro block require Public debt/GDP, while the audited legacy panel field debt_gdp is Bloomberg EHBBBR Index / Brazil Budget Balance (% GDP), a quarterly fiscal-flow measure. Decision: reject retain+relabel for the baseline and replace it with a genuine public-debt/GDP stock measure during the one controlled final panel rebuild.
A6: v25-02 | B6: 5-Oct-2026 | C6: Official BCB replacement source selected and archived | D6: WP-06; Data Freeze Gate; macro source archive | E6: Selected Banco Central do Brasil SGS 13762, “Dívida bruta do governo geral (% PIB) - Metodologia utilizada a partir de 2008”, official BCB-DSTAT monthly series in percentage points of GDP. Raw snapshot archived at datos_y_modelos/db/brazil_macroeconomic_data/public_debt_gdp/sgs_13762_public_debt_gdp.csv with provenance README; snapshot covers 2010-01 through 2026-08. Official source page: https://www3.bcb.gov.br/sgspub/consultarvalores/consultarValoresSeries.do?method=visualizarValores
A7: v25-03 | B7: 5-Oct-2026 | C7: Bloomberg alternative assessed but not selected | D7: WP-06; source triangulation | E7: Bloomberg AI cross-check identified WGPDCBRA Index as a closest government-debt/GDP alternative but reported it as World-Bank-sourced and quarterly/sparse rather than a direct monthly BCB SGS 13762 feed. It is therefore retained only as a possible cross-check, not the baseline source. The official BCB series is preferred for concept, frequency and domestic-source fidelity.
A8: v25-04 | B8: 5-Oct-2026 | C8: Coverage and panel-month availability verified | D8: WP-06; Data Freeze Gate | E8: BCB SGS 13762 fully covers the current econometric-panel window: 164 distinct panel month-ends from 2010-12 through 2025-06 can be mapped with contemporaneous, L1 or L2 reference-month values with 0 missing observations. Values remain in native percentage points of GDP; no /100, *100, log, z-score or standardization is intended.
A9: v25-05 | B9: 5-Oct-2026 | C9: Uniform L2 fiscal timing convention selected | D9: WP-06; final panel rebuild | E9: Selected a uniform two-reference-month lag (L2) for public_debt_gdp as a transparent conservative/reproducible information-timing convention. Across 164 panel months, L1 versus L2 correlation is 0.997613, mean absolute difference 0.5295 percentage point of GDP and maximum absolute difference 2.92 pp. The thesis/tracker must not claim that L2 exactly reconstructs every historical BCB publication-vintage date; it is the chosen conservative rule for the controlled rebuild.
A10: v25-06 | B10: 5-Oct-2026 | C10: Legacy panel-builder reproducibility gap documented | D10: WP-06; final panel rebuild; code integrity | E10: Repository and Git-history searches found no tracked Python/notebook/do-file that constructs or overwrites panel_main_and_robustness.xlsx; the relevant scripts only read the submitted panel, consistent with the panel having been assembled manually. Historical regression outputs remain untouched. Remedy: introduce a reproducible controlled panel-construction step during the final rebuild instead of manually patching the XLSX.
A11: v25-07 | B11: 5-Oct-2026 | C11: Data Freeze Gate moves to accounting-information timing | D11: Dashboard; Revision Tracker; Action Sequence; Estimation Plan | E11: Fiscal-control specification is now closed. CURRENT: choose observation-date-defensible information-availability/lag rules for both cf_cash_oper_to_tot_asset and tot_debt_to_ebitda. Then align/document the residual-maturity BUS/252 helper and close the corporate-pricing rule. Only after those blockers are closed should one reproducible rebuild inject BCB SGS 13762 public_debt_gdp (L2), replace legacy synthetic_cds_brl with validated sovereign_spread_brl, freeze the panel and rerun FE-Driscoll-Kraay. No panel edits or regressions were run during this fiscal decision.

Sheet v26 Change Log
A1: TFM Master Revision Matrix - v26 Change Log
A2: Changes introduced on 5-Oct-2026 after closing the joint accounting-information timing decision, validating Bloomberg point-in-time availability and vintage handling, quantifying the one-quarter fallback with zero sample loss, and moving the Data Freeze Gate to residual-maturity BUS/252 helper consistency.
A4: ID | B4: Date | C4: Change | D4: Affected items | E4: Detail
A5: v26-01 | B5: 5-Oct-2026 | C5: Historical point-in-time mechanism validated | D5: WP-06; Data Freeze Gate; final panel rebuild | E5: Bloomberg BQL company-financials tests confirmed that dates=<obs_date> retrieves the historical public-information vintage known as of the requested date. PETR4 examples showed 2010Q4 values still in force on 2011-04-29 and the switch to 2011Q1 on REVISION_DATE 2011-05-13. fill=PREV correctly carries the last available PIT value between revision/reporting dates. This rejects mechanical same-calendar-quarter mapping and fixed accounting L1/L2 as inferior to exact observation-date availability.
A6: v26-02 | B6: 5-Oct-2026 | C6: Restatement-vintage look-ahead identified | D6: WP-06; accounting controls; reproducibility | E6: Fixed-period Bloomberg tests showed that the local quarterly fundamental workbooks match Bloomberg's current/latest-restated historical values, while historical dates=<obs_date> values can differ materially. Therefore the legacy local workbooks cannot by themselves reconstruct what investors could have known at past observation dates; the final controlled rebuild must use/archive a historical PIT extract or an equivalent reproducible BQL query with extraction/provenance metadata.
A7: v26-03 | B7: 5-Oct-2026 | C7: Joint accounting timing rule selected | D7: WP-06; Estimation Plan; final panel rebuild | E7: Final common rule for cf_cash_oper_to_tot_asset and tot_debt_to_ebitda: at each exact bond obs_date, use Bloomberg quarterly PIT fundamentals and select the most recent fiscal quarter for which CF_CASH_FROM_OPER, BS_TOT_ASSET, SHORT_AND_LONG_TERM_DEBT and EBITDA are jointly non-missing. Compute both ratios from that same fiscal period and historical vintage. If the newest reported quarter is incomplete, use the immediately preceding quarter. Never mix fiscal periods across numerator/denominator or across the two accounting controls.
A8: v26-04 | B8: 5-Oct-2026 | C8: Exact thesis-panel coverage passed | D8: WP-06; Data Freeze Gate | E8: The exact 1,959 issuer-date pairs represented by the 4,229-row thesis panel were tested under current reported quarter plus one-quarter fallback. All 1,959 pairs resolve; 14 pairs require fallback (0.715%) and 0 pairs are unresolved. The strict daily-history diagnostic had only eight transient unresolved IVPR3B days (2014-05-12 to 2014-05-19), none of which is an actual thesis observation date.
A9: v26-05 | B9: 5-Oct-2026 | C9: Bond-row fallback impact quantified | D9: WP-06; final panel rebuild; sample preservation | E9: The 14 fallback issuer-date pairs map to 29 of 4,229 bond-level panel rows (0.686%) across 12 distinct bonds. These rows are retained using the immediately preceding jointly complete PIT quarter; accounting-timing remediation therefore causes zero sample loss.
A10: v26-06 | B10: 5-Oct-2026 | C10: Legacy panel remains untouched pending controlled rebuild | D10: WP-06; replication; code integrity | E10: The accounting timing decision is now closed conceptually, but panel_main_and_robustness.xlsx is not edited yet and regressions are not rerun. Because Git/repository history contains no tracked legacy panel builder, the final rebuild must introduce a reproducible construction step that combines the closed fiscal L2 rule, validated sovereign_spread_brl replacement, closed PIT accounting rule, corrected BUS/252 helper and finalized pricing rule, then freezes the authoritative panel once.
A11: v26-07 | B11: 5-Oct-2026 | C11: Data Freeze Gate moves to residual-maturity helper consistency | D11: Dashboard; Revision Tracker; Action Sequence; Estimation Plan | E11: Accounting-information timing is CLOSED. CURRENT: audit the reusable DayCounts('bus/252', calendar='cdr_anbima') implementation against the already-validated residual-maturity convention (ANBIMA BUS/252, terminal maturity date included when valid, 20 November holiday from 2024 onward) and determine whether changing the helper would affect other curve/spread calculations. After that, close the corporate-pricing/BVAL/no-fill-forward rule. Only then perform the one controlled reproducible rebuild/freeze and rerun FE-Driscoll-Kraay.

Sheet v27 Change Log
A1: TFM Master Revision Matrix - v27 Change Log
A2: Changes introduced on 6-Oct-2026 after closing the residual-maturity BUS/252 helper-consistency audit, isolating the missing 20-Nov holiday in cdr_anbima, validating WLA 3,144/3,144 after the patch, and moving the Data Freeze Gate to the corporate-pricing/BVAL/no-fill-forward rule.
A4: ID | B4: Date | C4: Change | D4: Affected items | E4: Detail
