Workbook
Name feriados: [1]Feriados!$A$2:$A$1265

Sheet ts
A1: bond_id | B1: issuer | C1: maturity | D1: bond_type | E1: exchange id | F1: sector | G1: obs_date | H1: month | I1: spread | J1: vix | K1: fed_3m_forward | L1: usd_brl | M1: gdp_yoy | N1: debt_gdp | O1: cf_cash_oper_to_tot_asset | P1: amount_issued_to_bs_tot_asset | Q1: tot_debt_to_ebitda | R1: days_to_maturity | S1: synthetic_cds_brl
A2: AM250786 Corp | B2: MRV ENGENHARIA PARTICIP | C2: 2/15/2022 | D2: BRAZIL IPCA+SPREAD | E2: MRVE3 BZ | F2: Home Builders | G2: 42916 | H2: 42916 | I2: -2.4705585 | J2: 11.18 | K2: 1.163 | L2: 3.3082 | M2: 0.79 | N2: -9.45 | O2: 2.0910397 | P2: 6.0559379 | Q2: 19.296258 | R2: 4.6150794 | S2: 3.8953252
A3: AM250786 Corp | B3: MRV ENGENHARIA PARTICIP | C3: 2/15/2022 | D3: BRAZIL IPCA+SPREAD | E3: MRVE3 BZ | F3: Home Builders | G3: 42947 | H3: 42947 | I3: -2.2332537 | J3: 10.26 | K3: 1.161 | L3: 3.1254 | M3: 0.79 | N3: -9.45 | O3: 6.6499526 | P3: 5.6131362 | Q3: 15.349094 | R3: 4.531746 | S3: 3.9363574
A4: AM250786 Corp | B4: MRV ENGENHARIA PARTICIP | C4: 2/15/2022 | D4: BRAZIL IPCA+SPREAD | E4: MRVE3 BZ | F4: Home Builders | G4: 42978 | H4: 42978 | I4: -3.0056741 | J4: 10.59 | K4: 1.1585 | L4: 3.1491 | M4: 0.79 | N4: -9.45 | O4: 6.6499526 | P4: 5.6131362 | Q4: 15.349094 | R4: 4.4404762 | S4: 3.9777411
A5: AM250786 Corp | B5: MRV ENGENHARIA PARTICIP | C5: 2/15/2022 | D5: BRAZIL IPCA+SPREAD | E5: MRVE3 BZ | F5: Home Builders | G5: 43007 | H5: 43008 | I5: -2.7892655 | J5: 9.51 | K5: 1.193 | L5: 3.1625 | M5: 1.64 | N5: -8.73 | O5: 6.6499526 | P5: 5.6131362 | Q5: 15.349094 | R5: 4.3611111 | S5: 4.010667
A6: AM250786 Corp | B6: MRV ENGENHARIA PARTICIP | C6: 2/15/2022 | D6: BRAZIL IPCA+SPREAD | E6: MRVE3 BZ | F6: Home Builders | G6: 43039 | H6: 43039 | I6: -3.3834352 | J6: 10.18 | K6: 1.273 | L6: 3.2713 | M6: 1.64 | N6: -8.73 | O6: 6.7083834 | P6: 5.4950716 | Q6: 14.055061 | R6: 4.2777778 | S6: 4.0421374
A7: AM250786 Corp | B7: MRV ENGENHARIA PARTICIP | C7: 2/15/2022 | D7: BRAZIL IPCA+SPREAD | E7: MRVE3 BZ | F7: Home Builders | G7: 43069 | H7: 43069 | I7: -3.713912 | J7: 11.28 | K7: 1.37226 | L7: 3.2681 | M7: 1.64 | N7: -8.73 | O7: 6.7083834 | P7: 5.4950716 | Q7: 14.055061 | R7: 4.1984127 | S7: 4.0691199
A8: AM250786 Corp | B8: MRV ENGENHARIA PARTICIP | C8: 2/15/2022 | D8: BRAZIL IPCA+SPREAD | E8: MRVE3 BZ | F8: Home Builders | G8: 43098 | H8: 43100 | I8: -3.4675158 | J8: 11.04 | K8: 1.431 | L8: 3.3125 | M8: 2.58 | N8: -7.77 | O8: 6.7083834 | P8: 5.4950716 | Q8: 14.055061 | R8: 4.1190476 | S8: 4.0931516
A9: AM250786 Corp | B9: MRV ENGENHARIA PARTICIP | C9: 2/15/2022 | D9: BRAZIL IPCA+SPREAD | E9: MRVE3 BZ | F9: Home Builders | G9: 43131 | H9: 43131 | I9: -3.5197495 | J9: 13.54 | K9: 1.5255 | L9: 3.1875 | M9: 2.58 | N9: -7.77 | O9: 5.4878378 | P9: 5.5563898 | Q9: 17.764548 | R9: 4.031746 | S9: 4.1161373
A10: AM250786 Corp | B10: MRV ENGENHARIA PARTICIP | C10: 2/15/2022 | D10: BRAZIL IPCA+SPREAD | E10: MRVE3 BZ | F10: Home Builders | G10: 43159 | H10: 43159 | I10: -3.5223998 | J10: 19.85 | K10: 1.613 | L10: 3.2475 | M10: 2.58 | N10: -7.77 | O10: 5.4878378 | P10: 5.5563898 | Q10: 17.764548 | R10: 3.9603175 | S10: 4.1322249
A11: AM250786 Corp | B11: MRV ENGENHARIA PARTICIP | C11: 2/15/2022 | D11: BRAZIL IPCA+SPREAD | E11: MRVE3 BZ | F11: Home Builders | G11: 43189 | H11: 43190 | I11: -3.4460002 | J11: 19.97 | K11: 1.723 | L11: 3.3063 | M11: 1.9 | N11: -7.3 | O11: 5.4878378 | P11: 5.5563898 | Q11: 17.764548 | R11: 3.8730159 | S11: 4.1485247
A12: AM250786 Corp | B12: MRV ENGENHARIA PARTICIP | C12: 2/15/2022 | D12: BRAZIL IPCA+SPREAD | E12: MRVE3 BZ | F12: Home Builders | G12: 43220 | H12: 43220 | I12: -3.3745002 | J12: 15.93 | K12: 1.833 | L12: 3.5063 | M12: 1.9 | N12: -7.3 | O12: 11.697276 | P12: 5.6549899 | Q12: 15.823253 | R12: 3.7936508 | S12: 4.1600957
A13: AM250786 Corp | B13: MRV ENGENHARIA PARTICIP | C13: 2/15/2022 | D13: BRAZIL IPCA+SPREAD | E13: MRVE3 BZ | F13: Home Builders | G13: 43251 | H13: 43251 | I13: -3.1892001 | J13: 15.43 | K13: 1.886 | L13: 3.7239 | M13: 1.9 | N13: -7.3 | O13: 11.697276 | P13: 5.6549899 | Q13: 15.823253 | R13: 3.7063492 | S13: 4.1692082
... A4230: ZQ942599 Corp | B4230: CONTEINERES VILA CONDE | C4230: 11/15/2031 | D4230: BRAZIL IPCA+SPREAD | E4230: STBP3 BZ | F4230: Transportation | G4230: 45838 | H4230: 45838 | I4230: -0.8235568 | J4230: 16.73 | K4230: 4.28217 | L4230: 5.4316 | M4230: 2.85 | N4230: -7.3 | O4230: 71.93088 | P4230: 10.870509 | Q4230: 9.3537415 | R4230: 6.3531746 | S4230: 2.3960225

Sheet Sheet1
A2: max | B2: =MAX(B6:B108) -> 132
A3: min | B3: =MIN(B6:B108) -> 1
A4: avg | B4: =AVERAGE(B6:B108) -> 41.058252
A5: bond | B5: count if
A6: AM250786 Corp | B6: =COUNTIF(ts!$A:$A,Sheet1!A6) -> 50
A7: AM934900 Corp | B7: =COUNTIF(ts!$A:$A,Sheet1!A7) -> 87
A8: AN275276 Corp | B8: =COUNTIF(ts!$A:$A,Sheet1!A8) -> 74
A9: AP304401 Corp | B9: =COUNTIF(ts!$A:$A,Sheet1!A9) -> 70
A10: AQ373215 Corp | B10: =COUNTIF(ts!$A:$A,Sheet1!A10) -> 74
A11: BG015275 Corp | B11: =COUNTIF(ts!$A:$A,Sheet1!A11) -> 48
A12: BK296481 Corp | B12: =COUNTIF(ts!$A:$A,Sheet1!A12) -> 55
A13: BQ418507 Corp | B13: =COUNTIF(ts!$A:$A,Sheet1!A13) -> 48
A14: BQ418645 Corp | B14: =COUNTIF(ts!$A:$A,Sheet1!A14) -> 48
A15: BQ883112 Corp | B15: =COUNTIF(ts!$A:$A,Sheet1!A15) -> 44
A16: BR877654 Corp | B16: =COUNTIF(ts!$A:$A,Sheet1!A16) -> 42
A17: BS068433 Corp | B17: =COUNTIF(ts!$A:$A,Sheet1!A17) -> 42
... A108: ZQ942599 Corp | B108: =COUNTIF(ts!$A:$A,Sheet1!A108) -> 55
